Workbook
Name articulo: listas!$K$2:$K$6
Name comercial: listas!$I$2:$I$6
Name CONOCIMIENTO: 'tarea uno'!$I$5:$I$6
Name datos: tabladatos2[#All]
Name IINVREAL: SUMAR.SI!$K$4:$K$103
Name INTENCION: 'tarea uno'!$E$5:$E$7
Name Inversión: 'tarea uno'!$H$5:$H$6
Name INVEXP: SUMAR.SI!$J$4:$J$103
Name INVREAL: SUMAR.SI!$J$4:$J$103
Name INVREAL16: SUMAR.SI!$M$4:$M$103
Name INVREAL17: SUMAR.SI!$L$4:$L$103
Name marca: listas!$J$2:$J$6
Name NativeTimeline_FECHA: #N/A
Name SECTOR: SUMAR.SI!$D$4:$D$103
Name SegmentaciónDeDatos_Calificación_Proyectos__1_10: #N/A
Name SegmentaciónDeDatos_COMERCIAL: #N/A
Name SegmentaciónDeDatos_MARCA: #N/A
Name SegmentaciónDeDatos_País_de_orígen: #N/A
Name Trabajo: 'tarea uno'!$G$5:$G$6

Sheet tarea uno
A1: Formato de inscripción
A2: Nombre | B2: Felipe Guzmán
A3: Correo | B3: felipeguzmanbotero@gmail.com | E3: Nivel 1 | G3: Nivel 2
A4: Monto que desea invertir | B4: 10000000 | E4: Intención | G4: Trabajo | H4: Inversión | I4: Conocimiento
A5: Días que se quedará en el país | B5: 2 | E5: Trabajo | G5: Buscando trabajo | H5: Socio de proyecto | I5: Académico
A6: Sector de interés | B6: Tecnología | E6: Inversión | G6: Ofreciendo trabajo | H6: Socio capitalista | I6: Otro tipo
A7: Intención frente a los proyectos | B7: Conocimiento | E7: Conocimiento
A8: Detalle inversión | B8: Otro tipo
A9: Conoce algún proyecto o no | B9: No
A10: País de orígen | B10: Colombia
A12: QUE SE APRENDIO: PARA LAS LISTAS SE LE TIENE QUE PONER EN DATOS, Y DESPUES A VALIDACION PARA PONER EN LISTA Y DESPUES ESPECIFICAR LAS CELDAS. Para hacer LISTAS ENLAZADAS TENEMOS QUE PONERLE EN VALIDACION DE DATOS>LISTAS>Y PONER LA FORMULA =INDIRECTO(LA CELDA DONDE SE COLOCO LA OTRA LISTA), para hacer eso debemos de nombrar el CONJUNTO DE CELDAS como esta en la primer lista para que se relacionen

Sheet UNION Y SEPARACION
B2: UNION | D2: formulas =concatenar y selecconar las celdas =celda&celda
B3: Luis | C3: Silva
B5: =+B3&C3 -> Luis Silva | C5: =CONCATENATE(B3,C3) -> Luis Silva
B6: =B3&" "&C3 -> Luis Silva
B10: SEPARAR | D10: SEPARACION FIJA, ESTA SE LE DA EN DATOS>SEPARACION POR COLUMNA >SEPARACION POR PUNTO FIJO
B11: 0001,Curso Platzi,2018 | D11: 1 | E11: , | F11: Curso Platzi | G11: , | H11: 2018
B12: 0001,Curso Platzi,2018 | D12: 1 | E12: , | F12: Curso Platzi | G12: , | H12: 2018
B13: 0001,Curso Platzi,2018 | D13: 1 | E13: , | F13: Curso Platzi | G13: , | H13: 2018
B14: 0001,Curso Platzi,2018 | D14: 1 | E14: , | F14: Curso Platzi | G14: , | H14: 2018
B15: 0001,Curso Platzi,2018 | D15: 1 | E15: , | F15: Curso Platzi | G15: , | H15: 2018
B18: SEPARAR | D18: SEPARACION DELIMITADA ESTA SE LE DA EN DATOS>SEPARACION POR COLUMNA >SEPARACION DELIMITADA
B19: 1 | C19: Curso Platzi | D19: 2018
B20: 1 | C20: Curso Platzi | D20: 2018
B21: 1 | C21: Curso Platzi | D21: 2018
B22: 1 | C22: Curso Platzi | D22: 2018
B23: 1 | C23: Curso Platzi | D23: 2018
B25: SEPARAR
B26: Nombre | C26: Monto que desea invertir | D26: Días que se quedará en el país | E26: Sector | F26: Intención frente a los proyectos | G26: Detalle inversión | H26: Conoce algún proyecto o no | I26: País de orígen
B27: VALENTINA | C27: 50000000 | D27: 1 | E27: Construcción | F27: Inversión | G27: Socio capitalista | H27: NO | I27: COLOMBIA
B28: GUILLERMO | C28: 10000000 | D28: 1 | E28: Agroindustrial | F28: Inversión | G28: Socio capitalista | H28: NO | I28: COLOMBIA
B29: JOSEP | C29: 0 | D29: 4 | E29: Construcción | F29: Trabajo | G29: Buscando trabajo | H29: NO | I29: COLOMBIA
B30: FERNANDO | C30: 0 | D30: Más de 5 | E30: Tecnología | F30: Trabajo | G30: Buscando trabajo | H30: NO | I30: COLOMBIA
B31: CHRISTIAN | C31: 0 | D31: 1 | E31: Construcción | F31: Trabajo | G31: Ofreciendo trabajo | H31: NO | I31: COLOMBIA
B32: ALBERTO | C32: 0 | D32: 3 | E32: Sector Real | F32: Trabajo | G32: Ofreciendo trabajo | H32: NO | I32: COLOMBIA
B33: NORA | C33: 1000000 | D33: 1 | E33: Sector Real | F33: Inversión | G33: Socio de proyecto | H33: NO | I33: CHILE
B34: MIGUEL | C34: 1000000 | D34: 2 | E34: Tecnología | F34: Inversión | G34: Socio capitalista | H34: SI | I34: COLOMBIA
B35: RAUL | C35: 0 | D35: 2 | E35: Tecnología | F35: Trabajo | G35: Ofreciendo trabajo | H35: SI | I35: BRASIL
B36: ADOLFO | C36: 0 | D36: Más de 5 | E36: Sector Real | F36: Trabajo | G36: Ofreciendo trabajo | H36: NO | I36: COLOMBIA
B37: EDUARDO | C37: 0 | D37: 2 | E37: Tecnología | F37: Trabajo | G37: Buscando trabajo | H37: SI | I37: COLOMBIA
B38: ISAAC | C38: 90000000 | D38: Más de 5 | E38: Tecnología | F38: Inversión | G38: Socio capitalista | H38: NO | I38: COLOMBIA
B39: ANTONIO | C39: 1000000 | D39: 2 | E39: Construcción | F39: Inversión | G39: Socio de proyecto | H39: NO | I39: COLOMBIA
B40: RUBEN | C40: 10000000 | D40: 4 | E40: Tecnología | F40: Inversión | G40: Socio capitalista | H40: SI | I40: COLOMBIA
B41: RICARDO | C41: 10000000 | D41: Más de 5 | E41: Sector Real | F41: Inversión | G41: Socio capitalista | H41: NO | I41: COLOMBIA
B42: FRANCISCO | C42: 1000000 | D42: 1 | E42: Tecnología | F42: Inversión | G42: Socio de proyecto | H42: SI | I42: COLOMBIA
B43: MARTIN | C43: 0 | D43: 2 | E43: Tecnología | F43: Trabajo | G43: Buscando trabajo | H43: SI | I43: COLOMBIA
B44: ANDRÉS | C44: 1000000 | D44: 1 | E44: Tecnología | F44: Inversión | G44: Socio capitalista | H44: NO | I44: COLOMBIA
B45: JUAN PABLO | C45: 1000000 | D45: Más de 5 | E45: Tecnología | F45: Inversión | G45: Socio de proyecto | H45: SI | I45: COLOMBIA
B46: ROBERTO | C46: 10000000 | D46: 1 | E46: Tecnología | F46: Inversión | G46: Socio de proyecto | H46: SI | I46: COLOMBIA
B47: EMILIO | C47: 0 | D47: Más de 5 | E47: Sector Real | F47: Trabajo | G47: Buscando trabajo | H47: NO | I47: COLOMBIA
B48: LEONEL | C48: 20000000 | D48: 2 | E48: Sector Real | F48: Inversión | G48: Socio capitalista | H48: NO | I48: COLOMBIA
B49: JOAN | C49: 0 | D49: Más de 5 | E49: Tecnología | F49: Trabajo | G49: Ofreciendo trabajo | H49: NO | I49: COLOMBIA
B50: SERGIO | C50: 5000000 | D50: 4 | E50: Sector Real | F50: Inversión | G50: Socio de proyecto | H50: SI | I50: BRASIL
B51: EUGENIO | C51: 20000000 | D51: 2 | E51: Construcción | F51: Inversión | G51: Socio de proyecto | H51: NO | I51: COLOMBIA
B52: SEBASTIAN | C52: 50000000 | D52: 2 | E52: Tecnología | F52: Inversión | G52: Socio capitalista | H52: NO | I52: COLOMBIA
B53: SAMUEL | C53: 30000000 | D53: Más de 5 | E53: Sector Real | F53: Inversión | G53: Socio de proyecto | H53: NO | I53: COLOMBIA
B54: ENRIQUE | C54: 5000000 | D54: 1 | E54: Tecnología | F54: Inversión | G54: Socio capitalista | H54: NO | I54: COLOMBIA
B55: DIEGO | C55: 10000000 | D55: Más de 5 | E55: Tecnología | F55: Inversión | G55: Socio de proyecto | H55: NO | I55: COLOMBIA
B56: PEDRO | C56: 0 | D56: 1 | E56: Educación | F56: Conocimiento | G56: Académico | H56: NO | I56: CHILE
B57: ALBERT | C57: 0 | D57: 2 | E57: Educación | F57: Conocimiento | G57: Académico | H57: NO | I57: COLOMBIA
B58: JORGE | C58: 5000000 | D58: 3 | E58: Tecnología | F58: Inversión | G58: Socio capitalista | H58: NO | I58: CHILE
B59: RAMON | C59: 0 | D59: 1 | E59: Agroindustrial | F59: Trabajo | G59: Buscando trabajo | H59: NO | I59: COLOMBIA
B60: HUGO | C60: 10000000 | D60: 2 | E60: Tecnología | F60: Inversión | G60: Socio de proyecto | H60: NO | I60: COLOMBIA
B61: MARIA | C61: 1000000 | D61: 1 | E61: Sector Real | F61: Inversión | G61: Socio capitalista | H61: NO | I61: COLOMBIA
B62: FELIX | C62: 10000000 | D62: Más de 5 | E62: Tecnología | F62: Inversión | G62: Socio de proyecto | H62: NO | I62: COLOMBIA
B63: VICTOR | C63: 0 | D63: 1 | E63: Tecnología | F63: Trabajo | G63: Buscando trabajo | H63: SI | I63: COLOMBIA
B64: JORDI | C64: 0 | D64: 1 | E64: Educación | F64: Conocimiento | G64: Académico | H64: NO | I64: COLOMBIA
B65: MARIA MÓNICA | C65: 0 | D65: 2 | E65: Tecnología | F65: Trabajo | G65: Buscando trabajo | H65: NO | I65: COLOMBIA
B66: CRISTOBAL | C66: 0 | D66: 1 | E66: Tecnología | F66: Trabajo | G66: Buscando trabajo | H66: SI | I66: COLOMBIA
B67: NICOLAS | C67: 10000000 | D67: Más de 5 | E67: Sector Real | F67: Inversión | G67: Socio capitalista | H67: NO | I67: COLOMBIA
B68: FELIPE | C68: 0 | D68: 1 | E68: Sector Real | F68: Trabajo | G68: Buscando trabajo | H68: SI | I68: BRASIL
B69: ISMAEL | C69: 30000000 | D69: 2 | E69: Tecnología | F69: Inversión | G69: Socio de proyecto | H69: NO | I69: BRASIL
B70: ALEJANDRO | C70: 1000000 | D70: 4 | E70: Tecnología | F70: Inversión | G70: Socio capitalista | H70: SI | I70: COLOMBIA
B71: MATEO | C71: 0 | D71: Más de 5 | E71: Tecnología | F71: Trabajo | G71: Buscando trabajo | H71: NO | I71: URUGUAY
B72: CRISTIAN | C72: 0 | D72: Más de 5 | E72: Tecnología | F72: Trabajo | G72: Buscando trabajo | H72: NO | I72: COLOMBIA
B73: DAVID | C73: 0 | D73: 1 | E73: Tecnología | F73: Trabajo | G73: Ofreciendo trabajo | H73: NO | I73: COLOMBIA
B74: SALVADOR | C74: 10000000 | D74: 2 | E74: Tecnología | F74: Inversión | G74: Socio de proyecto | H74: NO | I74: COLOMBIA
B75: ALFREDO | C75: 0 | D75: 2 | E75: Tecnología | F75: Trabajo | G75: Buscando trabajo | H75: SI | I75: PARAGUAY
B76: OSCAR | C76: 30000000 | D76: 2 | E76: Tecnología | F76: Inversión | G76: Socio de proyecto | H76: SI | I76: BRASIL
B77: JUAN | C77: 0 | D77: 1 | E77: Tecnología | F77: Conocimiento | G77: Otro tipo | H77: NO | I77: COLOMBIA
B78: IVAN | C78: 30000000 | D78: 2 | E78: Tecnología | F78: Inversión | G78: Socio de proyecto | H78: NO | I78: COLOMBIA
B79: ALEXANDER | C79: 50000000 | D79: 1 | E79: Construcción | F79: Inversión | G79: Socio capitalista | H79: SI | I79: COLOMBIA
B80: JAIME | C80: 10000000 | D80: 1 | E80: Tecnología | F80: Inversión | G80: Socio capitalista | H80: NO | I80: COLOMBIA
B81: HECTOR | C81: 30000000 | D81: Más de 5 | E81: Tecnología | F81: Inversión | G81: Socio de proyecto | H81: NO | I81: COLOMBIA
B82: ERNESTO | C82: 90000000 | D82: 1 | E82: Tecnología | F82: Inversión | G82: Socio de proyecto | H82: NO | I82: COLOMBIA
B83: MARCO | C83: 0 | D83: Más de 5 | E83: Tecnología | F83: Conocimiento | G83: Otro tipo | H83: NO | I83: PERU
B84: JAVIER | C84: 100000000 | D84: 3 | E84: Tecnología | F84: Inversión | G84: Socio capitalista | H84: NO | I84: BOLIVIA
B85: ESTEBAN | C85: 100000000 | D85: Más de 5 | E85: Tecnología | F85: Inversión | G85: Socio capitalista | H85: NO | I85: COLOMBIA
B86: MARCOS | C86: 0 | D86: 1 | E86: Sector Real | F86: Trabajo | G86: Buscando trabajo | H86: SI | I86: BRASIL
B87: ADRIAN | C87: 0 | D87: 2 | E87: Tecnología | F87: Trabajo | G87: Ofreciendo trabajo | H87: NO | I87: COLOMBIA
B88: DANIEL | C88: 1000000 | D88: 2 | E88: Tecnología | F88: Inversión | G88: Socio de proyecto | H88: NO | I88: COLOMBIA
B89: GREGORIO | C89: 20000000 | D89: 3 | E89: Agroindustrial | F89: Inversión | G89: Socio de proyecto | H89: SI | I89: COLOMBIA
B90: BORJA | C90: 50000000 | D90: 4 | E90: Tecnología | F90: Inversión | G90: Socio capitalista | H90: NO | I90: ECUADOR
B91: PABLO | C91: 0 | D91: Más de 5 | E91: Agroindustrial | F91: Inversión | G91: Socio capitalista | H91: SI | I91: COLOMBIA
B92: JOAQUIN | C92: 10000000 | D92: 4 | E92: Tecnología | F92: Inversión | G92: Socio capitalista | H92: SI | I92: COLOMBIA
B93: RODRIGO | C93: 0 | D93: 1 | E93: Sector Real | F93: Trabajo | G93: Buscando trabajo | H93: SI | I93: COLOMBIA
B94: AGUSTIN | C94: 10000000 | D94: 3 | E94: Tecnología | F94: Inversión | G94: Socio de proyecto | H94: NO | I94: COLOMBIA
B95: MANUEL | C95: 0 | D95: Más de 5 | E95: Sector Real | F95: Trabajo | G95: Ofreciendo trabajo | H95: NO | I95: ARGENTINA
B96: LORENZO | C96: 20000000 | D96: Más de 5 | E96: Agroindustrial | F96: Inversión | G96: Socio capitalista | H96: NO | I96: COLOMBIA
B97: SANTIAGO | C97: 100000000 | D97: 2 | E97: Tecnología | F97: Inversión | G97: Socio capitalista | H97: NO | I97: CHILE
B98: JONATHAN | C98: 0 | D98: 3 | E98: Educación | F98: Conocimiento | G98: Académico | H98: NO | I98: COLOMBIA
B99: CARLOS | C99: 1000000 | D99: 2 | E99: Tecnología | F99: Inversión | G99: Socio de proyecto | H99: NO | I99: COLOMBIA
B100: VICENTE | C100: 0 | D100: 3 | E100: Agroindustrial | F100: Trabajo | G100: Ofreciendo trabajo | H100: SI | I100: COLOMBIA
B101: ALVARO | C101: 10000000 | D101: 4 | E101: Sector Real | F101: Inversión | G101: Socio de proyecto | H101: NO | I101: COLOMBIA
B102: MARIO | C102: 10000000 | D102: Más de 5 | E102: Tecnología | F102: Inversión | G102: Socio capitalista | H102: NO | I102: COLOMBIA
B103: RAFAEL | C103: 10000000 | D103: 1 | E103: Sector Real | F103: Inversión | G103: Socio capitalista | H103: SI | I103: COLOMBIA
B104: ALEX | C104: 20000000 | D104: 1 | E104: Tecnología | F104: Inversión | G104: Socio capitalista | H104: NO | I104: URUGUAY
B105: IGNACIO | C105: 0 | D105: Más de 5 | E105: Tecnología | F105: Trabajo | G105: Buscando trabajo | H105: NO | I105: COLOMBIA
B106: GONZALO | C106: 30000000 | D106: Más de 5 | E106: Tecnología | F106: Inversión | G106: Socio capitalista | H106: NO | I106: COLOMBIA
B107: JESUS | C107: 0 | D107: Más de 5 | E107: Educación | F107: Conocimiento | G107: Académico | H107: NO | I107: OTRO PAÍS DEL MUNDO
B108: ALFONSO | C108: 10000000 | D108: 2 | E108: Tecnología | F108: Inversión | G108: Socio de proyecto | H108: SI | I108: COLOMBIA
...

Sheet SUM PROM Y REDONDEO
A1: Nombre | B1: País de orígen | C1: Sector | D1: Intención frente a los proyectos | E1: Detalle inversión | F1: Conoce algún proyecto o no | G1: Expectativa inversión 2018 | H1: Inversión real 2018 | I1: Inversión real 2017 | J1: Inversión real 2016 | K1: suma manuak | L1: formula | M1: promedio | N1: REDONDEO | O1: SUMAR.SI | P1: =SUM(G3:J101) -> 12768082553 | R1: Rutina de trabajo
A2: ALBERT | B2: COLOMBIA | C2: OTRO | D2: Conocimiento | E2: Académico | F2: NO | G2: 0 | H2: 0 | I2: 96781441 | J2: 47643060 | K2: =H2+I2+J2 -> 144424501 | L2: =SUM(G2:J2) -> 144424501 | M2: =AVERAGE(G2:J2) -> 36106125 | N2: =ROUND(AVERAGE(G2:J2),0) -> 36106125 | O2: =SUMIF(C2:C101,"Tecnología",G2:J101) -> 1069000000 | R2: Sumar la inversión total (manual y fórmula). Sumar al final cada año. Formas de arrastrar.
A3: JOAQUIN | B3: COLOMBIA | C3: Tecnología | D3: Inversión | E3: Socio capitalista | F3: SI | G3: 10000000 | H3: 40848959 | I3: 92963332 | J3: 47565587 | K3: =H3+I3+J3 -> 181377878 | L3: =SUM(G3:J3) -> 191377878 | M3: =AVERAGE(G3:J3) -> 47844470 | N3: =ROUND(AVERAGE(G3:J3),0) -> 47844470 | O3: =SUMIF(C3:C102,"Construcción",G3:J102) -> 211000000 | R3: Operaciones básicas (0 , X, /)
A4: CESAR | B4: COLOMBIA | C4: Construcción | D4: Trabajo | E4: Ofreciendo trabajo | F4: NO | G4: 0 | H4: 0 | I4: 49599457 | J4: 0 | K4: =H4+I4+J4 -> 49599457 | L4: =SUM(G4:J4) -> 49599457 | M4: =AVERAGE(G4:J4) -> 12399864 | N4: =ROUND(AVERAGE(G4:J4),0) -> 12399864 | O4: =SUMIF(C2:C101,"Agroindustrial",G2:J101) -> 50000000 | R4: Sacar promedio de inversión por año (manual y en fórmula)
A5: HUGO | B5: COLOMBIA | C5: Tecnología | D5: Inversión | E5: Socio de proyecto | F5: NO | G5: 10000000 | H5: 78308880 | I5: 3248026 | J5: 27143270 | K5: =H5+I5+J5 -> 108700176 | L5: =SUM(G5:J5) -> 118700176 | M5: =AVERAGE(G5:J5) -> 29675044 | N5: =ROUND(AVERAGE(G5:J5),0) -> 29675044 | R5: Redondear el promedio sin decimales (aparte y después en la fórmula de promedio por año)
A6: VALENTINA | B6: COLOMBIA | C6: Construcción | D6: Inversión | E6: Socio capitalista | F6: NO | G6: 50000000 | H6: 2910571 | I6: 37561085 | J6: 19598007 | K6: =H6+I6+J6 -> 60069663 | L6: =SUM(G6:J6) -> 110069663 | M6: =AVERAGE(G6:J6) -> 27517416 | N6: =ROUND(AVERAGE(G6:J6),0) -> 27517416 | R6: Buscar a ANDRES
A7: GERMAN | B7: COLOMBIA | C7: Tecnología | D7: Inversión | E7: Socio de proyecto | F7: NO | G7: 90000000 | H7: 50075523 | I7: 59142617 | J7: 95314026 | K7: =H7+I7+J7 -> 204532166 | L7: =SUM(G7:J7) -> 294532166 | M7: =AVERAGE(G7:J7) -> 73633042 | N7: =ROUND(AVERAGE(G7:J7),0) -> 73633042 | R7: Reemplazar a ANDRES por Andrés. Remplazar a todos los de construcción por infraestructura.
A8: DAVID | B8: COLOMBIA | C8: Tecnología | D8: Trabajo | E8: Ofreciendo trabajo | F8: NO | G8: 0 | H8: 0 | I8: 0 | J8: 67714973 | K8: =H8+I8+J8 -> 67714973 | L8: =SUM(G8:J8) -> 67714973 | M8: =AVERAGE(G8:J8) -> 16928743 | N8: =ROUND(AVERAGE(G8:J8),0) -> 16928743 | R8: Reto 4 tarea: Encontrar una formula que sume toda la inversión hecha en el sector tecnología en el 2018
A9: MIGUEL | B9: COLOMBIA | C9: Tecnología | D9: Inversión | E9: Socio capitalista | F9: SI | G9: 1000000 | H9: 5305190 | I9: 53291805 | J9: 84809282 | K9: =H9+I9+J9 -> 143406277 | L9: =SUM(G9:J9) -> 144406277 | M9: =AVERAGE(G9:J9) -> 36101569 | N9: =ROUND(AVERAGE(G9:J9),0) -> 36101569
A10: VICENTE | B10: COLOMBIA | C10: Agroindustrial | D10: Trabajo | E10: Ofreciendo trabajo | F10: SI | G10: 0 | H10: 0 | I10: 50085574 | J10: 42495353 | K10: =H10+I10+J10 -> 92580927 | L10: =SUM(G10:J10) -> 92580927 | M10: =AVERAGE(G10:J10) -> 23145232 | N10: =ROUND(AVERAGE(G10:J10),0) -> 23145232 | R10: Fórmulas de texto
A11: ALVARO | B11: COLOMBIA | C11: Sector Real | D11: Inversión | E11: Socio de proyecto | F11: NO | G11: 10000000 | H11: 38941670 | I11: 67846781 | J11: 87726693 | K11: =H11+I11+J11 -> 194515144 | L11: =SUM(G11:J11) -> 204515144 | M11: =AVERAGE(G11:J11) -> 51128786 | N11: =ROUND(AVERAGE(G11:J11),0) -> 51128786 | R11: Bonus 0 fórmulas de texto: mayúscula | S11: =UPPER(R11) -> BONUS 0 FÓRMULAS DE TEXTO: MAYÚSCULA
A12: LUIS | B12: VENEZUELA | C12: Tecnología | D12: Inversión | E12: Socio de proyecto | F12: NO | G12: 1000000 | H12: 28926771 | I12: 56939610 | J12: 92726884 | K12: =H12+I12+J12 -> 178593265 | L12: =SUM(G12:J12) -> 179593265 | M12: =AVERAGE(G12:J12) -> 44898316 | N12: =ROUND(AVERAGE(G12:J12),0) -> 44898316 | R12: Bonus 0 fórmulas de texto: minúscula | S12: =LOWER(R12) -> bonus 0 fórmulas de texto: minúscula
A13: DANIEL | B13: COLOMBIA | C13: Tecnología | D13: Inversión | E13: Socio de proyecto | F13: NO | G13: 1000000 | H13: 34252074 | I13: 0 | J13: 22994819 | K13: =H13+I13+J13 -> 57246893 | L13: =SUM(G13:J13) -> 58246893 | M13: =AVERAGE(G13:J13) -> 14561723 | N13: =ROUND(AVERAGE(G13:J13),0) -> 14561723 | R13: Bonus 0 fórmulas de texto: qué día es hoy | S13: =TODAY() -> 46116
A14: JOSEP | B14: COLOMBIA | C14: Construcción | D14: Trabajo | E14: Buscando trabajo | F14: NO | G14: 0 | H14: 0 | I14: 45347826 | J14: 14301768 | K14: =H14+I14+J14 -> 59649594 | L14: =SUM(G14:J14) -> 59649594 | M14: =AVERAGE(G14:J14) -> 14912398 | N14: =ROUND(AVERAGE(G14:J14),0) -> 14912399
A15: EDUARDO | B15: COLOMBIA | C15: Tecnología | D15: Trabajo | E15: Buscando trabajo | F15: SI | G15: 0 | H15: 0 | I15: 71453938 | J15: 38593802 | K15: =H15+I15+J15 -> 110047740 | L15: =SUM(G15:J15) -> 110047740 | M15: =AVERAGE(G15:J15) -> 27511935 | N15: =ROUND(AVERAGE(G15:J15),0) -> 27511935 | R15: BONUS
A16: LEONEL | B16: COLOMBIA | C16: Sector Real | D16: Inversión | E16: Socio capitalista | F16: NO | G16: 20000000 | H16: 32346156 | I16: 22346275 | J16: 73743047 | K16: =H16+I16+J16 -> 128435478 | L16: =SUM(G16:J16) -> 148435478 | M16: =AVERAGE(G16:J16) -> 37108870 | N16: =ROUND(AVERAGE(G16:J16),0) -> 37108870 | R16: Sumar días a una fecha | S16: 45918 | T16: =TODAY()-S16 -> 198
A17: JORDI | B17: COLOMBIA | C17: Educación | D17: Conocimiento | E17: Académico | F17: NO | G17: 0 | H17: 0 | I17: 96357193 | J17: 67901582 | K17: =H17+I17+J17 -> 164258775 | L17: =SUM(G17:J17) -> 164258775 | M17: =AVERAGE(G17:J17) -> 41064694 | N17: =ROUND(AVERAGE(G17:J17),0) -> 41064694 | R17: Restar fechas
A18: ESTEBAN | B18: COLOMBIA | C18: Tecnología | D18: Inversión | E18: Socio capitalista | F18: NO | G18: 100000000 | H18: 72903049 | I18: 67375493 | J18: 4753995 | K18: =H18+I18+J18 -> 145032537 | L18: =SUM(G18:J18) -> 245032537 | M18: =AVERAGE(G18:J18) -> 61258134 | N18: =ROUND(AVERAGE(G18:J18),0) -> 61258134
A19: JONATHAN | B19: COLOMBIA | C19: Educación | D19: Conocimiento | E19: Académico | F19: NO | G19: 0 | H19: 0 | I19: 80671052 | J19: 58339670 | K19: =H19+I19+J19 -> 139010722 | L19: =SUM(G19:J19) -> 139010722 | M19: =AVERAGE(G19:J19) -> 34752680 | N19: =ROUND(AVERAGE(G19:J19),0) -> 34752681
A20: ANDRES | B20: BRASIL | C20: Sector Real | D20: Trabajo | E20: Buscando trabajo | F20: SI | G20: 0 | H20: 0 | I20: 0 | J20: 44898366 | K20: =H20+I20+J20 -> 44898366 | L20: =SUM(G20:J20) -> 44898366 | M20: =AVERAGE(G20:J20) -> 11224592 | N20: =ROUND(AVERAGE(G20:J20),0) -> 11224592
A21: JOSE | B21: COLOMBIA | C21: Tecnología | D21: Inversión | E21: Socio de proyecto | F21: NO | G21: 1000000 | H21: 96696256 | I21: 62106884 | J21: 85228190 | K21: =H21+I21+J21 -> 244031330 | L21: =SUM(G21:J21) -> 245031330 | M21: =AVERAGE(G21:J21) -> 61257832 | N21: =ROUND(AVERAGE(G21:J21),0) -> 61257833
A22: FELIX | B22: COLOMBIA | C22: Tecnología | D22: Inversión | E22: Socio de proyecto | F22: NO | G22: 10000000 | H22: 51531809 | I22: 99819688 | J22: 24233431 | K22: =H22+I22+J22 -> 175584928 | L22: =SUM(G22:J22) -> 185584928 | M22: =AVERAGE(G22:J22) -> 46396232 | N22: =ROUND(AVERAGE(G22:J22),0) -> 46396232
A23: PABLO | B23: COLOMBIA | C23: Agroindustrial | D23: Inversión | E23: Socio capitalista | F23: SI | G23: 0 | H23: 0 | I23: 34214902 | J23: 24896611 | K23: =H23+I23+J23 -> 59111513 | L23: =SUM(G23:J23) -> 59111513 | M23: =AVERAGE(G23:J23) -> 14777878 | N23: =ROUND(AVERAGE(G23:J23),0) -> 14777878
A24: MANUEL | B24: ARGENTINA | C24: Sector Real | D24: Trabajo | E24: Ofreciendo trabajo | F24: NO | G24: 0 | H24: 0 | I24: 7121108 | J24: 6991703 | K24: =H24+I24+J24 -> 14112811 | L24: =SUM(G24:J24) -> 14112811 | M24: =AVERAGE(G24:J24) -> 3528202.8 | N24: =ROUND(AVERAGE(G24:J24),0) -> 3528203
A25: LORENZO | B25: COLOMBIA | C25: Agroindustrial | D25: Inversión | E25: Socio capitalista | F25: NO | G25: 20000000 | H25: 93037614 | I25: 48185946 | J25: 75039300 | K25: =H25+I25+J25 -> 216262860 | L25: =SUM(G25:J25) -> 236262860 | M25: =AVERAGE(G25:J25) -> 59065715 | N25: =ROUND(AVERAGE(G25:J25),0) -> 59065715
A26: ISAAC | B26: COLOMBIA | C26: Tecnología | D26: Inversión | E26: Socio capitalista | F26: NO | G26: 90000000 | H26: 62088180 | I26: 18047519 | J26: 3738158 | K26: =H26+I26+J26 -> 83873857 | L26: =SUM(G26:J26) -> 173873857 | M26: =AVERAGE(G26:J26) -> 43468464 | N26: =ROUND(AVERAGE(G26:J26),0) -> 43468464
A27: MARIA | B27: COLOMBIA | C27: Sector Real | D27: Inversión | E27: Socio capitalista | F27: NO | G27: 1000000 | H27: 1160848 | I27: 32268145 | J27: 13339687 | K27: =H27+I27+J27 -> 46768680 | L27: =SUM(G27:J27) -> 47768680 | M27: =AVERAGE(G27:J27) -> 11942170 | N27: =ROUND(AVERAGE(G27:J27),0) -> 11942170
A28: ANGEL | B28: COLOMBIA | C28: Tecnología | D28: Trabajo | E28: Ofreciendo trabajo | F28: NO | G28: 0 | H28: 0 | I28: 21224611 | J28: 62562457 | K28: =H28+I28+J28 -> 83787068 | L28: =SUM(G28:J28) -> 83787068 | M28: =AVERAGE(G28:J28) -> 20946767 | N28: =ROUND(AVERAGE(G28:J28),0) -> 20946767
A29: ADOLFO | B29: COLOMBIA | C29: Sector Real | D29: Trabajo | E29: Ofreciendo trabajo | F29: NO | G29: 0 | H29: 0 | I29: 85434615 | J29: 79508333 | K29: =H29+I29+J29 -> 164942948 | L29: =SUM(G29:J29) -> 164942948 | M29: =AVERAGE(G29:J29) -> 41235737 | N29: =ROUND(AVERAGE(G29:J29),0) -> 41235737
... A101: ADRIAN | B101: COLOMBIA | C101: Tecnología | D101: Trabajo | E101: Ofreciendo trabajo | F101: NO | G101: 0 | H101: 0 | I101: 24965127 | J101: 41129782 | K101: =H101+I101+J101 -> 66094909 | L101: =SUM(G101:J101) -> 66094909 | M101: =AVERAGE(G101:J101) -> 16523727 | N101: =ROUND(AVERAGE(G101:J101),0) -> 16523727

Sheet SUMAR.SI
Q1: Reto clase anterior: Encontrar una formula que sume toda la inversión hecha en el sector tecnología en el 2018
B3: Nombre | C3: País de orígen | D3: Sector | E3: Intención frente a los proyectos | F3: Detalle inversión | G3: Conoce algún proyecto o no | H3: Calificación Feria (1010) | I3: Calificación Proyectos (1010) | J3: Expectativa inversión 2018 | K3: Inversión real 2018 | L3: Inversión real 2017 | M3: Inversión real 2016 | N3: var 201702016 | O3: VAR 201702018 | Q3: ¿Cuál es la inversión real 2018 de cada sector? | R3: Columna1 | S3: =sumar.si(RANGO DE DATOS, EL DATO O TEXTO, RANGO A SUMAR) | U3: ¿Cuál es la DIFERENCIA ENTRE inversión real Y EXPECTATIVA 2018 de cada sector? | V3: Columna1
B4: ALBERT | C4: COLOMBIA | D4: Educación | E4: Conocimiento | F4: Académico | G4: NO | H4: 3 | I4: 8 | J4: 0 | K4: 0 | L4: 96781441 | M4: 47643060 | N4: =(Tabla3[[#This Row],[Inversión real 2017]]-Tabla3[[#This Row],[Inversión real 2016]])/Tabla3[[#This Row],[Inversión real 2016]] -> 1.0313859 | O4: =(Tabla3[[#This Row],[Inversión real 2017]]-Tabla3[[#This Row],[Inversión real 2018]])/Tabla3[[#This Row],[Inversión real 2018]] -> #DIV/0! | Q4: Sector | R4: Inversión 2018 | U4: Sector | V4: Inversión 2018
B5: JOAQUIN | C5: COLOMBIA | D5: Tecnología | E5: Inversión | F5: Socio capitalista | G5: SI | H5: 8 | I5: 7 | J5: 10000000 | K5: 40848959 | L5: 92963332 | M5: 47565587 | N5: =(Tabla3[[#This Row],[Inversión real 2017]]-Tabla3[[#This Row],[Inversión real 2016]])/Tabla3[[#This Row],[Inversión real 2016]] -> 0.95442415 | O5: =(Tabla3[[#This Row],[Inversión real 2017]]-Tabla3[[#This Row],[Inversión real 2018]])/Tabla3[[#This Row],[Inversión real 2018]] -> 1.2757822 | Q5: Tecnología | R5: 2002341114 | S5: =SUMIF($D$4:$D$103,Q5,$K$4:$K$103) -> 2002341114 | U5: Tecnología | V5: =SUMIF($D$4:$D$103,U5,$K$4:$K$103)-SUMIF($D$4:$D$103,U5,$J$4:$J$103) -> 933341114
B6: CESAR | C6: COLOMBIA | D6: Construcción | E6: Trabajo | F6: Ofreciendo trabajo | G6: NO | H6: 5 | I6: 10 | J6: $ - | K6: $ - | L6: 49599457 | M6: $ - | N6: =(Tabla3[[#This Row],[Inversión real 2017]]-Tabla3[[#This Row],[Inversión real 2016]])/Tabla3[[#This Row],[Inversión real 2016]] -> #VALUE! | O6: =(Tabla3[[#This Row],[Inversión real 2017]]-Tabla3[[#This Row],[Inversión real 2018]])/Tabla3[[#This Row],[Inversión real 2018]] -> #VALUE! | Q6: Sector Real | R6: 535791961 | S6: =SUMIF($D$4:$D$103,Q6,$K$4:$K$103) -> 535791961 | U6: Sector Real | V6: =SUMIF($D$4:$D$103,U6,$K$4:$K$103)-SUMIF($D$4:$D$103,U6,$J$4:$J$103) -> 298791961
B7: HUGO | C7: COLOMBIA | D7: Tecnología | E7: Inversión | F7: Socio de proyecto | G7: NO | H7: 4 | I7: 8 | J7: 10000000 | K7: 78308880 | L7: 3248026 | M7: 27143270 | N7: =(Tabla3[[#This Row],[Inversión real 2017]]-Tabla3[[#This Row],[Inversión real 2016]])/Tabla3[[#This Row],[Inversión real 2016]] -> -0.8803377 | O7: =(Tabla3[[#This Row],[Inversión real 2017]]-Tabla3[[#This Row],[Inversión real 2018]])/Tabla3[[#This Row],[Inversión real 2018]] -> -0.95852289 | Q7: Agroindustrial | R7: 253232607 | S7: =SUMIF($D$4:$D$103,Q7,$K$4:$K$103) -> 253232607 | U7: Agroindustrial | V7: =SUMIF($D$4:$D$103,U7,$K$4:$K$103)-SUMIF($D$4:$D$103,U7,$J$4:$J$103) -> 203232607
B8: VALENTINA | C8: COLOMBIA | D8: Construcción | E8: Inversión | F8: Socio capitalista | G8: NO | H8: 4 | I8: 9 | J8: 50000000 | K8: 2910571 | L8: 37561085 | M8: 19598007 | N8: =(Tabla3[[#This Row],[Inversión real 2017]]-Tabla3[[#This Row],[Inversión real 2016]])/Tabla3[[#This Row],[Inversión real 2016]] -> 0.91657677 | O8: =(Tabla3[[#This Row],[Inversión real 2017]]-Tabla3[[#This Row],[Inversión real 2018]])/Tabla3[[#This Row],[Inversión real 2018]] -> 11.905057 | Q8: Construcción | R8: 187304900 | S8: =SUMIF($D$4:$D$103,Q8,$K$4:$K$103) -> 187304900 | U8: Construcción | V8: =SUMIF($D$4:$D$103,U8,$K$4:$K$103)-SUMIF($D$4:$D$103,U8,$J$4:$J$103) -> -23695100
B9: GERMAN | C9: COLOMBIA | D9: Tecnología | E9: Inversión | F9: Socio de proyecto | G9: NO | H9: 9 | I9: 7 | J9: 90000000 | K9: 50075523 | L9: 59142617 | M9: 95314026 | N9: =(Tabla3[[#This Row],[Inversión real 2017]]-Tabla3[[#This Row],[Inversión real 2016]])/Tabla3[[#This Row],[Inversión real 2016]] -> -0.37949723 | O9: =(Tabla3[[#This Row],[Inversión real 2017]]-Tabla3[[#This Row],[Inversión real 2018]])/Tabla3[[#This Row],[Inversión real 2018]] -> 0.18106838 | Q9: Educación | R9: $ - | S9: =SUMIF($D$4:$D$103,Q9,$K$4:$K$103) -> 0 | U9: Educación | V9: =SUMIF($D$4:$D$103,U9,$K$4:$K$103)-SUMIF($D$4:$D$103,U9,$J$4:$J$103) -> 0
B10: DAVID | C10: COLOMBIA | D10: Tecnología | E10: Trabajo | F10: Ofreciendo trabajo | G10: NO | H10: 5 | I10: 9 | J10: $ - | K10: $ - | L10: $ - | M10: 67714973 | N10: =(Tabla3[[#This Row],[Inversión real 2017]]-Tabla3[[#This Row],[Inversión real 2016]])/Tabla3[[#This Row],[Inversión real 2016]] -> #VALUE! | O10: =(Tabla3[[#This Row],[Inversión real 2017]]-Tabla3[[#This Row],[Inversión real 2018]])/Tabla3[[#This Row],[Inversión real 2018]] -> #VALUE!
B11: MIGUEL | C11: COLOMBIA | D11: Tecnología | E11: Inversión | F11: Socio capitalista | G11: SI | H11: 8 | I11: 10 | J11: 1000000 | K11: 5305190 | L11: 53291805 | M11: 84809282 | N11: =(Tabla3[[#This Row],[Inversión real 2017]]-Tabla3[[#This Row],[Inversión real 2016]])/Tabla3[[#This Row],[Inversión real 2016]] -> -0.37162768 | O11: =(Tabla3[[#This Row],[Inversión real 2017]]-Tabla3[[#This Row],[Inversión real 2018]])/Tabla3[[#This Row],[Inversión real 2018]] -> 9.0452208
B12: VICENTE | C12: COLOMBIA | D12: Agroindustrial | E12: Trabajo | F12: Ofreciendo trabajo | G12: SI | H12: 8 | I12: 3 | J12: $ - | K12: $ - | L12: 50085574 | M12: 42495353 | N12: =(Tabla3[[#This Row],[Inversión real 2017]]-Tabla3[[#This Row],[Inversión real 2016]])/Tabla3[[#This Row],[Inversión real 2016]] -> 0.17861297 | O12: =(Tabla3[[#This Row],[Inversión real 2017]]-Tabla3[[#This Row],[Inversión real 2018]])/Tabla3[[#This Row],[Inversión real 2018]] -> #VALUE! | Q12: ¿Cuántas personas vienen en las diferentes modalidades? ¿Porcentaje de cada uno? | T12: contar.si | U12: ¿Cuál es la DIFERENCIA ENTRE inversión del 2017 y 2016? | V12: Columna1
B13: ALVARO | C13: COLOMBIA | D13: Sector Real | E13: Inversión | F13: Socio de proyecto | G13: NO | H13: 5 | I13: 9 | J13: 10000000 | K13: 38941670 | L13: 67846781 | M13: 87726693 | N13: =(Tabla3[[#This Row],[Inversión real 2017]]-Tabla3[[#This Row],[Inversión real 2016]])/Tabla3[[#This Row],[Inversión real 2016]] -> -0.22661189 | O13: =(Tabla3[[#This Row],[Inversión real 2017]]-Tabla3[[#This Row],[Inversión real 2018]])/Tabla3[[#This Row],[Inversión real 2018]] -> 0.74226686 | Q13: Intención | R13: Cantidad | S13: Porcentaje | U13: Sector | V13: Inversión 2018
B14: LUIS | C14: VENEZUELA | D14: Tecnología | E14: Inversión | F14: Socio de proyecto | G14: NO | H14: 4 | I14: 5 | J14: 1000000 | K14: 28926771 | L14: 56939610 | M14: 92726884 | N14: =(Tabla3[[#This Row],[Inversión real 2017]]-Tabla3[[#This Row],[Inversión real 2016]])/Tabla3[[#This Row],[Inversión real 2016]] -> -0.38594281 | O14: =(Tabla3[[#This Row],[Inversión real 2017]]-Tabla3[[#This Row],[Inversión real 2018]])/Tabla3[[#This Row],[Inversión real 2018]] -> 0.96840532 | Q14: Trabajo | R14: =ROUND(COUNTIF($E$4:$E$103,Q14),0) -> 33 | S14: =R14/SUM($R$14:$R$16) -> 0.33 | U14: Tecnología | V14: =SUMIF($D$4:$D$103,U14,$L$4:$L$103)-SUMIF($D$4:$D$103,U14,$M$4:$M$103) -> -497331542
B15: DANIEL | C15: COLOMBIA | D15: Tecnología | E15: Inversión | F15: Socio de proyecto | G15: NO | H15: 3 | I15: 8 | J15: 1000000 | K15: 34252074 | L15: $ - | M15: 22994819 | N15: =(Tabla3[[#This Row],[Inversión real 2017]]-Tabla3[[#This Row],[Inversión real 2016]])/Tabla3[[#This Row],[Inversión real 2016]] -> #VALUE! | O15: =(Tabla3[[#This Row],[Inversión real 2017]]-Tabla3[[#This Row],[Inversión real 2018]])/Tabla3[[#This Row],[Inversión real 2018]] -> #VALUE! | Q15: Inversión | R15: =ROUND(COUNTIF($E$4:$E$103,Q15),0) -> 59 | S15: =R15/SUM($R$14:$R$16) -> 0.59 | U15: Sector Real | V15: =SUMIF($D$4:$D$103,U15,$L$4:$L$103)-SUMIF($D$4:$D$103,U15,$M$4:$M$103) -> 1143341
B16: JOSEP | C16: COLOMBIA | D16: Construcción | E16: Trabajo | F16: Buscando trabajo | G16: NO | H16: 7 | I16: 9 | J16: $ - | K16: $ - | L16: 45347826 | M16: 14301768 | N16: =(Tabla3[[#This Row],[Inversión real 2017]]-Tabla3[[#This Row],[Inversión real 2016]])/Tabla3[[#This Row],[Inversión real 2016]] -> 2.1707846 | O16: =(Tabla3[[#This Row],[Inversión real 2017]]-Tabla3[[#This Row],[Inversión real 2018]])/Tabla3[[#This Row],[Inversión real 2018]] -> #VALUE! | Q16: Conocimiento | R16: =ROUND(COUNTIF($E$4:$E$103,Q16),0) -> 8 | S16: =R16/SUM($R$14:$R$16) -> 0.08 | U16: Agroindustrial | V16: =SUMIF($D$4:$D$103,U16,$L$4:$L$103)-SUMIF($D$4:$D$103,U16,$M$4:$M$103) -> 129879240
B17: EDUARDO | C17: COLOMBIA | D17: Tecnología | E17: Trabajo | F17: Buscando trabajo | G17: SI | H17: 4 | I17: 8 | J17: $ - | K17: $ - | L17: 71453938 | M17: 38593802 | N17: =(Tabla3[[#This Row],[Inversión real 2017]]-Tabla3[[#This Row],[Inversión real 2016]])/Tabla3[[#This Row],[Inversión real 2016]] -> 0.85143558 | O17: =(Tabla3[[#This Row],[Inversión real 2017]]-Tabla3[[#This Row],[Inversión real 2018]])/Tabla3[[#This Row],[Inversión real 2018]] -> #VALUE! | U17: Construcción | V17: =SUMIF($D$4:$D$103,U17,$L$4:$L$103)-SUMIF($D$4:$D$103,U17,$M$4:$M$103) -> 20785398
B18: LEONEL | C18: COLOMBIA | D18: Sector Real | E18: Inversión | F18: Socio capitalista | G18: NO | H18: 9 | I18: 10 | J18: 20000000 | K18: 32346156 | L18: 22346275 | M18: 73743047 | N18: =(Tabla3[[#This Row],[Inversión real 2017]]-Tabla3[[#This Row],[Inversión real 2016]])/Tabla3[[#This Row],[Inversión real 2016]] -> -0.69697109 | O18: =(Tabla3[[#This Row],[Inversión real 2017]]-Tabla3[[#This Row],[Inversión real 2018]])/Tabla3[[#This Row],[Inversión real 2018]] -> -0.30915207 | U18: Educación | V18: =SUMIF($D$4:$D$103,U18,$L$4:$L$103)-SUMIF($D$4:$D$103,U18,$M$4:$M$103) -> 256825755
B19: JORDI | C19: COLOMBIA | D19: Educación | E19: Conocimiento | F19: Académico | G19: NO | H19: 4 | I19: 6 | J19: $ - | K19: $ - | L19: 96357193 | M19: 67901582 | N19: =(Tabla3[[#This Row],[Inversión real 2017]]-Tabla3[[#This Row],[Inversión real 2016]])/Tabla3[[#This Row],[Inversión real 2016]] -> 0.4190714 | O19: =(Tabla3[[#This Row],[Inversión real 2017]]-Tabla3[[#This Row],[Inversión real 2018]])/Tabla3[[#This Row],[Inversión real 2018]] -> #VALUE! | Q19: Otras fórmulas | T19: sólo explicar
B20: ESTEBAN | C20: COLOMBIA | D20: Tecnología | E20: Inversión | F20: Socio capitalista | G20: NO | H20: 5 | I20: 7 | J20: 100000000 | K20: 72903049 | L20: 67375493 | M20: 4753995 | N20: =(Tabla3[[#This Row],[Inversión real 2017]]-Tabla3[[#This Row],[Inversión real 2016]])/Tabla3[[#This Row],[Inversión real 2016]] -> 13.172395 | O20: =(Tabla3[[#This Row],[Inversión real 2017]]-Tabla3[[#This Row],[Inversión real 2018]])/Tabla3[[#This Row],[Inversión real 2018]] -> -0.075820642 | Q20: Contar | R20: Cuenta el número de celdas que contienen números en un rango determinado | T20: =COUNT(F4:H11) -> 8 | U20: ¿Cuál es la DIFERENCIA ENTRE inversión del 2017 y 2016? | V20: Columna1
B21: JONATHAN | C21: COLOMBIA | D21: Educación | E21: Conocimiento | F21: Académico | G21: NO | H21: 6 | I21: 7 | J21: $ - | K21: $ - | L21: 80671052 | M21: 58339670 | N21: =(Tabla3[[#This Row],[Inversión real 2017]]-Tabla3[[#This Row],[Inversión real 2016]])/Tabla3[[#This Row],[Inversión real 2016]] -> 0.38278211 | O21: =(Tabla3[[#This Row],[Inversión real 2017]]-Tabla3[[#This Row],[Inversión real 2018]])/Tabla3[[#This Row],[Inversión real 2018]] -> #VALUE! | U21: Sector | V21: Inversión 2018
B22: FELIPE | C22: BRASIL | D22: Sector Real | E22: Trabajo | F22: Buscando trabajo | G22: SI | H22: 9 | I22: 8 | J22: $ - | K22: $ - | L22: $ - | M22: 44898366 | N22: =(Tabla3[[#This Row],[Inversión real 2017]]-Tabla3[[#This Row],[Inversión real 2016]])/Tabla3[[#This Row],[Inversión real 2016]] -> #VALUE! | O22: =(Tabla3[[#This Row],[Inversión real 2017]]-Tabla3[[#This Row],[Inversión real 2018]])/Tabla3[[#This Row],[Inversión real 2018]] -> #VALUE! | Q22: ContarA | R22: Cuenta el número de celdas no vacías en un rango determinado | T22: =COUNTA(F4:H11) -> 24 | U22: Tecnología | V22: =SUMIF(SECTOR,U22,IINVREAL) -> 2002341114
B23: JOSE | C23: COLOMBIA | D23: Tecnología | E23: Inversión | F23: Socio de proyecto | G23: NO | H23: 5 | I23: 6 | J23: 1000000 | K23: 96696256 | L23: 62106884 | M23: 85228190 | N23: =(Tabla3[[#This Row],[Inversión real 2017]]-Tabla3[[#This Row],[Inversión real 2016]])/Tabla3[[#This Row],[Inversión real 2016]] -> -0.27128707 | O23: =(Tabla3[[#This Row],[Inversión real 2017]]-Tabla3[[#This Row],[Inversión real 2018]])/Tabla3[[#This Row],[Inversión real 2018]] -> -0.3577116 | U23: Sector Real | V23: =SUMIF(SECTOR,U23,IINVREAL) -> 535791961
B24: FELIX | C24: COLOMBIA | D24: Tecnología | E24: Inversión | F24: Socio de proyecto | G24: NO | H24: 6 | I24: 7 | J24: 10000000 | K24: 51531809 | L24: 99819688 | M24: 24233431 | N24: =(Tabla3[[#This Row],[Inversión real 2017]]-Tabla3[[#This Row],[Inversión real 2016]])/Tabla3[[#This Row],[Inversión real 2016]] -> 3.1190902 | O24: =(Tabla3[[#This Row],[Inversión real 2017]]-Tabla3[[#This Row],[Inversión real 2018]])/Tabla3[[#This Row],[Inversión real 2018]] -> 0.93704995 | Q24: Pregunta: ¿En qué escenarios pueden ser útiles estas fórmulas? | U24: Agroindustrial | V24: =SUMIF(SECTOR,U24,IINVREAL) -> 253232607
B25: PABLO | C25: COLOMBIA | D25: Agroindustrial | E25: Inversión | F25: Socio capitalista | G25: SI | H25: 6 | I25: 10 | J25: $ - | K25: $ - | L25: 34214902 | M25: 24896611 | N25: =(Tabla3[[#This Row],[Inversión real 2017]]-Tabla3[[#This Row],[Inversión real 2016]])/Tabla3[[#This Row],[Inversión real 2016]] -> 0.3742795 | O25: =(Tabla3[[#This Row],[Inversión real 2017]]-Tabla3[[#This Row],[Inversión real 2018]])/Tabla3[[#This Row],[Inversión real 2018]] -> #VALUE! | U25: Construcción | V25: =SUMIF(SECTOR,U25,IINVREAL) -> 187304900
B26: MANUEL | C26: ARGENTINA | D26: Sector Real | E26: Trabajo | F26: Ofreciendo trabajo | G26: NO | H26: 8 | I26: 5 | J26: $ - | K26: $ - | L26: 7121108 | M26: 6991703 | N26: =(Tabla3[[#This Row],[Inversión real 2017]]-Tabla3[[#This Row],[Inversión real 2016]])/Tabla3[[#This Row],[Inversión real 2016]] -> 0.018508366 | O26: =(Tabla3[[#This Row],[Inversión real 2017]]-Tabla3[[#This Row],[Inversión real 2018]])/Tabla3[[#This Row],[Inversión real 2018]] -> #VALUE! | U26: Educación | V26: =SUMIF(SECTOR,U26,IINVREAL) -> 0
B27: LORENZO | C27: COLOMBIA | D27: Agroindustrial | E27: Inversión | F27: Socio capitalista | G27: NO | H27: 7 | I27: 10 | J27: 20000000 | K27: 93037614 | L27: 48185946 | M27: 75039300 | N27: =(Tabla3[[#This Row],[Inversión real 2017]]-Tabla3[[#This Row],[Inversión real 2016]])/Tabla3[[#This Row],[Inversión real 2016]] -> -0.3578572 | O27: =(Tabla3[[#This Row],[Inversión real 2017]]-Tabla3[[#This Row],[Inversión real 2018]])/Tabla3[[#This Row],[Inversión real 2018]] -> -0.48208102 | Q27: ¿Cuál es la calificación promedio? | S27: promedio sencillo
B28: ISAAC | C28: COLOMBIA | D28: Tecnología | E28: Inversión | F28: Socio capitalista | G28: NO | H28: 9 | I28: 10 | J28: 90000000 | K28: 62088180 | L28: 18047519 | M28: 3738158 | N28: =(Tabla3[[#This Row],[Inversión real 2017]]-Tabla3[[#This Row],[Inversión real 2016]])/Tabla3[[#This Row],[Inversión real 2016]] -> 3.8279177 | O28: =(Tabla3[[#This Row],[Inversión real 2017]]-Tabla3[[#This Row],[Inversión real 2018]])/Tabla3[[#This Row],[Inversión real 2018]] -> -0.7093244 | Q28: Tipo | R28: Calificación | U28: VARIACION PORCENTUAL TOTAL 2016-2017
B29: MARIA | C29: COLOMBIA | D29: Sector Real | E29: Inversión | F29: Socio capitalista | G29: NO | H29: 3 | I29: 9 | J29: 1000000 | K29: 1160848 | L29: 32268145 | M29: 13339687 | N29: =(Tabla3[[#This Row],[Inversión real 2017]]-Tabla3[[#This Row],[Inversión real 2016]])/Tabla3[[#This Row],[Inversión real 2016]] -> 1.4189582 | O29: =(Tabla3[[#This Row],[Inversión real 2017]]-Tabla3[[#This Row],[Inversión real 2018]])/Tabla3[[#This Row],[Inversión real 2018]] -> 26.797046 | Q29: Feria | R29: =AVERAGE(H4:H103) -> 5.81 | U29: =(SUM(INVREAL17)-SUM(INVREAL16))/SUM(INVREAL16) -> -0.020979823 | V29: VARIANZA
B30: ANGEL | C30: COLOMBIA | D30: Tecnología | E30: Trabajo | F30: Ofreciendo trabajo | G30: NO | H30: 6 | I30: 2 | J30: $ - | K30: $ - | L30: 21224611 | M30: 62562457 | N30: =(Tabla3[[#This Row],[Inversión real 2017]]-Tabla3[[#This Row],[Inversión real 2016]])/Tabla3[[#This Row],[Inversión real 2016]] -> -0.66074525 | O30: =(Tabla3[[#This Row],[Inversión real 2017]]-Tabla3[[#This Row],[Inversión real 2018]])/Tabla3[[#This Row],[Inversión real 2018]] -> #VALUE! | Q30: Proyectos | R30: =AVERAGE(I4:I103) -> 7.56
B31: ADOLFO | C31: COLOMBIA | D31: Sector Real | E31: Trabajo | F31: Ofreciendo trabajo | G31: NO | H31: 9 | I31: 9 | J31: $ - | K31: $ - | L31: 85434615 | M31: 79508333 | N31: =(Tabla3[[#This Row],[Inversión real 2017]]-Tabla3[[#This Row],[Inversión real 2016]])/Tabla3[[#This Row],[Inversión real 2016]] -> 0.074536615 | O31: =(Tabla3[[#This Row],[Inversión real 2017]]-Tabla3[[#This Row],[Inversión real 2018]])/Tabla3[[#This Row],[Inversión real 2018]] -> #VALUE! | Q31: Agregado | R31: =AVERAGE(R29:R30) -> 6.685 | S31: promedio sencillo
B32: ERNESTO | C32: COLOMBIA | D32: Tecnología | E32: Inversión | F32: Socio de proyecto | G32: NO | H32: 8 | I32: 7 | J32: 90000000 | K32: 23888885 | L32: 68725539 | M32: 78613526 | N32: =(Tabla3[[#This Row],[Inversión real 2017]]-Tabla3[[#This Row],[Inversión real 2016]])/Tabla3[[#This Row],[Inversión real 2016]] -> -0.12577972 | O32: =(Tabla3[[#This Row],[Inversión real 2017]]-Tabla3[[#This Row],[Inversión real 2018]])/Tabla3[[#This Row],[Inversión real 2018]] -> 1.8768835
B33: RAFAEL | C33: COLOMBIA | D33: Sector Real | E33: Inversión | F33: Socio capitalista | G33: SI | H33: 8 | I33: 8 | J33: 10000000 | K33: 23464528 | L33: 904543 | M33: $ - | N33: =(Tabla3[[#This Row],[Inversión real 2017]]-Tabla3[[#This Row],[Inversión real 2016]])/Tabla3[[#This Row],[Inversión real 2016]] -> #VALUE! | O33: =(Tabla3[[#This Row],[Inversión real 2017]]-Tabla3[[#This Row],[Inversión real 2018]])/Tabla3[[#This Row],[Inversión real 2018]] -> -0.96145062 | Q33: ¿Cuál es la calificación promedio de los proyectos de acuerdo a cada uno de los sectores? | S33: promedio.si
B34: TOMAS | C34: COLOMBIA | D34: Agroindustrial | E34: Trabajo | F34: Ofreciendo trabajo | G34: NO | H34: 6 | I34: 8 | J34: $ - | K34: $ - | L34: 66204884 | M34: 27801447 | N34: =(Tabla3[[#This Row],[Inversión real 2017]]-Tabla3[[#This Row],[Inversión real 2016]])/Tabla3[[#This Row],[Inversión real 2016]] -> 1.3813467 | O34: =(Tabla3[[#This Row],[Inversión real 2017]]-Tabla3[[#This Row],[Inversión real 2018]])/Tabla3[[#This Row],[Inversión real 2018]] -> #VALUE! | Q34: Sector | R34: Calificación
B35: MARCOS | C35: BRASIL | D35: Sector Real | E35: Trabajo | F35: Buscando trabajo | G35: SI | H35: 3 | I35: 5 | J35: $ - | K35: $ - | L35: 30987169 | M35: 7339680 | N35: =(Tabla3[[#This Row],[Inversión real 2017]]-Tabla3[[#This Row],[Inversión real 2016]])/Tabla3[[#This Row],[Inversión real 2016]] -> 3.2218692 | O35: =(Tabla3[[#This Row],[Inversión real 2017]]-Tabla3[[#This Row],[Inversión real 2018]])/Tabla3[[#This Row],[Inversión real 2018]] -> #VALUE! | Q35: Tecnología | R35: =AVERAGEIF($D$4:$D$103,Q35,$I$4:$I$103) -> 7.3333333
B36: MARIO | C36: COLOMBIA | D36: Tecnología | E36: Inversión | F36: Socio capitalista | G36: NO | H36: 6 | I36: 7 | J36: 10000000 | K36: 22390348 | L36: 24476166 | M36: $ - | N36: =(Tabla3[[#This Row],[Inversión real 2017]]-Tabla3[[#This Row],[Inversión real 2016]])/Tabla3[[#This Row],[Inversión real 2016]] -> #VALUE! | O36: =(Tabla3[[#This Row],[Inversión real 2017]]-Tabla3[[#This Row],[Inversión real 2018]])/Tabla3[[#This Row],[Inversión real 2018]] -> 0.093157016 | Q36: Sector Real | R36: =AVERAGEIF($D$4:$D$103,Q36,$I$4:$I$103) -> 8.0952381
B37: ARTURO | C37: COLOMBIA | D37: Sector Real | E37: Inversión | F37: Socio de proyecto | G37: NO | H37: 6 | I37: 10 | J37: 20000000 | K37: 31670482 | L37: 15619630 | M37: 59838390 | N37: =(Tabla3[[#This Row],[Inversión real 2017]]-Tabla3[[#This Row],[Inversión real 2016]])/Tabla3[[#This Row],[Inversión real 2016]] -> -0.73896975 | O37: =(Tabla3[[#This Row],[Inversión real 2017]]-Tabla3[[#This Row],[Inversión real 2018]])/Tabla3[[#This Row],[Inversión real 2018]] -> -0.50680795 | Q37: Agroindustrial | R37: =AVERAGEIF($D$4:$D$103,Q37,$I$4:$I$103) -> 7
B38: EUGENIO | C38: COLOMBIA | D38: Construcción | E38: Inversión | F38: Socio de proyecto | G38: NO | H38: 8 | I38: 5 | J38: 20000000 | K38: 81056910 | L38: 96438403 | M38: 90723423 | N38: =(Tabla3[[#This Row],[Inversión real 2017]]-Tabla3[[#This Row],[Inversión real 2016]])/Tabla3[[#This Row],[Inversión real 2016]] -> 0.062993434 | O38: =(Tabla3[[#This Row],[Inversión real 2017]]-Tabla3[[#This Row],[Inversión real 2018]])/Tabla3[[#This Row],[Inversión real 2018]] -> 0.18976165 | Q38: Construcción | R38: =AVERAGEIF($D$4:$D$103,Q38,$I$4:$I$103) -> 8.5
B39: JUAN | C39: COLOMBIA | D39: Tecnología | E39: Conocimiento | F39: Otro tipo | G39: NO | H39: 5 | I39: 7 | J39: $ - | K39: $ - | L39: $ - | M39: 52936315 | N39: =(Tabla3[[#This Row],[Inversión real 2017]]-Tabla3[[#This Row],[Inversión real 2016]])/Tabla3[[#This Row],[Inversión real 2016]] -> #VALUE! | O39: =(Tabla3[[#This Row],[Inversión real 2017]]-Tabla3[[#This Row],[Inversión real 2018]])/Tabla3[[#This Row],[Inversión real 2018]] -> #VALUE! | Q39: Educación | R39: =AVERAGEIF($D$4:$D$103,Q39,$I$4:$I$103) -> 7.3333333
B40: GONZALO | C40: COLOMBIA | D40: Tecnología | E40: Inversión | F40: Socio capitalista | G40: NO | H40: 9 | I40: 7 | J40: 30000000 | K40: 91413171 | L40: 13211402 | M40: $ - | N40: =(Tabla3[[#This Row],[Inversión real 2017]]-Tabla3[[#This Row],[Inversión real 2016]])/Tabla3[[#This Row],[Inversión real 2016]] -> #VALUE! | O40: =(Tabla3[[#This Row],[Inversión real 2017]]-Tabla3[[#This Row],[Inversión real 2018]])/Tabla3[[#This Row],[Inversión real 2018]] -> -0.85547595
B41: ANTONIO | C41: COLOMBIA | D41: Construcción | E41: Inversión | F41: Socio de proyecto | G41: NO | H41: 4 | I41: 7 | J41: 1000000 | K41: 87347043 | L41: 50796112 | M41: 72757830 | N41: =(Tabla3[[#This Row],[Inversión real 2017]]-Tabla3[[#This Row],[Inversión real 2016]])/Tabla3[[#This Row],[Inversión real 2016]] -> -0.3018468 | O41: =(Tabla3[[#This Row],[Inversión real 2017]]-Tabla3[[#This Row],[Inversión real 2018]])/Tabla3[[#This Row],[Inversión real 2018]] -> -0.41845642
B42: EMILIO | C42: COLOMBIA | D42: Sector Real | E42: Trabajo | F42: Buscando trabajo | G42: NO | H42: 4 | I42: 9 | J42: $ - | K42: $ - | L42: 38721754 | M42: 77230635 | N42: =(Tabla3[[#This Row],[Inversión real 2017]]-Tabla3[[#This Row],[Inversión real 2016]])/Tabla3[[#This Row],[Inversión real 2016]] -> -0.49862184 | O42: =(Tabla3[[#This Row],[Inversión real 2017]]-Tabla3[[#This Row],[Inversión real 2018]])/Tabla3[[#This Row],[Inversión real 2018]] -> #VALUE!
B43: AGUSTIN | C43: COLOMBIA | D43: Tecnología | E43: Inversión | F43: Socio de proyecto | G43: NO | H43: 9 | I43: 5 | J43: 10000000 | K43: 43538967 | L43: 5161300 | M43: 85417673 | N43: =(Tabla3[[#This Row],[Inversión real 2017]]-Tabla3[[#This Row],[Inversión real 2016]])/Tabla3[[#This Row],[Inversión real 2016]] -> -0.93957574 | O43: =(Tabla3[[#This Row],[Inversión real 2017]]-Tabla3[[#This Row],[Inversión real 2018]])/Tabla3[[#This Row],[Inversión real 2018]] -> -0.88145562
B44: JUAN PABLO | C44: COLOMBIA | D44: Tecnología | E44: Inversión | F44: Socio de proyecto | G44: SI | H44: 6 | I44: 10 | J44: 1000000 | K44: 95899452 | L44: 2565664 | M44: 39602953 | N44: =(Tabla3[[#This Row],[Inversión real 2017]]-Tabla3[[#This Row],[Inversión real 2016]])/Tabla3[[#This Row],[Inversión real 2016]] -> -0.93521534 | O44: =(Tabla3[[#This Row],[Inversión real 2017]]-Tabla3[[#This Row],[Inversión real 2018]])/Tabla3[[#This Row],[Inversión real 2018]] -> -0.97324631
B45: FRANCISCO | C45: COLOMBIA | D45: Tecnología | E45: Inversión | F45: Socio de proyecto | G45: SI | H45: 8 | I45: 8 | J45: 1000000 | K45: 81347428 | L45: 10860215 | M45: 28637290 | N45: =(Tabla3[[#This Row],[Inversión real 2017]]-Tabla3[[#This Row],[Inversión real 2016]])/Tabla3[[#This Row],[Inversión real 2016]] -> -0.62076666 | O45: =(Tabla3[[#This Row],[Inversión real 2017]]-Tabla3[[#This Row],[Inversión real 2018]])/Tabla3[[#This Row],[Inversión real 2018]] -> -0.8664959
B46: MARC | C46: COLOMBIA | D46: Sector Real | E46: Inversión | F46: Socio de proyecto | G46: SI | H46: 6 | I46: 10 | J46: 30000000 | K46: 52442860 | L46: 2659881 | M46: 80287314 | N46: =(Tabla3[[#This Row],[Inversión real 2017]]-Tabla3[[#This Row],[Inversión real 2016]])/Tabla3[[#This Row],[Inversión real 2016]] -> -0.96687047 | O46: =(Tabla3[[#This Row],[Inversión real 2017]]-Tabla3[[#This Row],[Inversión real 2018]])/Tabla3[[#This Row],[Inversión real 2018]] -> -0.9492804
B47: ROBERTO | C47: COLOMBIA | D47: Tecnología | E47: Inversión | F47: Socio de proyecto | G47: SI | H47: 7 | I47: 5 | J47: 10000000 | K47: 96199053 | L47: 31746355 | M47: 80063468 | N47: =(Tabla3[[#This Row],[Inversión real 2017]]-Tabla3[[#This Row],[Inversión real 2016]])/Tabla3[[#This Row],[Inversión real 2016]] -> -0.60348514 | O47: =(Tabla3[[#This Row],[Inversión real 2017]]-Tabla3[[#This Row],[Inversión real 2018]])/Tabla3[[#This Row],[Inversión real 2018]] -> -0.66999306
B48: CARLOS | C48: COLOMBIA | D48: Tecnología | E48: Inversión | F48: Socio de proyecto | G48: NO | H48: 5 | I48: 7 | J48: 1000000 | K48: 71783742 | L48: 64667814 | M48: 70653180 | N48: =(Tabla3[[#This Row],[Inversión real 2017]]-Tabla3[[#This Row],[Inversión real 2016]])/Tabla3[[#This Row],[Inversión real 2016]] -> -0.084714743 | O48: =(Tabla3[[#This Row],[Inversión real 2017]]-Tabla3[[#This Row],[Inversión real 2018]])/Tabla3[[#This Row],[Inversión real 2018]] -> -0.099130079
B49: JOEL | C49: COLOMBIA | D49: Sector Real | E49: Inversión | F49: Socio de proyecto | G49: NO | H49: 3 | I49: 8 | J49: 90000000 | K49: 94913746 | L49: 74083223 | M49: 31617670 | N49: =(Tabla3[[#This Row],[Inversión real 2017]]-Tabla3[[#This Row],[Inversión real 2016]])/Tabla3[[#This Row],[Inversión real 2016]] -> 1.3430956 | O49: =(Tabla3[[#This Row],[Inversión real 2017]]-Tabla3[[#This Row],[Inversión real 2018]])/Tabla3[[#This Row],[Inversión real 2018]] -> -0.21946793
B50: MARIANO | C50: COLOMBIA | D50: Sector Real | E50: Trabajo | F50: Ofreciendo trabajo | G50: NO | H50: 7 | I50: 9 | J50: $ - | K50: $ - | L50: 67753952 | M50: 77205812 | N50: =(Tabla3[[#This Row],[Inversión real 2017]]-Tabla3[[#This Row],[Inversión real 2016]])/Tabla3[[#This Row],[Inversión real 2016]] -> -0.1224242 | O50: =(Tabla3[[#This Row],[Inversión real 2017]]-Tabla3[[#This Row],[Inversión real 2018]])/Tabla3[[#This Row],[Inversión real 2018]] -> #VALUE!
B51: OSCAR | C51: BRASIL | D51: Tecnología | E51: Inversión | F51: Socio de proyecto | G51: SI | H51: 5 | I51: 6 | J51: 30000000 | K51: 33477783 | L51: $ - | M51: 27651635 | N51: =(Tabla3[[#This Row],[Inversión real 2017]]-Tabla3[[#This Row],[Inversión real 2016]])/Tabla3[[#This Row],[Inversión real 2016]] -> #VALUE! | O51: =(Tabla3[[#This Row],[Inversión real 2017]]-Tabla3[[#This Row],[Inversión real 2018]])/Tabla3[[#This Row],[Inversión real 2018]] -> #VALUE!
B52: ALEXANDER | C52: COLOMBIA | D52: Construcción | E52: Inversión | F52: Socio capitalista | G52: SI | H52: 9 | I52: 9 | J52: 50000000 | K52: 2702447 | L52: $ - | M52: 44671760 | N52: =(Tabla3[[#This Row],[Inversión real 2017]]-Tabla3[[#This Row],[Inversión real 2016]])/Tabla3[[#This Row],[Inversión real 2016]] -> #VALUE! | O52: =(Tabla3[[#This Row],[Inversión real 2017]]-Tabla3[[#This Row],[Inversión real 2018]])/Tabla3[[#This Row],[Inversión real 2018]] -> #VALUE!
B53: BORJA | C53: ECUADOR | D53: Tecnología | E53: Inversión | F53: Socio capitalista | G53: NO | H53: 6 | I53: 8 | J53: 50000000 | K53: 70787848 | L53: 33368202 | M53: 43277527 | N53: =(Tabla3[[#This Row],[Inversión real 2017]]-Tabla3[[#This Row],[Inversión real 2016]])/Tabla3[[#This Row],[Inversión real 2016]] -> -0.22897161 | O53: =(Tabla3[[#This Row],[Inversión real 2017]]-Tabla3[[#This Row],[Inversión real 2018]])/Tabla3[[#This Row],[Inversión real 2018]] -> -0.5286168
B54: RAUL | C54: BRASIL | D54: Tecnología | E54: Trabajo | F54: Ofreciendo trabajo | G54: SI | H54: 7 | I54: 5 | J54: $ - | K54: $ - | L54: 46563396 | M54: 63313535 | N54: =(Tabla3[[#This Row],[Inversión real 2017]]-Tabla3[[#This Row],[Inversión real 2016]])/Tabla3[[#This Row],[Inversión real 2016]] -> -0.26455858 | O54: =(Tabla3[[#This Row],[Inversión real 2017]]-Tabla3[[#This Row],[Inversión real 2018]])/Tabla3[[#This Row],[Inversión real 2018]] -> #VALUE!
B55: ALEX | C55: URUGUAY | D55: Tecnología | E55: Inversión | F55: Socio capitalista | G55: NO | H55: 5 | I55: 6 | J55: 20000000 | K55: 40064620 | L55: 98137438 | M55: $ - | N55: =(Tabla3[[#This Row],[Inversión real 2017]]-Tabla3[[#This Row],[Inversión real 2016]])/Tabla3[[#This Row],[Inversión real 2016]] -> #VALUE! | O55: =(Tabla3[[#This Row],[Inversión real 2017]]-Tabla3[[#This Row],[Inversión real 2018]])/Tabla3[[#This Row],[Inversión real 2018]] -> 1.4494788
B56: IVAN | C56: COLOMBIA | D56: Tecnología | E56: Inversión | F56: Socio de proyecto | G56: NO | H56: 4 | I56: 6 | J56: 30000000 | K56: 45289360 | L56: $ - | M56: 46980526 | N56: =(Tabla3[[#This Row],[Inversión real 2017]]-Tabla3[[#This Row],[Inversión real 2016]])/Tabla3[[#This Row],[Inversión real 2016]] -> #VALUE! | O56: =(Tabla3[[#This Row],[Inversión real 2017]]-Tabla3[[#This Row],[Inversión real 2018]])/Tabla3[[#This Row],[Inversión real 2018]] -> #VALUE!
B57: SAMUEL | C57: COLOMBIA | D57: Sector Real | E57: Inversión | F57: Socio de proyecto | G57: NO | H57: 7 | I57: 5 | J57: 30000000 | K57: 34397393 | L57: 72192037 | M57: 21247716 | N57: =(Tabla3[[#This Row],[Inversión real 2017]]-Tabla3[[#This Row],[Inversión real 2016]])/Tabla3[[#This Row],[Inversión real 2016]] -> 2.3976375 | O57: =(Tabla3[[#This Row],[Inversión real 2017]]-Tabla3[[#This Row],[Inversión real 2018]])/Tabla3[[#This Row],[Inversión real 2018]] -> 1.0987648
B58: ANDRES | C58: COLOMBIA | D58: Tecnología | E58: Trabajo | F58: Buscando trabajo | G58: SI | H58: 3 | I58: 9 | J58: $ - | K58: $ - | L58: 69870077 | M58: 98441580 | N58: =(Tabla3[[#This Row],[Inversión real 2017]]-Tabla3[[#This Row],[Inversión real 2016]])/Tabla3[[#This Row],[Inversión real 2016]] -> -0.29023816 | O58: =(Tabla3[[#This Row],[Inversión real 2017]]-Tabla3[[#This Row],[Inversión real 2018]])/Tabla3[[#This Row],[Inversión real 2018]] -> #VALUE!
B59: NORA | C59: CHILE | D59: Sector Real | E59: Inversión | F59: Socio de proyecto | G59: NO | H59: 3 | I59: 6 | J59: 1000000 | K59: 34126405 | L59: 88265167 | M59: 56002928 | N59: =(Tabla3[[#This Row],[Inversión real 2017]]-Tabla3[[#This Row],[Inversión real 2016]])/Tabla3[[#This Row],[Inversión real 2016]] -> 0.57608129 | O59: =(Tabla3[[#This Row],[Inversión real 2017]]-Tabla3[[#This Row],[Inversión real 2018]])/Tabla3[[#This Row],[Inversión real 2018]] -> 1.5864186
B60: ANDRÉS | C60: COLOMBIA | D60: Tecnología | E60: Inversión | F60: Socio capitalista | G60: NO | H60: 7 | I60: 10 | J60: 1000000 | K60: 53008255 | L60: 46917910 | M60: 47557281 | N60: =(Tabla3[[#This Row],[Inversión real 2017]]-Tabla3[[#This Row],[Inversión real 2016]])/Tabla3[[#This Row],[Inversión real 2016]] -> -0.013444229 | O60: =(Tabla3[[#This Row],[Inversión real 2017]]-Tabla3[[#This Row],[Inversión real 2018]])/Tabla3[[#This Row],[Inversión real 2018]] -> -0.11489427
B61: CRISTIAN | C61: COLOMBIA | D61: Tecnología | E61: Trabajo | F61: Buscando trabajo | G61: NO | H61: 5 | I61: 9 | J61: $ - | K61: $ - | L61: $ - | M61: 22675260 | N61: =(Tabla3[[#This Row],[Inversión real 2017]]-Tabla3[[#This Row],[Inversión real 2016]])/Tabla3[[#This Row],[Inversión real 2016]] -> #VALUE! | O61: =(Tabla3[[#This Row],[Inversión real 2017]]-Tabla3[[#This Row],[Inversión real 2018]])/Tabla3[[#This Row],[Inversión real 2018]] -> #VALUE!
B62: JAVIER | C62: BOLIVIA | D62: Tecnología | E62: Inversión | F62: Socio capitalista | G62: NO | H62: 9 | I62: 5 | J62: 100000000 | K62: 94688720 | L62: 86323763 | M62: 20929788 | N62: =(Tabla3[[#This Row],[Inversión real 2017]]-Tabla3[[#This Row],[Inversión real 2016]])/Tabla3[[#This Row],[Inversión real 2016]] -> 3.1244452 | O62: =(Tabla3[[#This Row],[Inversión real 2017]]-Tabla3[[#This Row],[Inversión real 2018]])/Tabla3[[#This Row],[Inversión real 2018]] -> -0.088341642
B63: DOMINGO | C63: COLOMBIA | D63: Educación | E63: Conocimiento | F63: Académico | G63: NO | H63: 4 | I63: 8 | J63: $ - | K63: $ - | L63: 96750826 | M63: 31435769 | N63: =(Tabla3[[#This Row],[Inversión real 2017]]-Tabla3[[#This Row],[Inversión real 2016]])/Tabla3[[#This Row],[Inversión real 2016]] -> 2.0777305 | O63: =(Tabla3[[#This Row],[Inversión real 2017]]-Tabla3[[#This Row],[Inversión real 2018]])/Tabla3[[#This Row],[Inversión real 2018]] -> #VALUE!
B64: NICOLAS | C64: COLOMBIA | D64: Sector Real | E64: Inversión | F64: Socio capitalista | G64: NO | H64: 5 | I64: 10 | J64: 10000000 | K64: 89686683 | L64: 62448793 | M64: 26812600 | N64: =(Tabla3[[#This Row],[Inversión real 2017]]-Tabla3[[#This Row],[Inversión real 2016]])/Tabla3[[#This Row],[Inversión real 2016]] -> 1.3290838 | O64: =(Tabla3[[#This Row],[Inversión real 2017]]-Tabla3[[#This Row],[Inversión real 2018]])/Tabla3[[#This Row],[Inversión real 2018]] -> -0.30370049
B65: HECTOR | C65: COLOMBIA | D65: Tecnología | E65: Inversión | F65: Socio de proyecto | G65: NO | H65: 3 | I65: 10 | J65: 30000000 | K65: 32890743 | L65: $ - | M65: 39864620 | N65: =(Tabla3[[#This Row],[Inversión real 2017]]-Tabla3[[#This Row],[Inversión real 2016]])/Tabla3[[#This Row],[Inversión real 2016]] -> #VALUE! | O65: =(Tabla3[[#This Row],[Inversión real 2017]]-Tabla3[[#This Row],[Inversión real 2018]])/Tabla3[[#This Row],[Inversión real 2018]] -> #VALUE!
B66: RICARDO | C66: COLOMBIA | D66: Sector Real | E66: Inversión | F66: Socio capitalista | G66: NO | H66: 3 | I66: 10 | J66: 10000000 | K66: 32370896 | L66: 96066942 | M66: 3767736 | N66: =(Tabla3[[#This Row],[Inversión real 2017]]-Tabla3[[#This Row],[Inversión real 2016]])/Tabla3[[#This Row],[Inversión real 2016]] -> 24.497259 | O66: =(Tabla3[[#This Row],[Inversión real 2017]]-Tabla3[[#This Row],[Inversión real 2018]])/Tabla3[[#This Row],[Inversión real 2018]] -> 1.9676949
B67: ALBERTO | C67: COLOMBIA | D67: Sector Real | E67: Trabajo | F67: Ofreciendo trabajo | G67: NO | H67: 5 | I67: 5 | J67: $ - | K67: $ - | L67: 24514428 | M67: 27890231 | N67: =(Tabla3[[#This Row],[Inversión real 2017]]-Tabla3[[#This Row],[Inversión real 2016]])/Tabla3[[#This Row],[Inversión real 2016]] -> -0.1210389 | O67: =(Tabla3[[#This Row],[Inversión real 2017]]-Tabla3[[#This Row],[Inversión real 2018]])/Tabla3[[#This Row],[Inversión real 2018]] -> #VALUE!
B68: RUBEN | C68: COLOMBIA | D68: Tecnología | E68: Inversión | F68: Socio capitalista | G68: SI | H68: 7 | I68: 7 | J68: 10000000 | K68: 31953589 | L68: 40068224 | M68: 80951038 | N68: =(Tabla3[[#This Row],[Inversión real 2017]]-Tabla3[[#This Row],[Inversión real 2016]])/Tabla3[[#This Row],[Inversión real 2016]] -> -0.50503137 | O68: =(Tabla3[[#This Row],[Inversión real 2017]]-Tabla3[[#This Row],[Inversión real 2018]])/Tabla3[[#This Row],[Inversión real 2018]] -> 0.25395066
B69: SEBASTIAN | C69: COLOMBIA | D69: Tecnología | E69: Inversión | F69: Socio capitalista | G69: NO | H69: 7 | I69: 5 | J69: 50000000 | K69: 78205651 | L69: 62381180 | M69: 6508585 | N69: =(Tabla3[[#This Row],[Inversión real 2017]]-Tabla3[[#This Row],[Inversión real 2016]])/Tabla3[[#This Row],[Inversión real 2016]] -> 8.5844458 | O69: =(Tabla3[[#This Row],[Inversión real 2017]]-Tabla3[[#This Row],[Inversión real 2018]])/Tabla3[[#This Row],[Inversión real 2018]] -> -0.20234434
B70: MOHAMED | C70: COLOMBIA | D70: Agroindustrial | E70: Trabajo | F70: Buscando trabajo | G70: NO | H70: 5 | I70: 4 | J70: $ - | K70: $ - | L70: 34584522 | M70: $ - | N70: =(Tabla3[[#This Row],[Inversión real 2017]]-Tabla3[[#This Row],[Inversión real 2016]])/Tabla3[[#This Row],[Inversión real 2016]] -> #VALUE! | O70: =(Tabla3[[#This Row],[Inversión real 2017]]-Tabla3[[#This Row],[Inversión real 2018]])/Tabla3[[#This Row],[Inversión real 2018]] -> #VALUE!
B71: MARCO | C71: PERU | D71: Tecnología | E71: Conocimiento | F71: Otro tipo | G71: NO | H71: 7 | I71: 7 | J71: $ - | K71: $ - | L71: 76942676 | M71: 74216691 | N71: =(Tabla3[[#This Row],[Inversión real 2017]]-Tabla3[[#This Row],[Inversión real 2016]])/Tabla3[[#This Row],[Inversión real 2016]] -> 0.03673008 | O71: =(Tabla3[[#This Row],[Inversión real 2017]]-Tabla3[[#This Row],[Inversión real 2018]])/Tabla3[[#This Row],[Inversión real 2018]] -> #VALUE!
B72: SERGIO | C72: BRASIL | D72: Sector Real | E72: Inversión | F72: Socio de proyecto | G72: SI | H72: 8 | I72: 9 | J72: 5000000 | K72: 70270294 | L72: 19588762 | M72: 78634577 | N72: =(Tabla3[[#This Row],[Inversión real 2017]]-Tabla3[[#This Row],[Inversión real 2016]])/Tabla3[[#This Row],[Inversión real 2016]] -> -0.7508887 | O72: =(Tabla3[[#This Row],[Inversión real 2017]]-Tabla3[[#This Row],[Inversión real 2018]])/Tabla3[[#This Row],[Inversión real 2018]] -> -0.72123694
B73: RAMON | C73: COLOMBIA | D73: Agroindustrial | E73: Trabajo | F73: Buscando trabajo | G73: NO | H73: 3 | I73: 5 | J73: $ - | K73: $ - | L73: 85955846 | M73: 25891596 | N73: =(Tabla3[[#This Row],[Inversión real 2017]]-Tabla3[[#This Row],[Inversión real 2016]])/Tabla3[[#This Row],[Inversión real 2016]] -> 2.3198357 | O73: =(Tabla3[[#This Row],[Inversión real 2017]]-Tabla3[[#This Row],[Inversión real 2018]])/Tabla3[[#This Row],[Inversión real 2018]] -> #VALUE!
B74: GREGORIO | C74: COLOMBIA | D74: Agroindustrial | E74: Inversión | F74: Socio de proyecto | G74: SI | H74: 8 | I74: 10 | J74: 20000000 | K74: 62745331 | L74: 39843357 | M74: 64840967 | N74: =(Tabla3[[#This Row],[Inversión real 2017]]-Tabla3[[#This Row],[Inversión real 2016]])/Tabla3[[#This Row],[Inversión real 2016]] -> -0.38552186 | O74: =(Tabla3[[#This Row],[Inversión real 2017]]-Tabla3[[#This Row],[Inversión real 2018]])/Tabla3[[#This Row],[Inversión real 2018]] -> -0.36499886
B75: JOAN | C75: COLOMBIA | D75: Tecnología | E75: Trabajo | F75: Ofreciendo trabajo | G75: NO | H75: 5 | I75: 7 | J75: $ - | K75: $ - | L75: 82583322 | M75: 809058 | N75: =(Tabla3[[#This Row],[Inversión real 2017]]-Tabla3[[#This Row],[Inversión real 2016]])/Tabla3[[#This Row],[Inversión real 2016]] -> 101.07343 | O75: =(Tabla3[[#This Row],[Inversión real 2017]]-Tabla3[[#This Row],[Inversión real 2018]])/Tabla3[[#This Row],[Inversión real 2018]] -> #VALUE!
B76: ALFONSO | C76: COLOMBIA | D76: Tecnología | E76: Inversión | F76: Socio de proyecto | G76: SI | H76: 6 | I76: 6 | J76: 10000000 | K76: 59890317 | L76: 42451842 | M76: $ - | N76: =(Tabla3[[#This Row],[Inversión real 2017]]-Tabla3[[#This Row],[Inversión real 2016]])/Tabla3[[#This Row],[Inversión real 2016]] -> #VALUE! | O76: =(Tabla3[[#This Row],[Inversión real 2017]]-Tabla3[[#This Row],[Inversión real 2018]])/Tabla3[[#This Row],[Inversión real 2018]] -> -0.29117353
B77: GUILLERMO | C77: COLOMBIA | D77: Agroindustrial | E77: Inversión | F77: Socio capitalista | G77: NO | H77: 3 | I77: 6 | J77: 10000000 | K77: 97449662 | L77: 49624160 | M77: 17854677 | N77: =(Tabla3[[#This Row],[Inversión real 2017]]-Tabla3[[#This Row],[Inversión real 2016]])/Tabla3[[#This Row],[Inversión real 2016]] -> 1.7793368 | O77: =(Tabla3[[#This Row],[Inversión real 2017]]-Tabla3[[#This Row],[Inversión real 2018]])/Tabla3[[#This Row],[Inversión real 2018]] -> -0.49077135
B78: CHRISTIAN | C78: COLOMBIA | D78: Construcción | E78: Trabajo | F78: Ofreciendo trabajo | G78: NO | H78: 8 | I78: 10 | J78: $ - | K78: $ - | L78: 44422091 | M78: 8898260 | N78: =(Tabla3[[#This Row],[Inversión real 2017]]-Tabla3[[#This Row],[Inversión real 2016]])/Tabla3[[#This Row],[Inversión real 2016]] -> 3.9922222 | O78: =(Tabla3[[#This Row],[Inversión real 2017]]-Tabla3[[#This Row],[Inversión real 2018]])/Tabla3[[#This Row],[Inversión real 2018]] -> #VALUE!
B79: MATEO | C79: URUGUAY | D79: Tecnología | E79: Trabajo | F79: Buscando trabajo | G79: NO | H79: 5 | I79: 7 | J79: $ - | K79: $ - | L79: $ - | M79: 63436099 | N79: =(Tabla3[[#This Row],[Inversión real 2017]]-Tabla3[[#This Row],[Inversión real 2016]])/Tabla3[[#This Row],[Inversión real 2016]] -> #VALUE! | O79: =(Tabla3[[#This Row],[Inversión real 2017]]-Tabla3[[#This Row],[Inversión real 2018]])/Tabla3[[#This Row],[Inversión real 2018]] -> #VALUE!
B80: JULIAN | C80: COLOMBIA | D80: Tecnología | E80: Inversión | F80: Socio capitalista | G80: SI | H80: 8 | I80: 9 | J80: 10000000 | K80: 99989764 | L80: 8030175 | M80: 37676206 | N80: =(Tabla3[[#This Row],[Inversión real 2017]]-Tabla3[[#This Row],[Inversión real 2016]])/Tabla3[[#This Row],[Inversión real 2016]] -> -0.78686349 | O80: =(Tabla3[[#This Row],[Inversión real 2017]]-Tabla3[[#This Row],[Inversión real 2018]])/Tabla3[[#This Row],[Inversión real 2018]] -> -0.91969003
B81: CRISTOBAL | C81: COLOMBIA | D81: Tecnología | E81: Trabajo | F81: Buscando trabajo | G81: SI | H81: 4 | I81: 5 | J81: $ - | K81: $ - | L81: 12862402 | M81: 68922404 | N81: =(Tabla3[[#This Row],[Inversión real 2017]]-Tabla3[[#This Row],[Inversión real 2016]])/Tabla3[[#This Row],[Inversión real 2016]] -> -0.81337851 | O81: =(Tabla3[[#This Row],[Inversión real 2017]]-Tabla3[[#This Row],[Inversión real 2018]])/Tabla3[[#This Row],[Inversión real 2018]] -> #VALUE!
B82: RODRIGO | C82: COLOMBIA | D82: Sector Real | E82: Trabajo | F82: Buscando trabajo | G82: SI | H82: 9 | I82: 9 | J82: $ - | K82: $ - | L82: 46914257 | M82: 43734508 | N82: =(Tabla3[[#This Row],[Inversión real 2017]]-Tabla3[[#This Row],[Inversión real 2016]])/Tabla3[[#This Row],[Inversión real 2016]] -> 0.072705722 | O82: =(Tabla3[[#This Row],[Inversión real 2017]]-Tabla3[[#This Row],[Inversión real 2018]])/Tabla3[[#This Row],[Inversión real 2018]] -> #VALUE!
B83: JESUS | C83: OTRO PAÍS DEL MUNDO | D83: Educación | E83: Conocimiento | F83: Académico | G83: NO | H83: 6 | I83: 10 | J83: $ - | K83: $ - | L83: 95212463 | M83: $ - | N83: =(Tabla3[[#This Row],[Inversión real 2017]]-Tabla3[[#This Row],[Inversión real 2016]])/Tabla3[[#This Row],[Inversión real 2016]] -> #VALUE! | O83: =(Tabla3[[#This Row],[Inversión real 2017]]-Tabla3[[#This Row],[Inversión real 2018]])/Tabla3[[#This Row],[Inversión real 2018]] -> #VALUE!
B84: JORGE | C84: CHILE | D84: Tecnología | E84: Inversión | F84: Socio capitalista | G84: NO | H84: 3 | I84: 9 | J84: 5000000 | K84: 32915397 | L84: 74493461 | M84: 151779 | N84: =(Tabla3[[#This Row],[Inversión real 2017]]-Tabla3[[#This Row],[Inversión real 2016]])/Tabla3[[#This Row],[Inversión real 2016]] -> 489.80216 | O84: =(Tabla3[[#This Row],[Inversión real 2017]]-Tabla3[[#This Row],[Inversión real 2018]])/Tabla3[[#This Row],[Inversión real 2018]] -> 1.2631798
B85: JULIO | C85: COLOMBIA | D85: Sector Real | E85: Trabajo | F85: Buscando trabajo | G85: NO | H85: 3 | I85: 7 | J85: $ - | K85: $ - | L85: 43223505 | M85: $ - | N85: =(Tabla3[[#This Row],[Inversión real 2017]]-Tabla3[[#This Row],[Inversión real 2016]])/Tabla3[[#This Row],[Inversión real 2016]] -> #VALUE! | O85: =(Tabla3[[#This Row],[Inversión real 2017]]-Tabla3[[#This Row],[Inversión real 2018]])/Tabla3[[#This Row],[Inversión real 2018]] -> #VALUE!
B86: MARIA MÓNICA | C86: COLOMBIA | D86: Tecnología | E86: Trabajo | F86: Buscando trabajo | G86: NO | H86: 7 | I86: 10 | J86: $ - | K86: $ - | L86: 14141858 | M86: 87162317 | N86: =(Tabla3[[#This Row],[Inversión real 2017]]-Tabla3[[#This Row],[Inversión real 2016]])/Tabla3[[#This Row],[Inversión real 2016]] -> -0.83775262 | O86: =(Tabla3[[#This Row],[Inversión real 2017]]-Tabla3[[#This Row],[Inversión real 2018]])/Tabla3[[#This Row],[Inversión real 2018]] -> #VALUE!
B87: IGNACIO | C87: COLOMBIA | D87: Tecnología | E87: Trabajo | F87: Buscando trabajo | G87: NO | H87: 3 | I87: 7 | J87: $ - | K87: $ - | L87: 29525162 | M87: $ - | N87: =(Tabla3[[#This Row],[Inversión real 2017]]-Tabla3[[#This Row],[Inversión real 2016]])/Tabla3[[#This Row],[Inversión real 2016]] -> #VALUE! | O87: =(Tabla3[[#This Row],[Inversión real 2017]]-Tabla3[[#This Row],[Inversión real 2018]])/Tabla3[[#This Row],[Inversión real 2018]] -> #VALUE!
B88: GABRIEL | C88: COLOMBIA | D88: Tecnología | E88: Trabajo | F88: Ofreciendo trabajo | G88: SI | H88: 7 | I88: 4 | J88: $ - | K88: $ - | L88: 29366791 | M88: 89805774 | N88: =(Tabla3[[#This Row],[Inversión real 2017]]-Tabla3[[#This Row],[Inversión real 2016]])/Tabla3[[#This Row],[Inversión real 2016]] -> -0.67299663 | O88: =(Tabla3[[#This Row],[Inversión real 2017]]-Tabla3[[#This Row],[Inversión real 2018]])/Tabla3[[#This Row],[Inversión real 2018]] -> #VALUE!
B89: MARTIN | C89: COLOMBIA | D89: Tecnología | E89: Trabajo | F89: Buscando trabajo | G89: SI | H89: 9 | I89: 5 | J89: $ - | K89: $ - | L89: 73195518 | M89: 10695678 | N89: =(Tabla3[[#This Row],[Inversión real 2017]]-Tabla3[[#This Row],[Inversión real 2016]])/Tabla3[[#This Row],[Inversión real 2016]] -> 5.8434669 | O89: =(Tabla3[[#This Row],[Inversión real 2017]]-Tabla3[[#This Row],[Inversión real 2018]])/Tabla3[[#This Row],[Inversión real 2018]] -> #VALUE!
B90: FERNANDO | C90: COLOMBIA | D90: Tecnología | E90: Trabajo | F90: Buscando trabajo | G90: NO | H90: 3 | I90: 6 | J90: $ - | K90: $ - | L90: 1432950 | M90: 29672451 | N90: =(Tabla3[[#This Row],[Inversión real 2017]]-Tabla3[[#This Row],[Inversión real 2016]])/Tabla3[[#This Row],[Inversión real 2016]] -> -0.95170773 | O90: =(Tabla3[[#This Row],[Inversión real 2017]]-Tabla3[[#This Row],[Inversión real 2018]])/Tabla3[[#This Row],[Inversión real 2018]] -> #VALUE!
B91: ALEJANDRO | C91: COLOMBIA | D91: Tecnología | E91: Inversión | F91: Socio capitalista | G91: SI | H91: 8 | I91: 7 | J91: 1000000 | K91: 77159264 | L91: $ - | M91: 97234303 | N91: =(Tabla3[[#This Row],[Inversión real 2017]]-Tabla3[[#This Row],[Inversión real 2016]])/Tabla3[[#This Row],[Inversión real 2016]] -> #VALUE! | O91: =(Tabla3[[#This Row],[Inversión real 2017]]-Tabla3[[#This Row],[Inversión real 2018]])/Tabla3[[#This Row],[Inversión real 2018]] -> #VALUE!
B92: SANTIAGO | C92: CHILE | D92: Tecnología | E92: Inversión | F92: Socio capitalista | G92: NO | H92: 7 | I92: 10 | J92: 100000000 | K92: 12451199 | L92: 74231711 | M92: 42951226 | N92: =(Tabla3[[#This Row],[Inversión real 2017]]-Tabla3[[#This Row],[Inversión real 2016]])/Tabla3[[#This Row],[Inversión real 2016]] -> 0.72827921 | O92: =(Tabla3[[#This Row],[Inversión real 2017]]-Tabla3[[#This Row],[Inversión real 2018]])/Tabla3[[#This Row],[Inversión real 2018]] -> 4.9618123
B93: LUCAS | C93: COLOMBIA | D93: Construcción | E93: Inversión | F93: Socio capitalista | G93: SI | H93: 3 | I93: 9 | J93: 90000000 | K93: 13287929 | L93: 27090183 | M93: 79518711 | N93: =(Tabla3[[#This Row],[Inversión real 2017]]-Tabla3[[#This Row],[Inversión real 2016]])/Tabla3[[#This Row],[Inversión real 2016]] -> -0.65932316 | O93: =(Tabla3[[#This Row],[Inversión real 2017]]-Tabla3[[#This Row],[Inversión real 2018]])/Tabla3[[#This Row],[Inversión real 2018]] -> 1.0387062
B94: PEDRO | C94: CHILE | D94: Educación | E94: Conocimiento | F94: Académico | G94: NO | H94: 6 | I94: 5 | J94: $ - | K94: $ - | L94: 20898506 | M94: 24525645 | N94: =(Tabla3[[#This Row],[Inversión real 2017]]-Tabla3[[#This Row],[Inversión real 2016]])/Tabla3[[#This Row],[Inversión real 2016]] -> -0.14789169 | O94: =(Tabla3[[#This Row],[Inversión real 2017]]-Tabla3[[#This Row],[Inversión real 2018]])/Tabla3[[#This Row],[Inversión real 2018]] -> #VALUE!
B95: ENRIQUE | C95: COLOMBIA | D95: Tecnología | E95: Inversión | F95: Socio capitalista | G95: NO | H95: 8 | I95: 7 | J95: 5000000 | K95: 37959268 | L95: 69132389 | M95: 99564796 | N95: =(Tabla3[[#This Row],[Inversión real 2017]]-Tabla3[[#This Row],[Inversión real 2016]])/Tabla3[[#This Row],[Inversión real 2016]] -> -0.30565429 | O95: =(Tabla3[[#This Row],[Inversión real 2017]]-Tabla3[[#This Row],[Inversión real 2018]])/Tabla3[[#This Row],[Inversión real 2018]] -> 0.82122556
B96: VICTOR | C96: COLOMBIA | D96: Tecnología | E96: Trabajo | F96: Buscando trabajo | G96: SI | H96: 3 | I96: 6 | J96: $ - | K96: $ - | L96: 26450622 | M96: 4227264 | N96: =(Tabla3[[#This Row],[Inversión real 2017]]-Tabla3[[#This Row],[Inversión real 2016]])/Tabla3[[#This Row],[Inversión real 2016]] -> 5.2571493 | O96: =(Tabla3[[#This Row],[Inversión real 2017]]-Tabla3[[#This Row],[Inversión real 2018]])/Tabla3[[#This Row],[Inversión real 2018]] -> #VALUE!
B97: ALFREDO | C97: PARAGUAY | D97: Tecnología | E97: Trabajo | F97: Buscando trabajo | G97: SI | H97: 6 | I97: 5 | J97: $ - | K97: $ - | L97: $ - | M97: 54376640 | N97: =(Tabla3[[#This Row],[Inversión real 2017]]-Tabla3[[#This Row],[Inversión real 2016]])/Tabla3[[#This Row],[Inversión real 2016]] -> #VALUE! | O97: =(Tabla3[[#This Row],[Inversión real 2017]]-Tabla3[[#This Row],[Inversión real 2018]])/Tabla3[[#This Row],[Inversión real 2018]] -> #VALUE!
B98: DARIO | C98: COLOMBIA | D98: Tecnología | E98: Inversión | F98: Socio de proyecto | G98: NO | H98: 7 | I98: 9 | J98: 90000000 | K98: 29991873 | L98: 39252741 | M98: 15542722 | N98: =(Tabla3[[#This Row],[Inversión real 2017]]-Tabla3[[#This Row],[Inversión real 2016]])/Tabla3[[#This Row],[Inversión real 2016]] -> 1.525474 | O98: =(Tabla3[[#This Row],[Inversión real 2017]]-Tabla3[[#This Row],[Inversión real 2018]])/Tabla3[[#This Row],[Inversión real 2018]] -> 0.30877925
B99: DIEGO | C99: COLOMBIA | D99: Tecnología | E99: Inversión | F99: Socio de proyecto | G99: NO | H99: 6 | I99: 10 | J99: 10000000 | K99: 7303129 | L99: 3765621 | M99: 18125151 | N99: =(Tabla3[[#This Row],[Inversión real 2017]]-Tabla3[[#This Row],[Inversión real 2016]])/Tabla3[[#This Row],[Inversión real 2016]] -> -0.79224333 | O99: =(Tabla3[[#This Row],[Inversión real 2017]]-Tabla3[[#This Row],[Inversión real 2018]])/Tabla3[[#This Row],[Inversión real 2018]] -> -0.48438252
B100: ISMAEL | C100: BRASIL | D100: Tecnología | E100: Inversión | F100: Socio de proyecto | G100: NO | H100: 3 | I100: 9 | J100: 30000000 | K100: 44457754 | L100: $ - | M100: 62249765 | N100: =(Tabla3[[#This Row],[Inversión real 2017]]-Tabla3[[#This Row],[Inversión real 2016]])/Tabla3[[#This Row],[Inversión real 2016]] -> #VALUE! | O100: =(Tabla3[[#This Row],[Inversión real 2017]]-Tabla3[[#This Row],[Inversión real 2018]])/Tabla3[[#This Row],[Inversión real 2018]] -> #VALUE!
B101: JAIME | C101: COLOMBIA | D101: Tecnología | E101: Inversión | F101: Socio capitalista | G101: NO | H101: 4 | I101: 10 | J101: 10000000 | K101: 54467236 | L101: $ - | M101: 1234692 | N101: =(Tabla3[[#This Row],[Inversión real 2017]]-Tabla3[[#This Row],[Inversión real 2016]])/Tabla3[[#This Row],[Inversión real 2016]] -> #VALUE! | O101: =(Tabla3[[#This Row],[Inversión real 2017]]-Tabla3[[#This Row],[Inversión real 2018]])/Tabla3[[#This Row],[Inversión real 2018]] -> #VALUE!
...

Sheet SUMAPRODUCTO
B2: ¿Cuál es la calificación promedio? Teniendo en cuenta que la feria tiene una ponderación del 70% y la de proyectos un 30%. | D2: PONDERACION, TOMAR EN CUENTA EL VALOR QUE TIENE CADA UNO AL MOMENTO DE SACAR ELPROMEDIO | E2: ¿Cuál es la calificación promedio? Teniendo en cuenta que la feria tiene una ponderación del 70% y la de proyectos un 30%.
B3: Tipo | C3: Cantidad | E3: Tipo | F3: Peso porcentual | G3: Cantidad
B4: Feria | C4: 5.8 | E4: Feria | F4: 0.7 | G4: 5.8
B5: Proyectos | C5: 7.6 | D5: PROMEDIO NORMAL | E5: Proyectos | F5: 0.3 | G5: 7.6
B6: Agregado | C6: =(C4*70%)+(C5*30%) -> 6.34 | D6: =AVERAGE(C4:C5) -> 6.7 | E6: Agregado | G6: =SUMPRODUCT(F4:F5,G4:G5) -> 6.34 | H6: SUMAPRODUCTO PARA TENER EL AGREGADO
C7: PROMEDIO AGREGADO
C9: Puntaje del semestre - Clase de Excel
B10: Estudiante | C10: Quiz | D10: Parcial 1 | E10: Parcial final | F10: Puntaje Final
B11: Peso porcentual | C11: 0.2 | D11: 0.3 | E11: 0.5 | G11: recuerda SUMAPRODUCTO ES LA FORMULA
B12: Pedro | C12: 9 | D12: 6 | E12: 5 | F12: =SUMPRODUCT($C$11:$E$11,C12:E12) -> 6.1
B13: Juan | C13: 3 | D13: 4 | E13: 8 | F13: =SUMPRODUCT($C$11:$E$11,C13:E13) -> 5.8
B14: Diego | C14: 4 | D14: 8 | E14: 7 | F14: =SUMPRODUCT($C$11:$E$11,C14:E14) -> 6.7 | H14: ¿Cómo fijar datos adecuadamente?
B15: Felipe | C15: 7 | D15: 8 | E15: 9 | F15: =SUMPRODUCT($C$11:$E$11,C15:E15) -> 8.3
B16: Mateo | C16: 5 | D16: 4 | E16: 7 | F16: =SUMPRODUCT($C$11:$E$11,C16:E16) -> 5.7
B17: Laura | C17: 10 | D17: 9 | E17: 8 | F17: =SUMPRODUCT($C$11:$E$11,C17:E17) -> 8.7
B18: Mónica | C18: 3 | D18: 6 | E18: 6 | F18: =SUMPRODUCT($C$11:$E$11,C18:E18) -> 5.4
B19: Luisa | C19: 4 | D19: 4 | E19: 9 | F19: =SUMPRODUCT($C$11:$E$11,C19:E19) -> 6.5 | G19: Reto | H19: Obtener Puntaje Final de cada estudiante (cada elemento tiene una equivalencia)
B20: Felipe | C20: 4 | D20: 3 | E20: 6 | F20: =SUMPRODUCT($C$11:$E$11,C20:E20) -> 4.7 | G20: (pausa) | H20: R. Cuantos estudiantes tiene la tabla (con fórmula)
B21: Orlando | C21: 5 | D21: 4 | E21: 7 | F21: =SUMPRODUCT($C$11:$E$11,C21:E21) -> 5.7 | H21: R. Cuál es el promedio de los estudiantes (Puntaje Final) | I21: =AVERAGE(F12:F27) -> 6.20625
B22: Marcela | C22: 6 | D22: 5 | E22: 8 | F22: =SUMPRODUCT($C$11:$E$11,C22:E22) -> 6.7
B23: María | C23: 4 | D23: 3 | E23: 6 | F23: =SUMPRODUCT($C$11:$E$11,C23:E23) -> 4.7
B24: César | C24: 5 | D24: 4 | E24: 7 | F24: =SUMPRODUCT($C$11:$E$11,C24:E24) -> 5.7
B25: Catalina | C25: 6 | D25: 5 | E25: 8 | F25: =SUMPRODUCT($C$11:$E$11,C25:E25) -> 6.7
B26: Natalia | C26: 3 | D26: 6 | E26: 6 | F26: =SUMPRODUCT($C$11:$E$11,C26:E26) -> 5.4
B27: Lorena | C27: 4 | D27: 4 | E27: 9 | F27: =SUMPRODUCT($C$11:$E$11,C27:E27) -> 6.5
B29: CONTEO | C29: =COUNTA(B12:B27) -> 16
J30: Fijación de Datos
J31: 1 | K31: 2 | L31: 3
J32: 4 | K32: 5 | L32: 6
J33: 7 | K33: 8 | L33: 9
J35: =SUM(J31:J33) -> 12 | K35: =SUM(K31:K33) -> 15 | L35: =SUM(L31:L33) -> 18 | M35: SIN FIJAR NADA SE VA MOVIENDO LA FILA | O35: =SUM($J31:$J33) -> 12 | P35: =SUM($J31:$J33) -> 12 | Q35: =SUM($J31:$J33) -> 12 | R35: COLUMNAS
J36: =SUM(J32:J34) -> 11 | K36: =SUM(K32:K34) -> 13 | L36: =SUM(L32:L34) -> 15 | O36: =SUM($J32:$J34) -> 11 | P36: =SUM($J32:$J34) -> 11 | Q36: =SUM($J32:$J34) -> 11 | R36: FIJAS
J37: =SUM(J33:J35) -> 19 | K37: =SUM(K33:K35) -> 23 | L37: =SUM(L33:L35) -> 27 | O37: =SUM($J33:$J35) -> 19 | P37: =SUM($J33:$J35) -> 19 | Q37: =SUM($J33:$J35) -> 19 | R37: =SUMA($J31:$J33)
J38: =SUM(J34:J36) -> 23 | K38: =SUM(K34:K36) -> 28 | L38: =SUM(L34:L36) -> 33 | O38: =SUM($J34:$J36) -> 23 | P38: =SUM($J34:$J36) -> 23 | Q38: =SUM($J34:$J36) -> 23
J39: =SUM(J35:J37) -> 42 | K39: =SUM(K35:K37) -> 51 | L39: =SUM(L35:L37) -> 60 | O39: =SUM($J35:$J37) -> 42 | P39: =SUM($J35:$J37) -> 42 | Q39: =SUM($J35:$J37) -> 42
J42: =SUM($J$31:$J$33) -> 12 | K42: =SUM($J$31:$J$33) -> 12 | L42: =SUM($J$31:$J$33) -> 12 | M42: FIJO TODO NO SE MUEVE DE LA MISMA FILA | O42: =SUM(J$31:J$33) -> 12 | P42: =SUM(K$31:K$33) -> 15 | Q42: =SUM(L$31:L$33) -> 18 | R42: FILAS FIJAS
J43: =SUM($J$31:$J$33) -> 12 | K43: =SUM($J$31:$J$33) -> 12 | L43: =SUM($J$31:$J$33) -> 12 | O43: =SUM(J$31:J$33) -> 12 | P43: =SUM(K$31:K$33) -> 15 | Q43: =SUM(L$31:L$33) -> 18
J44: =SUM($J$31:$J$33) -> 12 | K44: =SUM($J$31:$J$33) -> 12 | L44: =SUM($J$31:$J$33) -> 12 | O44: =SUM(J$31:J$33) -> 12 | P44: =SUM(K$31:K$33) -> 15 | Q44: =SUM(L$31:L$33) -> 18
J45: =SUM($J$31:$J$33) -> 12 | K45: =SUM($J$31:$J$33) -> 12 | L45: =SUM($J$31:$J$33) -> 12 | O45: =SUM(J$31:J$33) -> 12 | P45: =SUM(K$31:K$33) -> 15 | Q45: =SUM(L$31:L$33) -> 18
J46: =SUM($J$31:$J$33) -> 12 | K46: =SUM($J$31:$J$33) -> 12 | L46: =SUM($J$31:$J$33) -> 12 | O46: =SUM(J$31:J$33) -> 12 | P46: =SUM(K$31:K$33) -> 15 | Q46: =SUM(L$31:L$33) -> 18
J49: Volver arriba con hipervínculo

Sheet SUMAPRODUCTO2
K2: Primer punto
A3: Nombre | B3: País de orígen | C3: Sector | D3: Intención frente a los proyectos | E3: Detalle inversión | F3: Conoce algún proyecto o no | G3: Calificación Feria (1-10) | H3: Calificación Proyectos (1-10) | I3: Calificación personal | K3: ¿Cuál es la calificación de cada uno, teniendo en cuenta que los proyectos tienen un peso porcentual del 80% y la feria del 20%?
A4: ALBERT | B4: COLOMBIA | C4: Educación | D4: Conocimiento | E4: Académico | F4: NO | G4: 3 | H4: 8 | I4: =AVERAGE($G4:$H4) -> 5.5 | K4: Cuantas personas tiene la tabla (con fórmula) | Q4: =COUNTA(A4:A103) -> 100
A5: JOAQUIN | B5: COLOMBIA | C5: Tecnología | D5: Inversión | E5: Socio capitalista | F5: SI | G5: 8 | H5: 7 | I5: =AVERAGE($G5:$H5) -> 7.5 | K5: Cuál es el promedio de ambas calificaciones? (Puntaje Final)
A6: CESAR | B6: COLOMBIA | C6: Construcción | D6: Trabajo | E6: Ofreciendo trabajo | F6: NO | G6: 5 | H6: 10 | I6: =AVERAGE($G6:$H6) -> 7.5 | K6: PROMEDIOS PONDERADOS | L6: 0.2 | M6: 0.8 | N6: PROMEDIO NORMAL | P6: PROMEDIOS PONDERADOS
A7: HUGO | B7: COLOMBIA | C7: Tecnología | D7: Inversión | E7: Socio de proyecto | F7: NO | G7: 4 | H7: 8 | I7: =AVERAGE($G7:$H7) -> 6 | K7: =SUMPRODUCT(L6:M6,L7:M7) -> 7.21 | L7: =AVERAGE(G4:G103) -> 5.81 | M7: =AVERAGE(H4:H103) -> 7.56 | N7: =AVERAGE(L7:M7) -> 6.685 | P7: PROMEDIOS PONDERADOS
A8: VALENTINA | B8: COLOMBIA | C8: Construcción | D8: Inversión | E8: Socio capitalista | F8: NO | G8: 4 | H8: 9 | I8: =AVERAGE($G8:$H8) -> 6.5
A9: GERMAN | B9: COLOMBIA | C9: Tecnología | D9: Inversión | E9: Socio de proyecto | F9: NO | G9: 9 | H9: 7 | I9: =AVERAGE($G9:$H9) -> 8 | K9: Segundo punto
A10: DAVID | B10: COLOMBIA | C10: Tecnología | D10: Trabajo | E10: Ofreciendo trabajo | F10: NO | G10: 5 | H10: 9 | I10: =AVERAGE($G10:$H10) -> 7 | K10: Crear un hipervínculo que lo lleve a la celda Q100 de esta hoja.
A11: MIGUEL | B11: COLOMBIA | C11: Tecnología | D11: Inversión | E11: Socio capitalista | F11: SI | G11: 8 | H11: 10 | I11: =AVERAGE($G11:$H11) -> 9
A12: VICENTE | B12: COLOMBIA | C12: Agroindustrial | D12: Trabajo | E12: Ofreciendo trabajo | F12: SI | G12: 8 | H12: 3 | I12: =AVERAGE($G12:$H12) -> 5.5
A13: ALVARO | B13: COLOMBIA | C13: Sector Real | D13: Inversión | E13: Socio de proyecto | F13: NO | G13: 5 | H13: 9 | I13: =AVERAGE($G13:$H13) -> 7
A14: LUIS | B14: VENEZUELA | C14: Tecnología | D14: Inversión | E14: Socio de proyecto | F14: NO | G14: 4 | H14: 5 | I14: =AVERAGE($G14:$H14) -> 4.5
A15: DANIEL | B15: COLOMBIA | C15: Tecnología | D15: Inversión | E15: Socio de proyecto | F15: NO | G15: 3 | H15: 8 | I15: =AVERAGE($G15:$H15) -> 5.5
A16: JOSEP | B16: COLOMBIA | C16: Construcción | D16: Trabajo | E16: Buscando trabajo | F16: NO | G16: 7 | H16: 9 | I16: =AVERAGE($G16:$H16) -> 8
A17: EDUARDO | B17: COLOMBIA | C17: Tecnología | D17: Trabajo | E17: Buscando trabajo | F17: SI | G17: 4 | H17: 8 | I17: =AVERAGE($G17:$H17) -> 6
A18: LEONEL | B18: COLOMBIA | C18: Sector Real | D18: Inversión | E18: Socio capitalista | F18: NO | G18: 9 | H18: 10 | I18: =AVERAGE($G18:$H18) -> 9.5
A19: JORDI | B19: COLOMBIA | C19: Educación | D19: Conocimiento | E19: Académico | F19: NO | G19: 4 | H19: 6 | I19: =AVERAGE($G19:$H19) -> 5
A20: ESTEBAN | B20: COLOMBIA | C20: Tecnología | D20: Inversión | E20: Socio capitalista | F20: NO | G20: 5 | H20: 7 | I20: =AVERAGE($G20:$H20) -> 6
A21: JONATHAN | B21: COLOMBIA | C21: Educación | D21: Conocimiento | E21: Académico | F21: NO | G21: 6 | H21: 7 | I21: =AVERAGE($G21:$H21) -> 6.5
A22: FELIPE | B22: BRASIL | C22: Sector Real | D22: Trabajo | E22: Buscando trabajo | F22: SI | G22: 9 | H22: 8 | I22: =AVERAGE($G22:$H22) -> 8.5
... A103: ADRIAN | B103: COLOMBIA | C103: Tecnología | D103: Trabajo | E103: Ofreciendo trabajo | F103: NO | G103: 5 | H103: 10 | I103: =AVERAGE($G103:$H103) -> 7.5
B105: TRANSPONER
A106: Nombre | B106: ALBERT | C106: JOAQUIN | D106: CESAR | E106: HUGO | F106: VALENTINA | G106: GERMAN | H106: DAVID | I106: MIGUEL | J106: VICENTE | K106: ALVARO | L106: LUIS | M106: DANIEL | N106: JOSEP | O106: EDUARDO | P106: LEONEL | Q106: JORDI | R106: ESTEBAN | S106: JONATHAN | T106: FELIPE | U106: JOSE | V106: FELIX | W106: PABLO | X106: MANUEL | Y106: LORENZO | Z106: ISAAC | AA106: MARIA | AB106: ANGEL | AC106: ADOLFO | AD106: ERNESTO | AE106: RAFAEL | AF106: TOMAS | AG106: MARCOS | AH106: MARIO | AI106: ARTURO | AJ106: EUGENIO | AK106: JUAN | AL106: GONZALO | AM106: ANTONIO | AN106: EMILIO | AO106: AGUSTIN | AP106: JUAN PABLO | AQ106: FRANCISCO | AR106: MARC | AS106: ROBERTO | AT106: CARLOS | AU106: JOEL | AV106: MARIANO | AW106: OSCAR | AX106: ALEXANDER | AY106: BORJA | AZ106: RAUL | BA106: ALEX | BB106: IVAN | BC106: SAMUEL | BD106: ANDRES | BE106: NORA | BF106: ANDRÉS | BG106: CRISTIAN | BH106: JAVIER | BI106: DOMINGO | BJ106: NICOLAS | BK106: HECTOR | BL106: RICARDO | BM106: ALBERTO | BN106: RUBEN | BO106: SEBASTIAN | BP106: MOHAMED | BQ106: MARCO | BR106: SERGIO | BS106: RAMON | BT106: GREGORIO | BU106: JOAN | BV106: ALFONSO | BW106: GUILLERMO | BX106: CHRISTIAN | BY106: MATEO | BZ106: JULIAN | CA106: CRISTOBAL | CB106: RODRIGO | CC106: JESUS | CD106: JORGE | CE106: JULIO | CF106: MARIA MÓNICA | CG106: IGNACIO | CH106: GABRIEL | CI106: MARTIN | CJ106: FERNANDO | CK106: ALEJANDRO | CL106: SANTIAGO | CM106: LUCAS | CN106: PEDRO | CO106: ENRIQUE | CP106: VICTOR | CQ106: ALFREDO | CR106: DARIO | CS106: DIEGO | CT106: ISMAEL | CU106: JAIME | CV106: SALVADOR | CW106: ADRIAN
A107: País de orígen | B107: COLOMBIA | C107: COLOMBIA | D107: COLOMBIA | E107: COLOMBIA | F107: COLOMBIA | G107: COLOMBIA | H107: COLOMBIA | I107: COLOMBIA | J107: COLOMBIA | K107: COLOMBIA | L107: VENEZUELA | M107: COLOMBIA | N107: COLOMBIA | O107: COLOMBIA | P107: COLOMBIA | Q107: COLOMBIA | R107: COLOMBIA | S107: COLOMBIA | T107: BRASIL | U107: COLOMBIA | V107: COLOMBIA | W107: COLOMBIA | X107: ARGENTINA | Y107: COLOMBIA | Z107: COLOMBIA | AA107: COLOMBIA | AB107: COLOMBIA | AC107: COLOMBIA | AD107: COLOMBIA | AE107: COLOMBIA | AF107: COLOMBIA | AG107: BRASIL | AH107: COLOMBIA | AI107: COLOMBIA | AJ107: COLOMBIA | AK107: COLOMBIA | AL107: COLOMBIA | AM107: COLOMBIA | AN107: COLOMBIA | AO107: COLOMBIA | AP107: COLOMBIA | AQ107: COLOMBIA | AR107: COLOMBIA | AS107: COLOMBIA | AT107: COLOMBIA | AU107: COLOMBIA | AV107: COLOMBIA | AW107: BRASIL | AX107: COLOMBIA | AY107: ECUADOR | AZ107: BRASIL | BA107: URUGUAY | BB107: COLOMBIA | BC107: COLOMBIA | BD107: COLOMBIA | BE107: CHILE | BF107: COLOMBIA | BG107: COLOMBIA | BH107: BOLIVIA | BI107: COLOMBIA | BJ107: COLOMBIA | BK107: COLOMBIA | BL107: COLOMBIA | BM107: COLOMBIA | BN107: COLOMBIA | BO107: COLOMBIA | BP107: COLOMBIA | BQ107: PERU | BR107: BRASIL | BS107: COLOMBIA | BT107: COLOMBIA | BU107: COLOMBIA | BV107: COLOMBIA | BW107: COLOMBIA | BX107: COLOMBIA | BY107: URUGUAY | BZ107: COLOMBIA | CA107: COLOMBIA | CB107: COLOMBIA | CC107: OTRO PAÍS DEL MUNDO | CD107: CHILE | CE107: COLOMBIA | CF107: COLOMBIA | CG107: COLOMBIA | CH107: COLOMBIA | CI107: COLOMBIA | CJ107: COLOMBIA | CK107: COLOMBIA | CL107: CHILE | CM107: COLOMBIA | CN107: CHILE | CO107: COLOMBIA | CP107: COLOMBIA | CQ107: PARAGUAY | CR107: COLOMBIA | CS107: COLOMBIA | CT107: BRASIL | CU107: COLOMBIA | CV107: COLOMBIA | CW107: COLOMBIA
A108: Sector | B108: Educación | C108: Tecnología | D108: Construcción | E108: Tecnología | F108: Construcción | G108: Tecnología | H108: Tecnología | I108: Tecnología | J108: Agroindustrial | K108: Sector Real | L108: Tecnología | M108: Tecnología | N108: Construcción | O108: Tecnología | P108: Sector Real | Q108: Educación | R108: Tecnología | S108: Educación | T108: Sector Real | U108: Tecnología | V108: Tecnología | W108: Agroindustrial | X108: Sector Real | Y108: Agroindustrial | Z108: Tecnología | AA108: Sector Real | AB108: Tecnología | AC108: Sector Real | AD108: Tecnología | AE108: Sector Real | AF108: Agroindustrial | AG108: Sector Real | AH108: Tecnología | AI108: Sector Real | AJ108: Construcción | AK108: Tecnología | AL108: Tecnología | AM108: Construcción | AN108: Sector Real | AO108: Tecnología | AP108: Tecnología | AQ108: Tecnología | AR108: Sector Real | AS108: Tecnología | AT108: Tecnología | AU108: Sector Real | AV108: Sector Real | AW108: Tecnología | AX108: Construcción | AY108: Tecnología | AZ108: Tecnología | BA108: Tecnología | BB108: Tecnología | BC108: Sector Real | BD108: Tecnología | BE108: Sector Real | BF108: Tecnología | BG108: Tecnología | BH108: Tecnología | BI108: Educación | BJ108: Sector Real | BK108: Tecnología | BL108: Sector Real | BM108: Sector Real | BN108: Tecnología | BO108: Tecnología | BP108: Agroindustrial | BQ108: Tecnología | BR108: Sector Real | BS108: Agroindustrial | BT108: Agroindustrial | BU108: Tecnología | BV108: Tecnología | BW108: Agroindustrial | BX108: Construcción | BY108: Tecnología | BZ108: Tecnología | CA108: Tecnología | CB108: Sector Real | CC108: Educación | CD108: Tecnología | CE108: Sector Real | CF108: Tecnología | CG108: Tecnología | CH108: Tecnología | CI108: Tecnología | CJ108: Tecnología | CK108: Tecnología | CL108: Tecnología | CM108: Construcción | CN108: Educación | CO108: Tecnología | CP108: Tecnología | CQ108: Tecnología | CR108: Tecnología | CS108: Tecnología | CT108: Tecnología | CU108: Tecnología | CV108: Tecnología | CW108: Tecnología
A109: Intención frente a los proyectos | B109: Conocimiento | C109: Inversión | D109: Trabajo | E109: Inversión | F109: Inversión | G109: Inversión | H109: Trabajo | I109: Inversión | J109: Trabajo | K109: Inversión | L109: Inversión | M109: Inversión | N109: Trabajo | O109: Trabajo | P109: Inversión | Q109: Conocimiento | R109: Inversión | S109: Conocimiento | T109: Trabajo | U109: Inversión | V109: Inversión | W109: Inversión | X109: Trabajo | Y109: Inversión | Z109: Inversión | AA109: Inversión | AB109: Trabajo | AC109: Trabajo | AD109: Inversión | AE109: Inversión | AF109: Trabajo | AG109: Trabajo | AH109: Inversión | AI109: Inversión | AJ109: Inversión | AK109: Conocimiento | AL109: Inversión | AM109: Inversión | AN109: Trabajo | AO109: Inversión | AP109: Inversión | AQ109: Inversión | AR109: Inversión | AS109: Inversión | AT109: Inversión | AU109: Inversión | AV109: Trabajo | AW109: Inversión | AX109: Inversión | AY109: Inversión | AZ109: Trabajo | BA109: Inversión | BB109: Inversión | BC109: Inversión | BD109: Trabajo | BE109: Inversión | BF109: Inversión | BG109: Trabajo | BH109: Inversión | BI109: Conocimiento | BJ109: Inversión | BK109: Inversión | BL109: Inversión | BM109: Trabajo | BN109: Inversión | BO109: Inversión | BP109: Trabajo | BQ109: Conocimiento | BR109: Inversión | BS109: Trabajo | BT109: Inversión | BU109: Trabajo | BV109: Inversión | BW109: Inversión | BX109: Trabajo | BY109: Trabajo | BZ109: Inversión | CA109: Trabajo | CB109: Trabajo | CC109: Conocimiento | CD109: Inversión | CE109: Trabajo | CF109: Trabajo | CG109: Trabajo | CH109: Trabajo | CI109: Trabajo | CJ109: Trabajo | CK109: Inversión | CL109: Inversión | CM109: Inversión | CN109: Conocimiento | CO109: Inversión | CP109: Trabajo | CQ109: Trabajo | CR109: Inversión | CS109: Inversión | CT109: Inversión | CU109: Inversión | CV109: Inversión | CW109: Trabajo
A110: Detalle inversión | B110: Académico | C110: Socio capitalista | D110: Ofreciendo trabajo | E110: Socio de proyecto | F110: Socio capitalista | G110: Socio de proyecto | H110: Ofreciendo trabajo | I110: Socio capitalista | J110: Ofreciendo trabajo | K110: Socio de proyecto | L110: Socio de proyecto | M110: Socio de proyecto | N110: Buscando trabajo | O110: Buscando trabajo | P110: Socio capitalista | Q110: Académico | R110: Socio capitalista | S110: Académico | T110: Buscando trabajo | U110: Socio de proyecto | V110: Socio de proyecto | W110: Socio capitalista | X110: Ofreciendo trabajo | Y110: Socio capitalista | Z110: Socio capitalista | AA110: Socio capitalista | AB110: Ofreciendo trabajo | AC110: Ofreciendo trabajo | AD110: Socio de proyecto | AE110: Socio capitalista | AF110: Ofreciendo trabajo | AG110: Buscando trabajo | AH110: Socio capitalista | AI110: Socio de proyecto | AJ110: Socio de proyecto | AK110: Otro tipo | AL110: Socio capitalista | AM110: Socio de proyecto | AN110: Buscando trabajo | AO110: Socio de proyecto | AP110: Socio de proyecto | AQ110: Socio de proyecto | AR110: Socio de proyecto | AS110: Socio de proyecto | AT110: Socio de proyecto | AU110: Socio de proyecto | AV110: Ofreciendo trabajo | AW110: Socio de proyecto | AX110: Socio capitalista | AY110: Socio capitalista | AZ110: Ofreciendo trabajo | BA110: Socio capitalista | BB110: Socio de proyecto | BC110: Socio de proyecto | BD110: Buscando trabajo | BE110: Socio de proyecto | BF110: Socio capitalista | BG110: Buscando trabajo | BH110: Socio capitalista | BI110: Académico | BJ110: Socio capitalista | BK110: Socio de proyecto | BL110: Socio capitalista | BM110: Ofreciendo trabajo | BN110: Socio capitalista | BO110: Socio capitalista | BP110: Buscando trabajo | BQ110: Otro tipo | BR110: Socio de proyecto | BS110: Buscando trabajo | BT110: Socio de proyecto | BU110: Ofreciendo trabajo | BV110: Socio de proyecto | BW110: Socio capitalista | BX110: Ofreciendo trabajo | BY110: Buscando trabajo | BZ110: Socio capitalista | CA110: Buscando trabajo | CB110: Buscando trabajo | CC110: Académico | CD110: Socio capitalista | CE110: Buscando trabajo | CF110: Buscando trabajo | CG110: Buscando trabajo | CH110: Ofreciendo trabajo | CI110: Buscando trabajo | CJ110: Buscando trabajo | CK110: Socio capitalista | CL110: Socio capitalista | CM110: Socio capitalista | CN110: Académico | CO110: Socio capitalista | CP110: Buscando trabajo | CQ110: Buscando trabajo | CR110: Socio de proyecto | CS110: Socio de proyecto | CT110: Socio de proyecto | CU110: Socio capitalista | CV110: Socio de proyecto | CW110: Ofreciendo trabajo
A111: Conoce algún proyecto o no | B111: NO | C111: SI | D111: NO | E111: NO | F111: NO | G111: NO | H111: NO | I111: SI | J111: SI | K111: NO | L111: NO | M111: NO | N111: NO | O111: SI | P111: NO | Q111: NO | R111: NO | S111: NO | T111: SI | U111: NO | V111: NO | W111: SI | X111: NO | Y111: NO | Z111: NO | AA111: NO | AB111: NO | AC111: NO | AD111: NO | AE111: SI | AF111: NO | AG111: SI | AH111: NO | AI111: NO | AJ111: NO | AK111: NO | AL111: NO | AM111: NO | AN111: NO | AO111: NO | AP111: SI | AQ111: SI | AR111: SI | AS111: SI | AT111: NO | AU111: NO | AV111: NO | AW111: SI | AX111: SI | AY111: NO | AZ111: SI | BA111: NO | BB111: NO | BC111: NO | BD111: SI | BE111: NO | BF111: NO | BG111: NO | BH111: NO | BI111: NO | BJ111: NO | BK111: NO | BL111: NO | BM111: NO | BN111: SI | BO111: NO | BP111: NO | BQ111: NO | BR111: SI | BS111: NO | BT111: SI | BU111: NO | BV111: SI | BW111: NO | BX111: NO | BY111: NO | BZ111: SI | CA111: SI | CB111: SI | CC111: NO | CD111: NO | CE111: NO | CF111: NO | CG111: NO | CH111: SI | CI111: SI | CJ111: NO | CK111: SI | CL111: NO | CM111: SI | CN111: NO | CO111: NO | CP111: SI | CQ111: SI | CR111: NO | CS111: NO | CT111: NO | CU111: NO | CV111: NO | CW111: NO
A112: Calificación Feria (1-10) | B112: 3 | C112: 8 | D112: 5 | E112: 4 | F112: 4 | G112: 9 | H112: 5 | I112: 8 | J112: 8 | K112: 5 | L112: 4 | M112: 3 | N112: 7 | O112: 4 | P112: 9 | Q112: 4 | R112: 5 | S112: 6 | T112: 9 | U112: 5 | V112: 6 | W112: 6 | X112: 8 | Y112: 7 | Z112: 9 | AA112: 3 | AB112: 6 | AC112: 9 | AD112: 8 | AE112: 8 | AF112: 6 | AG112: 3 | AH112: 6 | AI112: 6 | AJ112: 8 | AK112: 5 | AL112: 9 | AM112: 4 | AN112: 4 | AO112: 9 | AP112: 6 | AQ112: 8 | AR112: 6 | AS112: 7 | AT112: 5 | AU112: 3 | AV112: 7 | AW112: 5 | AX112: 9 | AY112: 6 | AZ112: 7 | BA112: 5 | BB112: 4 | BC112: 7 | BD112: 3 | BE112: 3 | BF112: 7 | BG112: 5 | BH112: 9 | BI112: 4 | BJ112: 5 | BK112: 3 | BL112: 3 | BM112: 5 | BN112: 7 | BO112: 7 | BP112: 5 | BQ112: 7 | BR112: 8 | BS112: 3 | BT112: 8 | BU112: 5 | BV112: 6 | BW112: 3 | BX112: 8 | BY112: 5 | BZ112: 8 | CA112: 4 | CB112: 9 | CC112: 6 | CD112: 3 | CE112: 3 | CF112: 7 | CG112: 3 | CH112: 7 | CI112: 9 | CJ112: 3 | CK112: 8 | CL112: 7 | CM112: 3 | CN112: 6 | CO112: 8 | CP112: 3 | CQ112: 6 | CR112: 7 | CS112: 6 | CT112: 3 | CU112: 4 | CV112: 4 | CW112: 5
A113: Calificación Proyectos (1-10) | B113: 8 | C113: 7 | D113: 10 | E113: 8 | F113: 9 | G113: 7 | H113: 9 | I113: 10 | J113: 3 | K113: 9 | L113: 5 | M113: 8 | N113: 9 | O113: 8 | P113: 10 | Q113: 6 | R113: 7 | S113: 7 | T113: 8 | U113: 6 | V113: 7 | W113: 10 | X113: 5 | Y113: 10 | Z113: 10 | AA113: 9 | AB113: 2 | AC113: 9 | AD113: 7 | AE113: 8 | AF113: 8 | AG113: 5 | AH113: 7 | AI113: 10 | AJ113: 5 | AK113: 7 | AL113: 7 | AM113: 7 | AN113: 9 | AO113: 5 | AP113: 10 | AQ113: 8 | AR113: 10 | AS113: 5 | AT113: 7 | AU113: 8 | AV113: 9 | AW113: 6 | AX113: 9 | AY113: 8 | AZ113: 5 | BA113: 6 | BB113: 6 | BC113: 5 | BD113: 9 | BE113: 6 | BF113: 10 | BG113: 9 | BH113: 5 | BI113: 8 | BJ113: 10 | BK113: 10 | BL113: 10 | BM113: 5 | BN113: 7 | BO113: 5 | BP113: 4 | BQ113: 7 | BR113: 9 | BS113: 5 | BT113: 10 | BU113: 7 | BV113: 6 | BW113: 6 | BX113: 10 | BY113: 7 | BZ113: 9 | CA113: 5 | CB113: 9 | CC113: 10 | CD113: 9 | CE113: 7 | CF113: 10 | CG113: 7 | CH113: 4 | CI113: 5 | CJ113: 6 | CK113: 7 | CL113: 10 | CM113: 9 | CN113: 5 | CO113: 7 | CP113: 6 | CQ113: 5 | CR113: 9 | CS113: 10 | CT113: 9 | CU113: 10 | CV113: 10 | CW113: 10
A114: Calificación personal | B114: =AVERAGE(B$112:B$113) -> 5.5 | C114: =AVERAGE(C$112:C$113) -> 7.5 | D114: =AVERAGE(D$112:D$113) -> 7.5 | E114: =AVERAGE(E$112:E$113) -> 6 | F114: =AVERAGE(F$112:F$113) -> 6.5 | G114: =AVERAGE(G$112:G$113) -> 8 | H114: =AVERAGE(H$112:H$113) -> 7 | I114: =AVERAGE(I$112:I$113) -> 9 | ... CW114: =AVERAGE(CW$112:CW$113) -> 7.5

Sheet BUSCARV
B2: CIUDAD | C2: VENTAS | D2: CIUDADANOS | E2: EMPRESA | H2: CIUDAD | I2: VENTAS | J2: CIUDADANOS | K2: EMPRESA
B3: EL SALTO | C3: 20000 | D3: 200000 | E3: FOXCONN | H3: TLAJOMULCO | I3: =VLOOKUP(H3,Tabla1[],2,FALSE) -> 2569852 | J3: =VLOOKUP($H$3,Tabla1[],3,FALSE) -> 800000 | K3: =VLOOKUP($H$3,Tabla1[],4,FALSE) -> AEROPUERTO
B4: GUADALAJARA | C4: 50000 | D4: 30000 | E4: NVIDIA
B5: TLAQUEPAQUE | C5: 20001 | D5: 520000 | E5: GAPP | H5: CIUDAD | I5: VENTAS | J5: CIUDADANOS | K5: EMPRESA
B6: ZAPOPAN | C6: 685200 | D6: 600000 | E6: JABIL | H6: GUADALAJARA | I6: =VLOOKUP(H6,Tabla1[],2,FALSE) -> 50000 | J6: =VLOOKUP(H6,Tabla1[],3,FALSE) -> 30000 | K6: =VLOOKUP(H6,Tabla1[],4,FALSE) -> NVIDIA
B7: TLAJOMULCO | C7: 2569852 | D7: 800000 | E7: AEROPUERTO

Sheet buscarv2
B3: Gerente | C3: Ventas | E3: Nombre | F3: Expectativa inversión 2018 | G3: Inversión real 2018 | H3: BUSCARV con # de columna DIGITADA
B4: Orlando | C4: 10 | E4: JOAQUIN | F4: =IFERROR(VLOOKUP(E4,B14:L113,10,FALSE),"error") -> 10000000 | G4: =IFERROR(VLOOKUP(E4,$B$14:$L$113,11,FALSE),"error") -> 40848959
B5: Juan | C5: 20
B6: Pedro | C6: 30
B8: BUSCAR V | F8: 10 | G8: 11
B9: Gerente | C9: Ventas | E9: Nombre | F9: Expectativa inversión 2018 | G9: Inversión real 2018 | H9: BUSCARV con # de columna FORMULADA
B10: Orlando | C10: =VLOOKUP(B10,B4:C6,2,FALSE) -> 10 | E10: Luis | F10: =IFERROR(VLOOKUP(E10,$B$14:$L$113,F8,FALSE),"no encontrado") -> no encontrado | G10: =IFERROR(VLOOKUP(E10,$B$14:$L$113,G8,FALSE),"no encontrado") -> no encontrado
B11: Luis | C11: =IFERROR(VLOOKUP(B11,B4:C6,2,FALSE),"no encontrado") -> no encontrado
B13: Nombre | C13: Mail | D13: País de orígen | E13: Sector | F13: Intención frente a los proyectos | G13: Detalle inversión | H13: Conoce algún proyecto o no | I13: Calificación Feria (1-10) | J13: Calificación Proyectos (1-10) | K13: Expectativa inversión 2018 | L13: Inversión real 2018 | M13: Inversión real 2017 | N13: Inversión real 2016
B14: ALBERT | C14: ALBERT@gmail.com | D14: COLOMBIA | E14: Educación | F14: Conocimiento | G14: Académico | H14: NO | I14: 3 | J14: 8 | K14: $ - | L14: $ - | M14: =IFERROR(VLOOKUP(B14,'SUM PROM Y REDONDEO'!A2:J101,9,FALSE),"no eno") -> 96781441 | N14: =IFERROR(VLOOKUP(B14,'SUM PROM Y REDONDEO'!A2:J101,10,FALSE),"no eno") -> 47643060
B15: JOAQUIN | C15: JOAQUIN@gmail.com | D15: COLOMBIA | E15: Tecnología | F15: Inversión | G15: Socio capitalista | H15: SI | I15: 8 | J15: 7 | K15: 10000000 | L15: 40848959 | M15: =IFERROR(VLOOKUP(B15,'SUM PROM Y REDONDEO'!A3:J102,9,FALSE),"no eno") -> 92963332 | N15: =IFERROR(VLOOKUP(B15,'SUM PROM Y REDONDEO'!A3:J102,10,FALSE),"no eno") -> 47565587
B16: CESAR | C16: CESAR@gmail.com | D16: COLOMBIA | E16: Construcción | F16: Trabajo | G16: Ofreciendo trabajo | H16: NO | I16: 5 | J16: 10 | K16: $ - | L16: $ - | M16: =IFERROR(VLOOKUP(B16,'SUM PROM Y REDONDEO'!A4:J103,9,FALSE),"no eno") -> 49599457 | N16: =IFERROR(VLOOKUP(B16,'SUM PROM Y REDONDEO'!A4:J103,10,FALSE),"no eno") -> 0
B17: HUGO | C17: HUGO@gmail.com | D17: COLOMBIA | E17: Tecnología | F17: Inversión | G17: Socio de proyecto | H17: NO | I17: 4 | J17: 8 | K17: 10000000 | L17: 78308880 | M17: =IFERROR(VLOOKUP(B17,'SUM PROM Y REDONDEO'!A5:J104,9,FALSE),"no eno") -> 3248026 | N17: =IFERROR(VLOOKUP(B17,'SUM PROM Y REDONDEO'!A5:J104,10,FALSE),"no eno") -> 27143270
B18: VALENTINA | C18: VALENTINA@gmail.com | D18: COLOMBIA | E18: Construcción | F18: Inversión | G18: Socio capitalista | H18: NO | I18: 4 | J18: 9 | K18: 50000000 | L18: 2910571 | M18: =IFERROR(VLOOKUP(B18,'SUM PROM Y REDONDEO'!A6:J105,9,FALSE),"no eno") -> 37561085 | N18: =IFERROR(VLOOKUP(B18,'SUM PROM Y REDONDEO'!A6:J105,10,FALSE),"no eno") -> 19598007
B19: GERMAN | C19: GERMAN@gmail.com | D19: COLOMBIA | E19: Tecnología | F19: Inversión | G19: Socio de proyecto | H19: NO | I19: 9 | J19: 7 | K19: 90000000 | L19: 50075523 | M19: =IFERROR(VLOOKUP(B19,'SUM PROM Y REDONDEO'!A7:J106,9,FALSE),"no eno") -> 59142617 | N19: =IFERROR(VLOOKUP(B19,'SUM PROM Y REDONDEO'!A7:J106,10,FALSE),"no eno") -> 95314026
B20: DAVID | C20: DAVID@gmail.com | D20: COLOMBIA | E20: Tecnología | F20: Trabajo | G20: Ofreciendo trabajo | H20: NO | I20: 5 | J20: 9 | K20: $ - | L20: $ - | M20: =IFERROR(VLOOKUP(B20,'SUM PROM Y REDONDEO'!A8:J107,9,FALSE),"no eno") -> 0 | N20: =IFERROR(VLOOKUP(B20,'SUM PROM Y REDONDEO'!A8:J107,10,FALSE),"no eno") -> 67714973
B21: MIGUEL | C21: MIGUEL@gmail.com | D21: COLOMBIA | E21: Tecnología | F21: Inversión | G21: Socio capitalista | H21: SI | I21: 8 | J21: 10 | K21: 1000000 | L21: 5305190 | M21: =IFERROR(VLOOKUP(B21,'SUM PROM Y REDONDEO'!A9:J108,9,FALSE),"no eno") -> 53291805 | N21: =IFERROR(VLOOKUP(B21,'SUM PROM Y REDONDEO'!A9:J108,10,FALSE),"no eno") -> 84809282
B22: VICENTE | C22: VICENTE@gmail.com | D22: COLOMBIA | E22: Agroindustrial | F22: Trabajo | G22: Ofreciendo trabajo | H22: SI | I22: 8 | J22: 3 | K22: $ - | L22: $ - | M22: =IFERROR(VLOOKUP(B22,'SUM PROM Y REDONDEO'!A10:J109,9,FALSE),"no eno") -> 50085574 | N22: =IFERROR(VLOOKUP(B22,'SUM PROM Y REDONDEO'!A10:J109,10,FALSE),"no eno") -> 42495353
B23: ALVARO | C23: ALVARO@gmail.com | D23: COLOMBIA | E23: Sector Real | F23: Inversión | G23: Socio de proyecto | H23: NO | I23: 5 | J23: 9 | K23: 10000000 | L23: 38941670 | M23: =IFERROR(VLOOKUP(B23,'SUM PROM Y REDONDEO'!A11:J110,9,FALSE),"no eno") -> 67846781 | N23: =IFERROR(VLOOKUP(B23,'SUM PROM Y REDONDEO'!A11:J110,10,FALSE),"no eno") -> 87726693
B24: LUIS | C24: LUIS@gmail.com | D24: VENEZUELA | E24: Tecnología | F24: Inversión | G24: Socio de proyecto | H24: NO | I24: 4 | J24: 5 | K24: 1000000 | L24: 28926771 | M24: =IFERROR(VLOOKUP(B24,'SUM PROM Y REDONDEO'!A12:J111,9,FALSE),"no eno") -> 56939610 | N24: =IFERROR(VLOOKUP(B24,'SUM PROM Y REDONDEO'!A12:J111,10,FALSE),"no eno") -> 92726884
B25: DANIEL | C25: DANIEL@gmail.com | D25: COLOMBIA | E25: Tecnología | F25: Inversión | G25: Socio de proyecto | H25: NO | I25: 3 | J25: 8 | K25: 1000000 | L25: 34252074 | M25: =IFERROR(VLOOKUP(B25,'SUM PROM Y REDONDEO'!A13:J112,9,FALSE),"no eno") -> 0 | N25: =IFERROR(VLOOKUP(B25,'SUM PROM Y REDONDEO'!A13:J112,10,FALSE),"no eno") -> 22994819
B26: JOSEP | C26: JOSEP@gmail.com | D26: COLOMBIA | E26: Construcción | F26: Trabajo | G26: Buscando trabajo | H26: NO | I26: 7 | J26: 9 | K26: $ - | L26: $ - | M26: =IFERROR(VLOOKUP(B26,'SUM PROM Y REDONDEO'!A14:J113,9,FALSE),"no eno") -> 45347826 | N26: =IFERROR(VLOOKUP(B26,'SUM PROM Y REDONDEO'!A14:J113,10,FALSE),"no eno") -> 14301768
B27: EDUARDO | C27: EDUARDO@gmail.com | D27: COLOMBIA | E27: Tecnología | F27: Trabajo | G27: Buscando trabajo | H27: SI | I27: 4 | J27: 8 | K27: $ - | L27: $ - | M27: =IFERROR(VLOOKUP(B27,'SUM PROM Y REDONDEO'!A15:J114,9,FALSE),"no eno") -> 71453938 | N27: =IFERROR(VLOOKUP(B27,'SUM PROM Y REDONDEO'!A15:J114,10,FALSE),"no eno") -> 38593802
B28: LEONEL | C28: LEONEL@gmail.com | D28: COLOMBIA | E28: Sector Real | F28: Inversión | G28: Socio capitalista | H28: NO | I28: 9 | J28: 10 | K28: 20000000 | L28: 32346156 | M28: =IFERROR(VLOOKUP(B28,'SUM PROM Y REDONDEO'!A16:J115,9,FALSE),"no eno") -> 22346275 | N28: =IFERROR(VLOOKUP(B28,'SUM PROM Y REDONDEO'!A16:J115,10,FALSE),"no eno") -> 73743047
B29: JORDI | C29: JORDI@gmail.com | D29: COLOMBIA | E29: Educación | F29: Conocimiento | G29: Académico | H29: NO | I29: 4 | J29: 6 | K29: $ - | L29: $ - | M29: =IFERROR(VLOOKUP(B29,'SUM PROM Y REDONDEO'!A17:J116,9,FALSE),"no eno") -> 96357193 | N29: =IFERROR(VLOOKUP(B29,'SUM PROM Y REDONDEO'!A17:J116,10,FALSE),"no eno") -> 67901582
B30: ESTEBAN | C30: ESTEBAN@gmail.com | D30: COLOMBIA | E30: Tecnología | F30: Inversión | G30: Socio capitalista | H30: NO | I30: 5 | J30: 7 | K30: 100000000 | L30: 72903049 | M30: =IFERROR(VLOOKUP(B30,'SUM PROM Y REDONDEO'!A18:J117,9,FALSE),"no eno") -> 67375493 | N30: =IFERROR(VLOOKUP(B30,'SUM PROM Y REDONDEO'!A18:J117,10,FALSE),"no eno") -> 4753995
B31: JONATHAN | C31: JONATHAN@gmail.com | D31: COLOMBIA | E31: Educación | F31: Conocimiento | G31: Académico | H31: NO | I31: 6 | J31: 7 | K31: $ - | L31: $ - | M31: =IFERROR(VLOOKUP(B31,'SUM PROM Y REDONDEO'!A19:J118,9,FALSE),"no eno") -> 80671052 | N31: =IFERROR(VLOOKUP(B31,'SUM PROM Y REDONDEO'!A19:J118,10,FALSE),"no eno") -> 58339670
B32: FELIPE | C32: FELIPE@gmail.com | D32: BRASIL | E32: Sector Real | F32: Trabajo | G32: Buscando trabajo | H32: SI | I32: 9 | J32: 8 | K32: $ - | L32: $ - | M32: =IFERROR(VLOOKUP(B32,'SUM PROM Y REDONDEO'!A20:J119,9,FALSE),"no eno") -> no eno | N32: =IFERROR(VLOOKUP(B32,'SUM PROM Y REDONDEO'!A20:J119,10,FALSE),"no eno") -> no eno
B33: JOSE | C33: JOSE@gmail.com | D33: COLOMBIA | E33: Tecnología | F33: Inversión | G33: Socio de proyecto | H33: NO | I33: 5 | J33: 6 | K33: 1000000 | L33: 96696256 | M33: =IFERROR(VLOOKUP(B33,'SUM PROM Y REDONDEO'!A21:J120,9,FALSE),"no eno") -> 62106884 | N33: =IFERROR(VLOOKUP(B33,'SUM PROM Y REDONDEO'!A21:J120,10,FALSE),"no eno") -> 85228190
B34: FELIX | C34: FELIX@gmail.com | D34: COLOMBIA | E34: Tecnología | F34: Inversión | G34: Socio de proyecto | H34: NO | I34: 6 | J34: 7 | K34: 10000000 | L34: 51531809 | M34: =IFERROR(VLOOKUP(B34,'SUM PROM Y REDONDEO'!A22:J121,9,FALSE),"no eno") -> 99819688 | N34: =IFERROR(VLOOKUP(B34,'SUM PROM Y REDONDEO'!A22:J121,10,FALSE),"no eno") -> 24233431
B35: PABLO | C35: PABLO@gmail.com | D35: COLOMBIA | E35: Agroindustrial | F35: Inversión | G35: Socio capitalista | H35: SI | I35: 6 | J35: 10 | K35: $ - | L35: $ - | M35: =IFERROR(VLOOKUP(B35,'SUM PROM Y REDONDEO'!A23:J122,9,FALSE),"no eno") -> 34214902 | N35: =IFERROR(VLOOKUP(B35,'SUM PROM Y REDONDEO'!A23:J122,10,FALSE),"no eno") -> 24896611
B36: MANUEL | C36: MANUEL@gmail.com | D36: ARGENTINA | E36: Sector Real | F36: Trabajo | G36: Ofreciendo trabajo | H36: NO | I36: 8 | J36: 5 | K36: $ - | L36: $ - | M36: =IFERROR(VLOOKUP(B36,'SUM PROM Y REDONDEO'!A24:J123,9,FALSE),"no eno") -> 7121108 | N36: =IFERROR(VLOOKUP(B36,'SUM PROM Y REDONDEO'!A24:J123,10,FALSE),"no eno") -> 6991703
B37: LORENZO | C37: LORENZO@gmail.com | D37: COLOMBIA | E37: Agroindustrial | F37: Inversión | G37: Socio capitalista | H37: NO | I37: 7 | J37: 10 | K37: 20000000 | L37: 93037614 | M37: =IFERROR(VLOOKUP(B37,'SUM PROM Y REDONDEO'!A25:J124,9,FALSE),"no eno") -> 48185946 | N37: =IFERROR(VLOOKUP(B37,'SUM PROM Y REDONDEO'!A25:J124,10,FALSE),"no eno") -> 75039300
B38: ISAAC | C38: ISAAC@gmail.com | D38: COLOMBIA | E38: Tecnología | F38: Inversión | G38: Socio capitalista | H38: NO | I38: 9 | J38: 10 | K38: 90000000 | L38: 62088180 | M38: =IFERROR(VLOOKUP(B38,'SUM PROM Y REDONDEO'!A26:J125,9,FALSE),"no eno") -> 18047519 | N38: =IFERROR(VLOOKUP(B38,'SUM PROM Y REDONDEO'!A26:J125,10,FALSE),"no eno") -> 3738158
B39: MARIA | C39: MARIA@gmail.com | D39: COLOMBIA | E39: Sector Real | F39: Inversión | G39: Socio capitalista | H39: NO | I39: 3 | J39: 9 | K39: 1000000 | L39: 1160848 | M39: =IFERROR(VLOOKUP(B39,'SUM PROM Y REDONDEO'!A27:J126,9,FALSE),"no eno") -> 32268145 | N39: =IFERROR(VLOOKUP(B39,'SUM PROM Y REDONDEO'!A27:J126,10,FALSE),"no eno") -> 13339687
B40: ANGEL | C40: ANGEL@gmail.com | D40: COLOMBIA | E40: Tecnología | F40: Trabajo | G40: Ofreciendo trabajo | H40: NO | I40: 6 | J40: 2 | K40: $ - | L40: $ - | M40: =IFERROR(VLOOKUP(B40,'SUM PROM Y REDONDEO'!A28:J127,9,FALSE),"no eno") -> 21224611 | N40: =IFERROR(VLOOKUP(B40,'SUM PROM Y REDONDEO'!A28:J127,10,FALSE),"no eno") -> 62562457
B41: ADOLFO | C41: ADOLFO@gmail.com | D41: COLOMBIA | E41: Sector Real | F41: Trabajo | G41: Ofreciendo trabajo | H41: NO | I41: 9 | J41: 9 | K41: $ - | L41: $ - | M41: =IFERROR(VLOOKUP(B41,'SUM PROM Y REDONDEO'!A29:J128,9,FALSE),"no eno") -> 85434615 | N41: =IFERROR(VLOOKUP(B41,'SUM PROM Y REDONDEO'!A29:J128,10,FALSE),"no eno") -> 79508333
B42: ERNESTO | C42: ERNESTO@gmail.com | D42: COLOMBIA | E42: Tecnología | F42: Inversión | G42: Socio de proyecto | H42: NO | I42: 8 | J42: 7 | K42: 90000000 | L42: 23888885 | M42: =IFERROR(VLOOKUP(B42,'SUM PROM Y REDONDEO'!A30:J129,9,FALSE),"no eno") -> 68725539 | N42: =IFERROR(VLOOKUP(B42,'SUM PROM Y REDONDEO'!A30:J129,10,FALSE),"no eno") -> 78613526
B43: RAFAEL | C43: RAFAEL@gmail.com | D43: COLOMBIA | E43: Sector Real | F43: Inversión | G43: Socio capitalista | H43: SI | I43: 8 | J43: 8 | K43: 10000000 | L43: 23464528 | M43: =IFERROR(VLOOKUP(B43,'SUM PROM Y REDONDEO'!A31:J130,9,FALSE),"no eno") -> 904543 | N43: =IFERROR(VLOOKUP(B43,'SUM PROM Y REDONDEO'!A31:J130,10,FALSE),"no eno") -> 0
B44: TOMAS | C44: TOMAS@gmail.com | D44: COLOMBIA | E44: Agroindustrial | F44: Trabajo | G44: Ofreciendo trabajo | H44: NO | I44: 6 | J44: 8 | K44: $ - | L44: $ - | M44: =IFERROR(VLOOKUP(B44,'SUM PROM Y REDONDEO'!A32:J131,9,FALSE),"no eno") -> 66204884 | N44: =IFERROR(VLOOKUP(B44,'SUM PROM Y REDONDEO'!A32:J131,10,FALSE),"no eno") -> 27801447
B45: MARCOS | C45: MARCOS@gmail.com | D45: BRASIL | E45: Sector Real | F45: Trabajo | G45: Buscando trabajo | H45: SI | I45: 3 | J45: 5 | K45: $ - | L45: $ - | M45: =IFERROR(VLOOKUP(B45,'SUM PROM Y REDONDEO'!A33:J132,9,FALSE),"no eno") -> 30987169 | N45: =IFERROR(VLOOKUP(B45,'SUM PROM Y REDONDEO'!A33:J132,10,FALSE),"no eno") -> 7339680
B46: MARIO | C46: MARIO@gmail.com | D46: COLOMBIA | E46: Tecnología | F46: Inversión | G46: Socio capitalista | H46: NO | I46: 6 | J46: 7 | K46: 10000000 | L46: 22390348 | M46: =IFERROR(VLOOKUP(B46,'SUM PROM Y REDONDEO'!A34:J133,9,FALSE),"no eno") -> 24476166 | N46: =IFERROR(VLOOKUP(B46,'SUM PROM Y REDONDEO'!A34:J133,10,FALSE),"no eno") -> 0
B47: ARTURO | C47: ARTURO@gmail.com | D47: COLOMBIA | E47: Sector Real | F47: Inversión | G47: Socio de proyecto | H47: NO | I47: 6 | J47: 10 | K47: 20000000 | L47: 31670482 | M47: =IFERROR(VLOOKUP(B47,'SUM PROM Y REDONDEO'!A35:J134,9,FALSE),"no eno") -> 15619630 | N47: =IFERROR(VLOOKUP(B47,'SUM PROM Y REDONDEO'!A35:J134,10,FALSE),"no eno") -> 59838390
B48: EUGENIO | C48: EUGENIO@gmail.com | D48: COLOMBIA | E48: Construcción | F48: Inversión | G48: Socio de proyecto | H48: NO | I48: 8 | J48: 5 | K48: 20000000 | L48: 81056910 | M48: =IFERROR(VLOOKUP(B48,'SUM PROM Y REDONDEO'!A36:J135,9,FALSE),"no eno") -> 96438403 | N48: =IFERROR(VLOOKUP(B48,'SUM PROM Y REDONDEO'!A36:J135,10,FALSE),"no eno") -> 90723423
B49: JUAN | C49: JUAN@gmail.com | D49: COLOMBIA | E49: Tecnología | F49: Conocimiento | G49: Otro tipo | H49: NO | I49: 5 | J49: 7 | K49: $ - | L49: $ - | M49: =IFERROR(VLOOKUP(B49,'SUM PROM Y REDONDEO'!A37:J136,9,FALSE),"no eno") -> 0 | N49: =IFERROR(VLOOKUP(B49,'SUM PROM Y REDONDEO'!A37:J136,10,FALSE),"no eno") -> 52936315
B50: GONZALO | C50: GONZALO@gmail.com | D50: COLOMBIA | E50: Tecnología | F50: Inversión | G50: Socio capitalista | H50: NO | I50: 9 | J50: 7 | K50: 30000000 | L50: 91413171 | M50: =IFERROR(VLOOKUP(B50,'SUM PROM Y REDONDEO'!A38:J137,9,FALSE),"no eno") -> 13211402 | N50: =IFERROR(VLOOKUP(B50,'SUM PROM Y REDONDEO'!A38:J137,10,FALSE),"no eno") -> 0
B51: ANTONIO | C51: ANTONIO@gmail.com | D51: COLOMBIA | E51: Construcción | F51: Inversión | G51: Socio de proyecto | H51: NO | I51: 4 | J51: 7 | K51: 1000000 | L51: 87347043 | M51: =IFERROR(VLOOKUP(B51,'SUM PROM Y REDONDEO'!A39:J138,9,FALSE),"no eno") -> 50796112 | N51: =IFERROR(VLOOKUP(B51,'SUM PROM Y REDONDEO'!A39:J138,10,FALSE),"no eno") -> 72757830
B52: EMILIO | C52: EMILIO@gmail.com | D52: COLOMBIA | E52: Sector Real | F52: Trabajo | G52: Buscando trabajo | H52: NO | I52: 4 | J52: 9 | K52: $ - | L52: $ - | M52: =IFERROR(VLOOKUP(B52,'SUM PROM Y REDONDEO'!A40:J139,9,FALSE),"no eno") -> 38721754 | N52: =IFERROR(VLOOKUP(B52,'SUM PROM Y REDONDEO'!A40:J139,10,FALSE),"no eno") -> 77230635
B53: AGUSTIN | C53: AGUSTIN@gmail.com | D53: COLOMBIA | E53: Tecnología | F53: Inversión | G53: Socio de proyecto | H53: NO | I53: 9 | J53: 5 | K53: 10000000 | L53: 43538967 | M53: =IFERROR(VLOOKUP(B53,'SUM PROM Y REDONDEO'!A41:J140,9,FALSE),"no eno") -> 5161300 | N53: =IFERROR(VLOOKUP(B53,'SUM PROM Y REDONDEO'!A41:J140,10,FALSE),"no eno") -> 85417673
B54: JUAN PABLO | C54: JUAN PABLO@gmail.com | D54: COLOMBIA | E54: Tecnología | F54: Inversión | G54: Socio de proyecto | H54: SI | I54: 6 | J54: 10 | K54: 1000000 | L54: 95899452 | M54: =IFERROR(VLOOKUP(B54,'SUM PROM Y REDONDEO'!A42:J141,9,FALSE),"no eno") -> 2565664 | N54: =IFERROR(VLOOKUP(B54,'SUM PROM Y REDONDEO'!A42:J141,10,FALSE),"no eno") -> 39602953
B55: FRANCISCO | C55: FRANCISCO@gmail.com | D55: COLOMBIA | E55: Tecnología | F55: Inversión | G55: Socio de proyecto | H55: SI | I55: 8 | J55: 8 | K55: 1000000 | L55: 81347428 | M55: =IFERROR(VLOOKUP(B55,'SUM PROM Y REDONDEO'!A43:J142,9,FALSE),"no eno") -> 10860215 | N55: =IFERROR(VLOOKUP(B55,'SUM PROM Y REDONDEO'!A43:J142,10,FALSE),"no eno") -> 28637290
B56: MARC | C56: MARC@gmail.com | D56: COLOMBIA | E56: Sector Real | F56: Inversión | G56: Socio de proyecto | H56: SI | I56: 6 | J56: 10 | K56: 30000000 | L56: 52442860 | M56: =IFERROR(VLOOKUP(B56,'SUM PROM Y REDONDEO'!A44:J143,9,FALSE),"no eno") -> 2659881 | N56: =IFERROR(VLOOKUP(B56,'SUM PROM Y REDONDEO'!A44:J143,10,FALSE),"no eno") -> 80287314
B57: ROBERTO | C57: ROBERTO@gmail.com | D57: COLOMBIA | E57: Tecnología | F57: Inversión | G57: Socio de proyecto | H57: SI | I57: 7 | J57: 5 | K57: 10000000 | L57: 96199053 | M57: =IFERROR(VLOOKUP(B57,'SUM PROM Y REDONDEO'!A45:J144,9,FALSE),"no eno") -> 31746355 | N57: =IFERROR(VLOOKUP(B57,'SUM PROM Y REDONDEO'!A45:J144,10,FALSE),"no eno") -> 80063468
B58: CARLOS | C58: CARLOS@gmail.com | D58: COLOMBIA | E58: Tecnología | F58: Inversión | G58: Socio de proyecto | H58: NO | I58: 5 | J58: 7 | K58: 1000000 | L58: 71783742 | M58: =IFERROR(VLOOKUP(B58,'SUM PROM Y REDONDEO'!A46:J145,9,FALSE),"no eno") -> 64667814 | N58: =IFERROR(VLOOKUP(B58,'SUM PROM Y REDONDEO'!A46:J145,10,FALSE),"no eno") -> 70653180
B59: JOEL | C59: JOEL@gmail.com | D59: COLOMBIA | E59: Sector Real | F59: Inversión | G59: Socio de proyecto | H59: NO | I59: 3 | J59: 8 | K59: 90000000 | L59: 94913746 | M59: =IFERROR(VLOOKUP(B59,'SUM PROM Y REDONDEO'!A47:J146,9,FALSE),"no eno") -> 74083223 | N59: =IFERROR(VLOOKUP(B59,'SUM PROM Y REDONDEO'!A47:J146,10,FALSE),"no eno") -> 31617670
B60: MARIANO | C60: MARIANO@gmail.com | D60: COLOMBIA | E60: Sector Real | F60: Trabajo | G60: Ofreciendo trabajo | H60: NO | I60: 7 | J60: 9 | K60: $ - | L60: $ - | M60: =IFERROR(VLOOKUP(B60,'SUM PROM Y REDONDEO'!A48:J147,9,FALSE),"no eno") -> 67753952 | N60: =IFERROR(VLOOKUP(B60,'SUM PROM Y REDONDEO'!A48:J147,10,FALSE),"no eno") -> 77205812
B61: OSCAR | C61: OSCAR@gmail.com | D61: BRASIL | E61: Tecnología | F61: Inversión | G61: Socio de proyecto | H61: SI | I61: 5 | J61: 6 | K61: 30000000 | L61: 33477783 | M61: =IFERROR(VLOOKUP(B61,'SUM PROM Y REDONDEO'!A49:J148,9,FALSE),"no eno") -> 0 | N61: =IFERROR(VLOOKUP(B61,'SUM PROM Y REDONDEO'!A49:J148,10,FALSE),"no eno") -> 27651635
B62: ALEXANDER | C62: ALEXANDER@gmail.com | D62: COLOMBIA | E62: Construcción | F62: Inversión | G62: Socio capitalista | H62: SI | I62: 9 | J62: 9 | K62: 50000000 | L62: 2702447 | M62: =IFERROR(VLOOKUP(B62,'SUM PROM Y REDONDEO'!A50:J149,9,FALSE),"no eno") -> 0 | N62: =IFERROR(VLOOKUP(B62,'SUM PROM Y REDONDEO'!A50:J149,10,FALSE),"no eno") -> 44671760
B63: BORJA | C63: BORJA@gmail.com | D63: ECUADOR | E63: Tecnología | F63: Inversión | G63: Socio capitalista | H63: NO | I63: 6 | J63: 8 | K63: 50000000 | L63: 70787848 | M63: =IFERROR(VLOOKUP(B63,'SUM PROM Y REDONDEO'!A51:J150,9,FALSE),"no eno") -> 33368202 | N63: =IFERROR(VLOOKUP(B63,'SUM PROM Y REDONDEO'!A51:J150,10,FALSE),"no eno") -> 43277527
B64: RAUL | C64: RAUL@gmail.com | D64: BRASIL | E64: Tecnología | F64: Trabajo | G64: Ofreciendo trabajo | H64: SI | I64: 7 | J64: 5 | K64: $ - | L64: $ - | M64: =IFERROR(VLOOKUP(B64,'SUM PROM Y REDONDEO'!A52:J151,9,FALSE),"no eno") -> 46563396 | N64: =IFERROR(VLOOKUP(B64,'SUM PROM Y REDONDEO'!A52:J151,10,FALSE),"no eno") -> 63313535
B65: ALEX | C65: ALEX@gmail.com | D65: URUGUAY | E65: Tecnología | F65: Inversión | G65: Socio capitalista | H65: NO | I65: 5 | J65: 6 | K65: 20000000 | L65: 40064620 | M65: =IFERROR(VLOOKUP(B65,'SUM PROM Y REDONDEO'!A53:J152,9,FALSE),"no eno") -> 98137438 | N65: =IFERROR(VLOOKUP(B65,'SUM PROM Y REDONDEO'!A53:J152,10,FALSE),"no eno") -> 0
B66: IVAN | C66: IVAN@gmail.com | D66: COLOMBIA | E66: Tecnología | F66: Inversión | G66: Socio de proyecto | H66: NO | I66: 4 | J66: 6 | K66: 30000000 | L66: 45289360 | M66: =IFERROR(VLOOKUP(B66,'SUM PROM Y REDONDEO'!A54:J153,9,FALSE),"no eno") -> 0 | N66: =IFERROR(VLOOKUP(B66,'SUM PROM Y REDONDEO'!A54:J153,10,FALSE),"no eno") -> 46980526
B67: SAMUEL | C67: SAMUEL@gmail.com | D67: COLOMBIA | E67: Sector Real | F67: Inversión | G67: Socio de proyecto | H67: NO | I67: 7 | J67: 5 | K67: 30000000 | L67: 34397393 | M67: =IFERROR(VLOOKUP(B67,'SUM PROM Y REDONDEO'!A55:J154,9,FALSE),"no eno") -> 72192037 | N67: =IFERROR(VLOOKUP(B67,'SUM PROM Y REDONDEO'!A55:J154,10,FALSE),"no eno") -> 21247716
B68: ANDRES | C68: ANDRES@gmail.com | D68: COLOMBIA | E68: Tecnología | F68: Trabajo | G68: Buscando trabajo | H68: SI | I68: 3 | J68: 9 | K68: $ - | L68: $ - | M68: =IFERROR(VLOOKUP(B68,'SUM PROM Y REDONDEO'!A56:J155,9,FALSE),"no eno") -> 69870077 | N68: =IFERROR(VLOOKUP(B68,'SUM PROM Y REDONDEO'!A56:J155,10,FALSE),"no eno") -> 98441580
B69: NORA | C69: NORA@gmail.com | D69: CHILE | E69: Sector Real | F69: Inversión | G69: Socio de proyecto | H69: NO | I69: 3 | J69: 6 | K69: 1000000 | L69: 34126405 | M69: =IFERROR(VLOOKUP(B69,'SUM PROM Y REDONDEO'!A57:J156,9,FALSE),"no eno") -> 88265167 | N69: =IFERROR(VLOOKUP(B69,'SUM PROM Y REDONDEO'!A57:J156,10,FALSE),"no eno") -> 56002928
B70: ANDRÉS | C70: ANDRÉS@gmail.com | D70: COLOMBIA | E70: Tecnología | F70: Inversión | G70: Socio capitalista | H70: NO | I70: 7 | J70: 10 | K70: 1000000 | L70: 53008255 | M70: =IFERROR(VLOOKUP(B70,'SUM PROM Y REDONDEO'!A58:J157,9,FALSE),"no eno") -> 46917910 | N70: =IFERROR(VLOOKUP(B70,'SUM PROM Y REDONDEO'!A58:J157,10,FALSE),"no eno") -> 47557281
B71: CRISTIAN | C71: CRISTIAN@gmail.com | D71: COLOMBIA | E71: Tecnología | F71: Trabajo | G71: Buscando trabajo | H71: NO | I71: 5 | J71: 9 | K71: $ - | L71: $ - | M71: =IFERROR(VLOOKUP(B71,'SUM PROM Y REDONDEO'!A59:J158,9,FALSE),"no eno") -> 0 | N71: =IFERROR(VLOOKUP(B71,'SUM PROM Y REDONDEO'!A59:J158,10,FALSE),"no eno") -> 22675260
B72: JAVIER | C72: JAVIER@gmail.com | D72: BOLIVIA | E72: Tecnología | F72: Inversión | G72: Socio capitalista | H72: NO | I72: 9 | J72: 5 | K72: 100000000 | L72: 94688720 | M72: =IFERROR(VLOOKUP(B72,'SUM PROM Y REDONDEO'!A60:J159,9,FALSE),"no eno") -> 86323763 | N72: =IFERROR(VLOOKUP(B72,'SUM PROM Y REDONDEO'!A60:J159,10,FALSE),"no eno") -> 20929788
B73: DOMINGO | C73: DOMINGO@gmail.com | D73: COLOMBIA | E73: Educación | F73: Conocimiento | G73: Académico | H73: NO | I73: 4 | J73: 8 | K73: $ - | L73: $ - | M73: =IFERROR(VLOOKUP(B73,'SUM PROM Y REDONDEO'!A61:J160,9,FALSE),"no eno") -> 96750826 | N73: =IFERROR(VLOOKUP(B73,'SUM PROM Y REDONDEO'!A61:J160,10,FALSE),"no eno") -> 31435769
B74: NICOLAS | C74: NICOLAS@gmail.com | D74: COLOMBIA | E74: Sector Real | F74: Inversión | G74: Socio capitalista | H74: NO | I74: 5 | J74: 10 | K74: 10000000 | L74: 89686683 | M74: =IFERROR(VLOOKUP(B74,'SUM PROM Y REDONDEO'!A62:J161,9,FALSE),"no eno") -> 62448793 | N74: =IFERROR(VLOOKUP(B74,'SUM PROM Y REDONDEO'!A62:J161,10,FALSE),"no eno") -> 26812600
B75: HECTOR | C75: HECTOR@gmail.com | D75: COLOMBIA | E75: Tecnología | F75: Inversión | G75: Socio de proyecto | H75: NO | I75: 3 | J75: 10 | K75: 30000000 | L75: 32890743 | M75: =IFERROR(VLOOKUP(B75,'SUM PROM Y REDONDEO'!A63:J162,9,FALSE),"no eno") -> 0 | N75: =IFERROR(VLOOKUP(B75,'SUM PROM Y REDONDEO'!A63:J162,10,FALSE),"no eno") -> 39864620
B76: RICARDO | C76: RICARDO@gmail.com | D76: COLOMBIA | E76: Sector Real | F76: Inversión | G76: Socio capitalista | H76: NO | I76: 3 | J76: 10 | K76: 10000000 | L76: 32370896 | M76: =IFERROR(VLOOKUP(B76,'SUM PROM Y REDONDEO'!A64:J163,9,FALSE),"no eno") -> 96066942 | N76: =IFERROR(VLOOKUP(B76,'SUM PROM Y REDONDEO'!A64:J163,10,FALSE),"no eno") -> 3767736
B77: ALBERTO | C77: ALBERTO@gmail.com | D77: COLOMBIA | E77: Sector Real | F77: Trabajo | G77: Ofreciendo trabajo | H77: NO | I77: 5 | J77: 5 | K77: $ - | L77: $ - | M77: =IFERROR(VLOOKUP(B77,'SUM PROM Y REDONDEO'!A65:J164,9,FALSE),"no eno") -> 24514428 | N77: =IFERROR(VLOOKUP(B77,'SUM PROM Y REDONDEO'!A65:J164,10,FALSE),"no eno") -> 27890231
B78: RUBEN | C78: RUBEN@gmail.com | D78: COLOMBIA | E78: Tecnología | F78: Inversión | G78: Socio capitalista | H78: SI | I78: 7 | J78: 7 | K78: 10000000 | L78: 31953589 | M78: =IFERROR(VLOOKUP(B78,'SUM PROM Y REDONDEO'!A66:J165,9,FALSE),"no eno") -> 40068224 | N78: =IFERROR(VLOOKUP(B78,'SUM PROM Y REDONDEO'!A66:J165,10,FALSE),"no eno") -> 80951038
B79: SEBASTIAN | C79: SEBASTIAN@gmail.com | D79: COLOMBIA | E79: Tecnología | F79: Inversión | G79: Socio capitalista | H79: NO | I79: 7 | J79: 5 | K79: 50000000 | L79: 78205651 | M79: =IFERROR(VLOOKUP(B79,'SUM PROM Y REDONDEO'!A67:J166,9,FALSE),"no eno") -> 62381180 | N79: =IFERROR(VLOOKUP(B79,'SUM PROM Y REDONDEO'!A67:J166,10,FALSE),"no eno") -> 6508585
B80: MOHAMED | C80: MOHAMED@gmail.com | D80: COLOMBIA | E80: Agroindustrial | F80: Trabajo | G80: Buscando trabajo | H80: NO | I80: 5 | J80: 4 | K80: $ - | L80: $ - | M80: =IFERROR(VLOOKUP(B80,'SUM PROM Y REDONDEO'!A68:J167,9,FALSE),"no eno") -> 34584522 | N80: =IFERROR(VLOOKUP(B80,'SUM PROM Y REDONDEO'!A68:J167,10,FALSE),"no eno") -> 0
B81: MARCO | C81: MARCO@gmail.com | D81: PERU | E81: Tecnología | F81: Conocimiento | G81: Otro tipo | H81: NO | I81: 7 | J81: 7 | K81: $ - | L81: $ - | M81: =IFERROR(VLOOKUP(B81,'SUM PROM Y REDONDEO'!A69:J168,9,FALSE),"no eno") -> 76942676 | N81: =IFERROR(VLOOKUP(B81,'SUM PROM Y REDONDEO'!A69:J168,10,FALSE),"no eno") -> 74216691
B82: SERGIO | C82: SERGIO@gmail.com | D82: BRASIL | E82: Sector Real | F82: Inversión | G82: Socio de proyecto | H82: SI | I82: 8 | J82: 9 | K82: 5000000 | L82: 70270294 | M82: =IFERROR(VLOOKUP(B82,'SUM PROM Y REDONDEO'!A70:J169,9,FALSE),"no eno") -> 19588762 | N82: =IFERROR(VLOOKUP(B82,'SUM PROM Y REDONDEO'!A70:J169,10,FALSE),"no eno") -> 78634577
B83: RAMON | C83: RAMON@gmail.com | D83: COLOMBIA | E83: Agroindustrial | F83: Trabajo | G83: Buscando trabajo | H83: NO | I83: 3 | J83: 5 | K83: $ - | L83: $ - | M83: =IFERROR(VLOOKUP(B83,'SUM PROM Y REDONDEO'!A71:J170,9,FALSE),"no eno") -> 85955846 | N83: =IFERROR(VLOOKUP(B83,'SUM PROM Y REDONDEO'!A71:J170,10,FALSE),"no eno") -> 25891596
B84: GREGORIO | C84: GREGORIO@gmail.com | D84: COLOMBIA | E84: Agroindustrial | F84: Inversión | G84: Socio de proyecto | H84: SI | I84: 8 | J84: 10 | K84: 20000000 | L84: 62745331 | M84: =IFERROR(VLOOKUP(B84,'SUM PROM Y REDONDEO'!A72:J171,9,FALSE),"no eno") -> 39843357 | N84: =IFERROR(VLOOKUP(B84,'SUM PROM Y REDONDEO'!A72:J171,10,FALSE),"no eno") -> 64840967
B85: JOAN | C85: JOAN@gmail.com | D85: COLOMBIA | E85: Tecnología | F85: Trabajo | G85: Ofreciendo trabajo | H85: NO | I85: 5 | J85: 7 | K85: $ - | L85: $ - | M85: =IFERROR(VLOOKUP(B85,'SUM PROM Y REDONDEO'!A73:J172,9,FALSE),"no eno") -> 82583322 | N85: =IFERROR(VLOOKUP(B85,'SUM PROM Y REDONDEO'!A73:J172,10,FALSE),"no eno") -> 809058
B86: ALFONSO | C86: ALFONSO@gmail.com | D86: COLOMBIA | E86: Tecnología | F86: Inversión | G86: Socio de proyecto | H86: SI | I86: 6 | J86: 6 | K86: 10000000 | L86: 59890317 | M86: =IFERROR(VLOOKUP(B86,'SUM PROM Y REDONDEO'!A74:J173,9,FALSE),"no eno") -> 42451842 | N86: =IFERROR(VLOOKUP(B86,'SUM PROM Y REDONDEO'!A74:J173,10,FALSE),"no eno") -> 0
B87: GUILLERMO | C87: GUILLERMO@gmail.com | D87: COLOMBIA | E87: Agroindustrial | F87: Inversión | G87: Socio capitalista | H87: NO | I87: 3 | J87: 6 | K87: 10000000 | L87: 97449662 | M87: =IFERROR(VLOOKUP(B87,'SUM PROM Y REDONDEO'!A75:J174,9,FALSE),"no eno") -> 49624160 | N87: =IFERROR(VLOOKUP(B87,'SUM PROM Y REDONDEO'!A75:J174,10,FALSE),"no eno") -> 17854677
B88: CHRISTIAN | C88: CHRISTIAN@gmail.com | D88: COLOMBIA | E88: Construcción | F88: Trabajo | G88: Ofreciendo trabajo | H88: NO | I88: 8 | J88: 10 | K88: $ - | L88: $ - | M88: =IFERROR(VLOOKUP(B88,'SUM PROM Y REDONDEO'!A76:J175,9,FALSE),"no eno") -> 44422091 | N88: =IFERROR(VLOOKUP(B88,'SUM PROM Y REDONDEO'!A76:J175,10,FALSE),"no eno") -> 8898260
B89: MATEO | C89: MATEO@gmail.com | D89: URUGUAY | E89: Tecnología | F89: Trabajo | G89: Buscando trabajo | H89: NO | I89: 5 | J89: 7 | K89: $ - | L89: $ - | M89: =IFERROR(VLOOKUP(B89,'SUM PROM Y REDONDEO'!A77:J176,9,FALSE),"no eno") -> 0 | N89: =IFERROR(VLOOKUP(B89,'SUM PROM Y REDONDEO'!A77:J176,10,FALSE),"no eno") -> 63436099
B90: JULIAN | C90: JULIAN@gmail.com | D90: COLOMBIA | E90: Tecnología | F90: Inversión | G90: Socio capitalista | H90: SI | I90: 8 | J90: 9 | K90: 10000000 | L90: 99989764 | M90: =IFERROR(VLOOKUP(B90,'SUM PROM Y REDONDEO'!A78:J177,9,FALSE),"no eno") -> 8030175 | N90: =IFERROR(VLOOKUP(B90,'SUM PROM Y REDONDEO'!A78:J177,10,FALSE),"no eno") -> 37676206
B91: CRISTOBAL | C91: CRISTOBAL@gmail.com | D91: COLOMBIA | E91: Tecnología | F91: Trabajo | G91: Buscando trabajo | H91: SI | I91: 4 | J91: 5 | K91: $ - | L91: $ - | M91: =IFERROR(VLOOKUP(B91,'SUM PROM Y REDONDEO'!A79:J178,9,FALSE),"no eno") -> 12862402 | N91: =IFERROR(VLOOKUP(B91,'SUM PROM Y REDONDEO'!A79:J178,10,FALSE),"no eno") -> 68922404
B92: RODRIGO | C92: RODRIGO@gmail.com | D92: COLOMBIA | E92: Sector Real | F92: Trabajo | G92: Buscando trabajo | H92: SI | I92: 9 | J92: 9 | K92: $ - | L92: $ - | M92: =IFERROR(VLOOKUP(B92,'SUM PROM Y REDONDEO'!A80:J179,9,FALSE),"no eno") -> 46914257 | N92: =IFERROR(VLOOKUP(B92,'SUM PROM Y REDONDEO'!A80:J179,10,FALSE),"no eno") -> 43734508
B93: JESUS | C93: JESUS@gmail.com | D93: OTRO PAÍS DEL MUNDO | E93: Educación | F93: Conocimiento | G93: Académico | H93: NO | I93: 6 | J93: 10 | K93: $ - | L93: $ - | M93: =IFERROR(VLOOKUP(B93,'SUM PROM Y REDONDEO'!A81:J180,9,FALSE),"no eno") -> 95212463 | N93: =IFERROR(VLOOKUP(B93,'SUM PROM Y REDONDEO'!A81:J180,10,FALSE),"no eno") -> 0
B94: JORGE | C94: JORGE@gmail.com | D94: CHILE | E94: Tecnología | F94: Inversión | G94: Socio capitalista | H94: NO | I94: 3 | J94: 9 | K94: 5000000 | L94: 32915397 | M94: =IFERROR(VLOOKUP(B94,'SUM PROM Y REDONDEO'!A82:J181,9,FALSE),"no eno") -> 74493461 | N94: =IFERROR(VLOOKUP(B94,'SUM PROM Y REDONDEO'!A82:J181,10,FALSE),"no eno") -> 151779
B95: JULIO | C95: JULIO@gmail.com | D95: COLOMBIA | E95: Sector Real | F95: Trabajo | G95: Buscando trabajo | H95: NO | I95: 3 | J95: 7 | K95: $ - | L95: $ - | M95: =IFERROR(VLOOKUP(B95,'SUM PROM Y REDONDEO'!A83:J182,9,FALSE),"no eno") -> 43223505 | N95: =IFERROR(VLOOKUP(B95,'SUM PROM Y REDONDEO'!A83:J182,10,FALSE),"no eno") -> 0
B96: MARIA MÓNICA | C96: MARIA MÓNICA@gmail.com | D96: COLOMBIA | E96: Tecnología | F96: Trabajo | G96: Buscando trabajo | H96: NO | I96: 7 | J96: 10 | K96: $ - | L96: $ - | M96: =IFERROR(VLOOKUP(B96,'SUM PROM Y REDONDEO'!A84:J183,9,FALSE),"no eno") -> 14141858 | N96: =IFERROR(VLOOKUP(B96,'SUM PROM Y REDONDEO'!A84:J183,10,FALSE),"no eno") -> 87162317
B97: IGNACIO | C97: IGNACIO@gmail.com | D97: COLOMBIA | E97: Tecnología | F97: Trabajo | G97: Buscando trabajo | H97: NO | I97: 3 | J97: 7 | K97: $ - | L97: $ - | M97: =IFERROR(VLOOKUP(B97,'SUM PROM Y REDONDEO'!A85:J184,9,FALSE),"no eno") -> 29525162 | N97: =IFERROR(VLOOKUP(B97,'SUM PROM Y REDONDEO'!A85:J184,10,FALSE),"no eno") -> 0
B98: GABRIEL | C98: GABRIEL@gmail.com | D98: COLOMBIA | E98: Tecnología | F98: Trabajo | G98: Ofreciendo trabajo | H98: SI | I98: 7 | J98: 4 | K98: $ - | L98: $ - | M98: =IFERROR(VLOOKUP(B98,'SUM PROM Y REDONDEO'!A86:J185,9,FALSE),"no eno") -> 29366791 | N98: =IFERROR(VLOOKUP(B98,'SUM PROM Y REDONDEO'!A86:J185,10,FALSE),"no eno") -> 89805774
B99: MARTIN | C99: MARTIN@gmail.com | D99: COLOMBIA | E99: Tecnología | F99: Trabajo | G99: Buscando trabajo | H99: SI | I99: 9 | J99: 5 | K99: $ - | L99: $ - | M99: =IFERROR(VLOOKUP(B99,'SUM PROM Y REDONDEO'!A87:J186,9,FALSE),"no eno") -> 73195518 | N99: =IFERROR(VLOOKUP(B99,'SUM PROM Y REDONDEO'!A87:J186,10,FALSE),"no eno") -> 10695678
B100: FERNANDO | C100: FERNANDO@gmail.com | D100: COLOMBIA | E100: Tecnología | F100: Trabajo | G100: Buscando trabajo | H100: NO | I100: 3 | J100: 6 | K100: $ - | L100: $ - | M100: =IFERROR(VLOOKUP(B100,'SUM PROM Y REDONDEO'!A88:J187,9,FALSE),"no eno") -> 1432950 | N100: =IFERROR(VLOOKUP(B100,'SUM PROM Y REDONDEO'!A88:J187,10,FALSE),"no eno") -> 29672451
B101: ALEJANDRO | C101: ALEJANDRO@gmail.com | D101: COLOMBIA | E101: Tecnología | F101: Inversión | G101: Socio capitalista | H101: SI | I101: 8 | J101: 7 | K101: 1000000 | L101: 77159264 | M101: =IFERROR(VLOOKUP(B101,'SUM PROM Y REDONDEO'!A89:J188,9,FALSE),"no eno") -> 0 | N101: =IFERROR(VLOOKUP(B101,'SUM PROM Y REDONDEO'!A89:J188,10,FALSE),"no eno") -> 97234303
B102: SANTIAGO | C102: SANTIAGO@gmail.com | D102: CHILE | E102: Tecnología | F102: Inversión | G102: Socio capitalista | H102: NO | I102: 7 | J102: 10 | K102: 100000000 | L102: 12451199 | M102: =IFERROR(VLOOKUP(B102,'SUM PROM Y REDONDEO'!A90:J189,9,FALSE),"no eno") -> 74231711 | N102: =IFERROR(VLOOKUP(B102,'SUM PROM Y REDONDEO'!A90:J189,10,FALSE),"no eno") -> 42951226
B103: LUCAS | C103: LUCAS@gmail.com | D103: COLOMBIA | E103: Construcción | F103: Inversión | G103: Socio capitalista | H103: SI | I103: 3 | J103: 9 | K103: 90000000 | L103: 13287929 | M103: =IFERROR(VLOOKUP(B103,'SUM PROM Y REDONDEO'!A91:J190,9,FALSE),"no eno") -> 27090183 | N103: =IFERROR(VLOOKUP(B103,'SUM PROM Y REDONDEO'!A91:J190,10,FALSE),"no eno") -> 79518711
B104: PEDRO | C104: PEDRO@gmail.com | D104: CHILE | E104: Educación | F104: Conocimiento | G104: Académico | H104: NO | I104: 6 | J104: 5 | K104: $ - | L104: $ - | M104: =IFERROR(VLOOKUP(B104,'SUM PROM Y REDONDEO'!A92:J191,9,FALSE),"no eno") -> 20898506 | N104: =IFERROR(VLOOKUP(B104,'SUM PROM Y REDONDEO'!A92:J191,10,FALSE),"no eno") -> 24525645
...

Sheet buscarv3
O5: Suma de Calificación Proyectos (1-10) | P5: Etiquetas de columna
E6: BUSCARV con # de columna - DIGITADA | G6: BUSCARV con # de columna FORMULADA | O6: Etiquetas de fila | P6: ARGENTINA | Q6: BOLIVIA | R6: BRASIL | S6: CHILE | T6: COLOMBIA | U6: ECUADOR | V6: OTRO PAÍS DEL MUNDO | W6: PARAGUAY | X6: PERU | Y6: URUGUAY | Z6: VENEZUELA | AA6: Total general
G7: 7 | J7: 10 | K7: 11 | L7: 12 | M7: 13 | O7: DOMINGO | T7: 8 | AA7: 8
A8: Nombre | B8: Mail | C8: País de orígen | D8: Sector | E8: Intención frente a los proyectos | F8: Detalle inversión | G8: Conoce algún proyecto o no | H8: Calificación Feria (1-10) | I8: Calificación Proyectos (1-10) | J8: Expectativa inversión 2018 | K8: Inversión real 2018 | L8: Inversión real 2017 | M8: Inversión real 2016 | N8: Inversion de 2016 | O8: JULIO | T8: 7 | AA8: 7
A9: ALBERT | B9: ALBERT@gmail.com | C9: COLOMBIA | D9: Educación | E9: =IFERROR(VLOOKUP(A9,bdbuscarv!$A$1:$M$101,5,FALSE),"no encontrado") -> Conocimiento | F9: =IFERROR(VLOOKUP(A9,Tabla4[#All],6,FALSE),"no encontrado") -> Académico | G9: =IFERROR(VLOOKUP(A9,Tabla4[#All],7,FALSE),"no encontrado") -> NO | H9: =IFERROR(VLOOKUP(A9,Tabla4[#All],8,FALSE),"no encontrado") -> 3 | I9: =IFERROR(VLOOKUP(A9,Tabla4[#All],9,FALSE),"no encontrado") -> 8 | J9: =IFERROR(VLOOKUP(A9,Tabla4[#All],$J$7,FALSE),"no encontrado") -> $ - | K9: =IFERROR(VLOOKUP(A9,Tabla4[#All],$K$7,FALSE),"no encontrado") -> $ - | L9: =IFERROR(VLOOKUP(A9,Tabla4[#All],$L$7,FALSE),"no encontrado") -> 96781441 | M9: =IFERROR(VLOOKUP(A9,Tabla4[#All],$M$7,FALSE),"no encontrado") -> 47643060 | O9: ADOLFO | T9: 9 | AA9: 9
A10: JOAQUIN | B10: JOAQUIN@gmail.com | C10: COLOMBIA | D10: Tecnología | E10: =IFERROR(VLOOKUP(A10,bdbuscarv!$A$1:$M$101,5,FALSE),"no encontrado") -> Inversión | F10: =IFERROR(VLOOKUP(A10,Tabla4[#All],6,FALSE),"no encontrado") -> Socio capitalista | G10: =IFERROR(VLOOKUP(A10,Tabla4[#All],7,FALSE),"no encontrado") -> SI | H10: =IFERROR(VLOOKUP(A10,Tabla4[#All],8,FALSE),"no encontrado") -> 8 | I10: =IFERROR(VLOOKUP(A10,Tabla4[#All],9,FALSE),"no encontrado") -> 7 | J10: =IFERROR(VLOOKUP(A10,Tabla4[#All],$J$7,FALSE),"no encontrado") -> 10000000 | K10: =IFERROR(VLOOKUP(A10,Tabla4[#All],$K$7,FALSE),"no encontrado") -> 40848959 | L10: =IFERROR(VLOOKUP(A10,Tabla4[#All],$L$7,FALSE),"no encontrado") -> 92963332 | M10: =IFERROR(VLOOKUP(A10,Tabla4[#All],$M$7,FALSE),"no encontrado") -> 47565587 | O10: ADRIAN | T10: 10 | AA10: 10
A11: CESAR | B11: CESAR@gmail.com | C11: COLOMBIA | D11: Construcción | E11: =IFERROR(VLOOKUP(A11,bdbuscarv!$A$1:$M$101,5,FALSE),"no encontrado") -> Trabajo | F11: =IFERROR(VLOOKUP(A11,Tabla4[#All],6,FALSE),"no encontrado") -> Ofreciendo trabajo | G11: =IFERROR(VLOOKUP(A11,Tabla4[#All],7,FALSE),"no encontrado") -> NO | H11: =IFERROR(VLOOKUP(A11,Tabla4[#All],8,FALSE),"no encontrado") -> 5 | I11: =IFERROR(VLOOKUP(A11,Tabla4[#All],9,FALSE),"no encontrado") -> 10 | J11: =IFERROR(VLOOKUP(A11,Tabla4[#All],$J$7,FALSE),"no encontrado") -> $ - | K11: =IFERROR(VLOOKUP(A11,Tabla4[#All],$K$7,FALSE),"no encontrado") -> $ - | L11: =IFERROR(VLOOKUP(A11,Tabla4[#All],$L$7,FALSE),"no encontrado") -> 49599457 | M11: =IFERROR(VLOOKUP(A11,Tabla4[#All],$M$7,FALSE),"no encontrado") -> $ - | O11: AGUSTIN | T11: 5 | AA11: 5
A12: HUGO | B12: HUGO@gmail.com | C12: COLOMBIA | D12: Tecnología | E12: =IFERROR(VLOOKUP(A12,bdbuscarv!$A$1:$M$101,5,FALSE),"no encontrado") -> Inversión | F12: =IFERROR(VLOOKUP(A12,Tabla4[#All],6,FALSE),"no encontrado") -> Socio de proyecto | G12: =IFERROR(VLOOKUP(A12,Tabla4[#All],7,FALSE),"no encontrado") -> NO | H12: =IFERROR(VLOOKUP(A12,Tabla4[#All],8,FALSE),"no encontrado") -> 4 | I12: =IFERROR(VLOOKUP(A12,Tabla4[#All],9,FALSE),"no encontrado") -> 8 | J12: =IFERROR(VLOOKUP(A12,Tabla4[#All],$J$7,FALSE),"no encontrado") -> 10000000 | K12: =IFERROR(VLOOKUP(A12,Tabla4[#All],$K$7,FALSE),"no encontrado") -> 78308880 | L12: =IFERROR(VLOOKUP(A12,Tabla4[#All],$L$7,FALSE),"no encontrado") -> 3248026 | M12: =IFERROR(VLOOKUP(A12,Tabla4[#All],$M$7,FALSE),"no encontrado") -> 27143270 | O12: ALBERT | T12: 8 | AA12: 8
A13: VALENTINA | B13: VALENTINA@gmail.com | C13: COLOMBIA | D13: Construcción | E13: =IFERROR(VLOOKUP(A13,bdbuscarv!$A$1:$M$101,5,FALSE),"no encontrado") -> Inversión | F13: =IFERROR(VLOOKUP(A13,Tabla4[#All],6,FALSE),"no encontrado") -> Socio capitalista | G13: =IFERROR(VLOOKUP(A13,Tabla4[#All],7,FALSE),"no encontrado") -> NO | H13: =IFERROR(VLOOKUP(A13,Tabla4[#All],8,FALSE),"no encontrado") -> 4 | I13: =IFERROR(VLOOKUP(A13,Tabla4[#All],9,FALSE),"no encontrado") -> 9 | J13: =IFERROR(VLOOKUP(A13,Tabla4[#All],$J$7,FALSE),"no encontrado") -> 50000000 | K13: =IFERROR(VLOOKUP(A13,Tabla4[#All],$K$7,FALSE),"no encontrado") -> 2910571 | L13: =IFERROR(VLOOKUP(A13,Tabla4[#All],$L$7,FALSE),"no encontrado") -> 37561085 | M13: =IFERROR(VLOOKUP(A13,Tabla4[#All],$M$7,FALSE),"no encontrado") -> 19598007 | O13: ALBERTO | T13: 5 | AA13: 5
A14: GERMAN | B14: GERMAN@gmail.com | C14: COLOMBIA | D14: Tecnología | E14: =IFERROR(VLOOKUP(A14,bdbuscarv!$A$1:$M$101,5,FALSE),"no encontrado") -> Inversión | F14: =IFERROR(VLOOKUP(A14,Tabla4[#All],6,FALSE),"no encontrado") -> Socio de proyecto | G14: =IFERROR(VLOOKUP(A14,Tabla4[#All],7,FALSE),"no encontrado") -> NO | H14: =IFERROR(VLOOKUP(A14,Tabla4[#All],8,FALSE),"no encontrado") -> 9 | I14: =IFERROR(VLOOKUP(A14,Tabla4[#All],9,FALSE),"no encontrado") -> 7 | J14: =IFERROR(VLOOKUP(A14,Tabla4[#All],$J$7,FALSE),"no encontrado") -> 90000000 | K14: =IFERROR(VLOOKUP(A14,Tabla4[#All],$K$7,FALSE),"no encontrado") -> 50075523 | L14: =IFERROR(VLOOKUP(A14,Tabla4[#All],$L$7,FALSE),"no encontrado") -> 59142617 | M14: =IFERROR(VLOOKUP(A14,Tabla4[#All],$M$7,FALSE),"no encontrado") -> 95314026 | O14: ALEJANDRO | T14: 7 | AA14: 7
A15: DAVID | B15: DAVID@gmail.com | C15: COLOMBIA | D15: Tecnología | E15: =IFERROR(VLOOKUP(A15,bdbuscarv!$A$1:$M$101,5,FALSE),"no encontrado") -> Trabajo | F15: =IFERROR(VLOOKUP(A15,Tabla4[#All],6,FALSE),"no encontrado") -> Ofreciendo trabajo | G15: =IFERROR(VLOOKUP(A15,Tabla4[#All],7,FALSE),"no encontrado") -> NO | H15: =IFERROR(VLOOKUP(A15,Tabla4[#All],8,FALSE),"no encontrado") -> 5 | I15: =IFERROR(VLOOKUP(A15,Tabla4[#All],9,FALSE),"no encontrado") -> 9 | J15: =IFERROR(VLOOKUP(A15,Tabla4[#All],$J$7,FALSE),"no encontrado") -> $ - | K15: =IFERROR(VLOOKUP(A15,Tabla4[#All],$K$7,FALSE),"no encontrado") -> $ - | L15: =IFERROR(VLOOKUP(A15,Tabla4[#All],$L$7,FALSE),"no encontrado") -> $ - | M15: =IFERROR(VLOOKUP(A15,Tabla4[#All],$M$7,FALSE),"no encontrado") -> 67714973 | O15: ALEX | Y15: 6 | AA15: 6
A16: MIGUEL | B16: MIGUEL@gmail.com | C16: COLOMBIA | D16: Tecnología | E16: =IFERROR(VLOOKUP(A16,bdbuscarv!$A$1:$M$101,5,FALSE),"no encontrado") -> Inversión | F16: =IFERROR(VLOOKUP(A16,Tabla4[#All],6,FALSE),"no encontrado") -> Socio capitalista | G16: =IFERROR(VLOOKUP(A16,Tabla4[#All],7,FALSE),"no encontrado") -> SI | H16: =IFERROR(VLOOKUP(A16,Tabla4[#All],8,FALSE),"no encontrado") -> 8 | I16: =IFERROR(VLOOKUP(A16,Tabla4[#All],9,FALSE),"no encontrado") -> 10 | J16: =IFERROR(VLOOKUP(A16,Tabla4[#All],$J$7,FALSE),"no encontrado") -> 1000000 | K16: =IFERROR(VLOOKUP(A16,Tabla4[#All],$K$7,FALSE),"no encontrado") -> 5305190 | L16: =IFERROR(VLOOKUP(A16,Tabla4[#All],$L$7,FALSE),"no encontrado") -> 53291805 | M16: =IFERROR(VLOOKUP(A16,Tabla4[#All],$M$7,FALSE),"no encontrado") -> 84809282 | O16: ALEXANDER | T16: 9 | AA16: 9
A17: VICENTE | B17: VICENTE@gmail.com | C17: COLOMBIA | D17: Agroindustrial | E17: =IFERROR(VLOOKUP(A17,bdbuscarv!$A$1:$M$101,5,FALSE),"no encontrado") -> Trabajo | F17: =IFERROR(VLOOKUP(A17,Tabla4[#All],6,FALSE),"no encontrado") -> Ofreciendo trabajo | G17: =IFERROR(VLOOKUP(A17,Tabla4[#All],7,FALSE),"no encontrado") -> SI | H17: =IFERROR(VLOOKUP(A17,Tabla4[#All],8,FALSE),"no encontrado") -> 8 | I17: =IFERROR(VLOOKUP(A17,Tabla4[#All],9,FALSE),"no encontrado") -> 3 | J17: =IFERROR(VLOOKUP(A17,Tabla4[#All],$J$7,FALSE),"no encontrado") -> $ - | K17: =IFERROR(VLOOKUP(A17,Tabla4[#All],$K$7,FALSE),"no encontrado") -> $ - | L17: =IFERROR(VLOOKUP(A17,Tabla4[#All],$L$7,FALSE),"no encontrado") -> 50085574 | M17: =IFERROR(VLOOKUP(A17,Tabla4[#All],$M$7,FALSE),"no encontrado") -> 42495353 | O17: ALFONSO | T17: 6 | AA17: 6
A18: ALVARO | B18: ALVARO@gmail.com | C18: COLOMBIA | D18: Sector Real | E18: =IFERROR(VLOOKUP(A18,bdbuscarv!$A$1:$M$101,5,FALSE),"no encontrado") -> Inversión | F18: =IFERROR(VLOOKUP(A18,Tabla4[#All],6,FALSE),"no encontrado") -> Socio de proyecto | G18: =IFERROR(VLOOKUP(A18,Tabla4[#All],7,FALSE),"no encontrado") -> NO | H18: =IFERROR(VLOOKUP(A18,Tabla4[#All],8,FALSE),"no encontrado") -> 5 | I18: =IFERROR(VLOOKUP(A18,Tabla4[#All],9,FALSE),"no encontrado") -> 9 | J18: =IFERROR(VLOOKUP(A18,Tabla4[#All],$J$7,FALSE),"no encontrado") -> 10000000 | K18: =IFERROR(VLOOKUP(A18,Tabla4[#All],$K$7,FALSE),"no encontrado") -> 38941670 | L18: =IFERROR(VLOOKUP(A18,Tabla4[#All],$L$7,FALSE),"no encontrado") -> 67846781 | M18: =IFERROR(VLOOKUP(A18,Tabla4[#All],$M$7,FALSE),"no encontrado") -> 87726693 | O18: ALFREDO | W18: 5 | AA18: 5
A19: LUIS | B19: LUIS@gmail.com | C19: VENEZUELA | D19: Tecnología | E19: =IFERROR(VLOOKUP(A19,bdbuscarv!$A$1:$M$101,5,FALSE),"no encontrado") -> Inversión | F19: =IFERROR(VLOOKUP(A19,Tabla4[#All],6,FALSE),"no encontrado") -> Socio de proyecto | G19: =IFERROR(VLOOKUP(A19,Tabla4[#All],7,FALSE),"no encontrado") -> NO | H19: =IFERROR(VLOOKUP(A19,Tabla4[#All],8,FALSE),"no encontrado") -> 4 | I19: =IFERROR(VLOOKUP(A19,Tabla4[#All],9,FALSE),"no encontrado") -> 5 | J19: =IFERROR(VLOOKUP(A19,Tabla4[#All],$J$7,FALSE),"no encontrado") -> 1000000 | K19: =IFERROR(VLOOKUP(A19,Tabla4[#All],$K$7,FALSE),"no encontrado") -> 28926771 | L19: =IFERROR(VLOOKUP(A19,Tabla4[#All],$L$7,FALSE),"no encontrado") -> 56939610 | M19: =IFERROR(VLOOKUP(A19,Tabla4[#All],$M$7,FALSE),"no encontrado") -> 92726884 | O19: ALVARO | T19: 9 | AA19: 9
A20: DANIEL | B20: DANIEL@gmail.com | C20: COLOMBIA | D20: Tecnología | E20: =IFERROR(VLOOKUP(A20,bdbuscarv!$A$1:$M$101,5,FALSE),"no encontrado") -> Inversión | F20: =IFERROR(VLOOKUP(A20,Tabla4[#All],6,FALSE),"no encontrado") -> Socio de proyecto | G20: =IFERROR(VLOOKUP(A20,Tabla4[#All],7,FALSE),"no encontrado") -> NO | H20: =IFERROR(VLOOKUP(A20,Tabla4[#All],8,FALSE),"no encontrado") -> 3 | I20: =IFERROR(VLOOKUP(A20,Tabla4[#All],9,FALSE),"no encontrado") -> 8 | J20: =IFERROR(VLOOKUP(A20,Tabla4[#All],$J$7,FALSE),"no encontrado") -> 1000000 | K20: =IFERROR(VLOOKUP(A20,Tabla4[#All],$K$7,FALSE),"no encontrado") -> 34252074 | L20: =IFERROR(VLOOKUP(A20,Tabla4[#All],$L$7,FALSE),"no encontrado") -> $ - | M20: =IFERROR(VLOOKUP(A20,Tabla4[#All],$M$7,FALSE),"no encontrado") -> 22994819 | O20: ANDRES | T20: 9 | AA20: 9
A21: JOSEP | B21: JOSEP@gmail.com | C21: COLOMBIA | D21: Construcción | E21: =IFERROR(VLOOKUP(A21,bdbuscarv!$A$1:$M$101,5,FALSE),"no encontrado") -> Trabajo | F21: =IFERROR(VLOOKUP(A21,Tabla4[#All],6,FALSE),"no encontrado") -> Buscando trabajo | G21: =IFERROR(VLOOKUP(A21,Tabla4[#All],7,FALSE),"no encontrado") -> NO | H21: =IFERROR(VLOOKUP(A21,Tabla4[#All],8,FALSE),"no encontrado") -> 7 | I21: =IFERROR(VLOOKUP(A21,Tabla4[#All],9,FALSE),"no encontrado") -> 9 | J21: =IFERROR(VLOOKUP(A21,Tabla4[#All],$J$7,FALSE),"no encontrado") -> $ - | K21: =IFERROR(VLOOKUP(A21,Tabla4[#All],$K$7,FALSE),"no encontrado") -> $ - | L21: =IFERROR(VLOOKUP(A21,Tabla4[#All],$L$7,FALSE),"no encontrado") -> 45347826 | M21: =IFERROR(VLOOKUP(A21,Tabla4[#All],$M$7,FALSE),"no encontrado") -> 14301768 | O21: ANDRÉS | T21: 10 | AA21: 10
A22: EDUARDO | B22: EDUARDO@gmail.com | C22: COLOMBIA | D22: Tecnología | E22: =IFERROR(VLOOKUP(A22,bdbuscarv!$A$1:$M$101,5,FALSE),"no encontrado") -> Trabajo | F22: =IFERROR(VLOOKUP(A22,Tabla4[#All],6,FALSE),"no encontrado") -> Buscando trabajo | G22: =IFERROR(VLOOKUP(A22,Tabla4[#All],7,FALSE),"no encontrado") -> SI | H22: =IFERROR(VLOOKUP(A22,Tabla4[#All],8,FALSE),"no encontrado") -> 4 | I22: =IFERROR(VLOOKUP(A22,Tabla4[#All],9,FALSE),"no encontrado") -> 8 | J22: =IFERROR(VLOOKUP(A22,Tabla4[#All],$J$7,FALSE),"no encontrado") -> $ - | K22: =IFERROR(VLOOKUP(A22,Tabla4[#All],$K$7,FALSE),"no encontrado") -> $ - | L22: =IFERROR(VLOOKUP(A22,Tabla4[#All],$L$7,FALSE),"no encontrado") -> 71453938 | M22: =IFERROR(VLOOKUP(A22,Tabla4[#All],$M$7,FALSE),"no encontrado") -> 38593802 | O22: ANGEL | T22: 2 | AA22: 2
A23: LEONEL | B23: LEONEL@gmail.com | C23: COLOMBIA | D23: Sector Real | E23: =IFERROR(VLOOKUP(A23,bdbuscarv!$A$1:$M$101,5,FALSE),"no encontrado") -> Inversión | F23: =IFERROR(VLOOKUP(A23,Tabla4[#All],6,FALSE),"no encontrado") -> Socio capitalista | G23: =IFERROR(VLOOKUP(A23,Tabla4[#All],7,FALSE),"no encontrado") -> NO | H23: =IFERROR(VLOOKUP(A23,Tabla4[#All],8,FALSE),"no encontrado") -> 9 | I23: =IFERROR(VLOOKUP(A23,Tabla4[#All],9,FALSE),"no encontrado") -> 10 | J23: =IFERROR(VLOOKUP(A23,Tabla4[#All],$J$7,FALSE),"no encontrado") -> 20000000 | K23: =IFERROR(VLOOKUP(A23,Tabla4[#All],$K$7,FALSE),"no encontrado") -> 32346156 | L23: =IFERROR(VLOOKUP(A23,Tabla4[#All],$L$7,FALSE),"no encontrado") -> 22346275 | M23: =IFERROR(VLOOKUP(A23,Tabla4[#All],$M$7,FALSE),"no encontrado") -> 73743047 | O23: ANTONIO | T23: 7 | AA23: 7
A24: JORDI | B24: JORDI@gmail.com | C24: COLOMBIA | D24: Educación | E24: =IFERROR(VLOOKUP(A24,bdbuscarv!$A$1:$M$101,5,FALSE),"no encontrado") -> Conocimiento | F24: =IFERROR(VLOOKUP(A24,Tabla4[#All],6,FALSE),"no encontrado") -> Académico | G24: =IFERROR(VLOOKUP(A24,Tabla4[#All],7,FALSE),"no encontrado") -> NO | H24: =IFERROR(VLOOKUP(A24,Tabla4[#All],8,FALSE),"no encontrado") -> 4 | I24: =IFERROR(VLOOKUP(A24,Tabla4[#All],9,FALSE),"no encontrado") -> 6 | J24: =IFERROR(VLOOKUP(A24,Tabla4[#All],$J$7,FALSE),"no encontrado") -> $ - | K24: =IFERROR(VLOOKUP(A24,Tabla4[#All],$K$7,FALSE),"no encontrado") -> $ - | L24: =IFERROR(VLOOKUP(A24,Tabla4[#All],$L$7,FALSE),"no encontrado") -> 96357193 | M24: =IFERROR(VLOOKUP(A24,Tabla4[#All],$M$7,FALSE),"no encontrado") -> 67901582 | O24: ARTURO | T24: 10 | AA24: 10
A25: ESTEBAN | B25: ESTEBAN@gmail.com | C25: COLOMBIA | D25: Tecnología | E25: =IFERROR(VLOOKUP(A25,bdbuscarv!$A$1:$M$101,5,FALSE),"no encontrado") -> Inversión | F25: =IFERROR(VLOOKUP(A25,Tabla4[#All],6,FALSE),"no encontrado") -> Socio capitalista | G25: =IFERROR(VLOOKUP(A25,Tabla4[#All],7,FALSE),"no encontrado") -> NO | H25: =IFERROR(VLOOKUP(A25,Tabla4[#All],8,FALSE),"no encontrado") -> 5 | I25: =IFERROR(VLOOKUP(A25,Tabla4[#All],9,FALSE),"no encontrado") -> 7 | J25: =IFERROR(VLOOKUP(A25,Tabla4[#All],$J$7,FALSE),"no encontrado") -> 100000000 | K25: =IFERROR(VLOOKUP(A25,Tabla4[#All],$K$7,FALSE),"no encontrado") -> 72903049 | L25: =IFERROR(VLOOKUP(A25,Tabla4[#All],$L$7,FALSE),"no encontrado") -> 67375493 | M25: =IFERROR(VLOOKUP(A25,Tabla4[#All],$M$7,FALSE),"no encontrado") -> 4753995 | O25: BORJA | U25: 8 | AA25: 8
A26: JONATHAN | B26: JONATHAN@gmail.com | C26: COLOMBIA | D26: Educación | E26: =IFERROR(VLOOKUP(A26,bdbuscarv!$A$1:$M$101,5,FALSE),"no encontrado") -> Conocimiento | F26: =IFERROR(VLOOKUP(A26,Tabla4[#All],6,FALSE),"no encontrado") -> Académico | G26: =IFERROR(VLOOKUP(A26,Tabla4[#All],7,FALSE),"no encontrado") -> NO | H26: =IFERROR(VLOOKUP(A26,Tabla4[#All],8,FALSE),"no encontrado") -> 6 | I26: =IFERROR(VLOOKUP(A26,Tabla4[#All],9,FALSE),"no encontrado") -> 7 | J26: =IFERROR(VLOOKUP(A26,Tabla4[#All],$J$7,FALSE),"no encontrado") -> $ - | K26: =IFERROR(VLOOKUP(A26,Tabla4[#All],$K$7,FALSE),"no encontrado") -> $ - | L26: =IFERROR(VLOOKUP(A26,Tabla4[#All],$L$7,FALSE),"no encontrado") -> 80671052 | M26: =IFERROR(VLOOKUP(A26,Tabla4[#All],$M$7,FALSE),"no encontrado") -> 58339670 | O26: CARLOS | T26: 7 | AA26: 7
A27: FELIPE | B27: FELIPE@gmail.com | C27: BRASIL | D27: Sector Real | E27: =IFERROR(VLOOKUP(A27,bdbuscarv!$A$1:$M$101,5,FALSE),"no encontrado") -> Trabajo | F27: =IFERROR(VLOOKUP(A27,Tabla4[#All],6,FALSE),"no encontrado") -> Buscando trabajo | G27: =IFERROR(VLOOKUP(A27,Tabla4[#All],7,FALSE),"no encontrado") -> SI | H27: =IFERROR(VLOOKUP(A27,Tabla4[#All],8,FALSE),"no encontrado") -> 9 | I27: =IFERROR(VLOOKUP(A27,Tabla4[#All],9,FALSE),"no encontrado") -> 8 | J27: =IFERROR(VLOOKUP(A27,Tabla4[#All],$J$7,FALSE),"no encontrado") -> $ - | K27: =IFERROR(VLOOKUP(A27,Tabla4[#All],$K$7,FALSE),"no encontrado") -> $ - | L27: =IFERROR(VLOOKUP(A27,Tabla4[#All],$L$7,FALSE),"no encontrado") -> $ - | M27: =IFERROR(VLOOKUP(A27,Tabla4[#All],$M$7,FALSE),"no encontrado") -> 44898366 | O27: CESAR | T27: 10 | AA27: 10
A28: JOSE | B28: JOSE@gmail.com | C28: COLOMBIA | D28: Tecnología | E28: =IFERROR(VLOOKUP(A28,bdbuscarv!$A$1:$M$101,5,FALSE),"no encontrado") -> Inversión | F28: =IFERROR(VLOOKUP(A28,Tabla4[#All],6,FALSE),"no encontrado") -> Socio de proyecto | G28: =IFERROR(VLOOKUP(A28,Tabla4[#All],7,FALSE),"no encontrado") -> NO | H28: =IFERROR(VLOOKUP(A28,Tabla4[#All],8,FALSE),"no encontrado") -> 5 | I28: =IFERROR(VLOOKUP(A28,Tabla4[#All],9,FALSE),"no encontrado") -> 6 | J28: =IFERROR(VLOOKUP(A28,Tabla4[#All],$J$7,FALSE),"no encontrado") -> 1000000 | K28: =IFERROR(VLOOKUP(A28,Tabla4[#All],$K$7,FALSE),"no encontrado") -> 96696256 | L28: =IFERROR(VLOOKUP(A28,Tabla4[#All],$L$7,FALSE),"no encontrado") -> 62106884 | M28: =IFERROR(VLOOKUP(A28,Tabla4[#All],$M$7,FALSE),"no encontrado") -> 85228190 | O28: CHRISTIAN | T28: 10 | AA28: 10
A29: FELIX | B29: FELIX@gmail.com | C29: COLOMBIA | D29: Tecnología | E29: =IFERROR(VLOOKUP(A29,bdbuscarv!$A$1:$M$101,5,FALSE),"no encontrado") -> Inversión | F29: =IFERROR(VLOOKUP(A29,Tabla4[#All],6,FALSE),"no encontrado") -> Socio de proyecto | G29: =IFERROR(VLOOKUP(A29,Tabla4[#All],7,FALSE),"no encontrado") -> NO | H29: =IFERROR(VLOOKUP(A29,Tabla4[#All],8,FALSE),"no encontrado") -> 6 | I29: =IFERROR(VLOOKUP(A29,Tabla4[#All],9,FALSE),"no encontrado") -> 7 | J29: =IFERROR(VLOOKUP(A29,Tabla4[#All],$J$7,FALSE),"no encontrado") -> 10000000 | K29: =IFERROR(VLOOKUP(A29,Tabla4[#All],$K$7,FALSE),"no encontrado") -> 51531809 | L29: =IFERROR(VLOOKUP(A29,Tabla4[#All],$L$7,FALSE),"no encontrado") -> 99819688 | M29: =IFERROR(VLOOKUP(A29,Tabla4[#All],$M$7,FALSE),"no encontrado") -> 24233431 | O29: CRISTIAN | T29: 9 | AA29: 9
A30: PABLO | B30: PABLO@gmail.com | C30: COLOMBIA | D30: Agroindustrial | E30: =IFERROR(VLOOKUP(A30,bdbuscarv!$A$1:$M$101,5,FALSE),"no encontrado") -> Inversión | F30: =IFERROR(VLOOKUP(A30,Tabla4[#All],6,FALSE),"no encontrado") -> Socio capitalista | G30: =IFERROR(VLOOKUP(A30,Tabla4[#All],7,FALSE),"no encontrado") -> SI | H30: =IFERROR(VLOOKUP(A30,Tabla4[#All],8,FALSE),"no encontrado") -> 6 | I30: =IFERROR(VLOOKUP(A30,Tabla4[#All],9,FALSE),"no encontrado") -> 10 | J30: =IFERROR(VLOOKUP(A30,Tabla4[#All],$J$7,FALSE),"no encontrado") -> $ - | K30: =IFERROR(VLOOKUP(A30,Tabla4[#All],$K$7,FALSE),"no encontrado") -> $ - | L30: =IFERROR(VLOOKUP(A30,Tabla4[#All],$L$7,FALSE),"no encontrado") -> 34214902 | M30: =IFERROR(VLOOKUP(A30,Tabla4[#All],$M$7,FALSE),"no encontrado") -> 24896611 | O30: CRISTOBAL | T30: 5 | AA30: 5
A31: MANUEL | B31: MANUEL@gmail.com | C31: ARGENTINA | D31: Sector Real | E31: =IFERROR(VLOOKUP(A31,bdbuscarv!$A$1:$M$101,5,FALSE),"no encontrado") -> Trabajo | F31: =IFERROR(VLOOKUP(A31,Tabla4[#All],6,FALSE),"no encontrado") -> Ofreciendo trabajo | G31: =IFERROR(VLOOKUP(A31,Tabla4[#All],7,FALSE),"no encontrado") -> NO | H31: =IFERROR(VLOOKUP(A31,Tabla4[#All],8,FALSE),"no encontrado") -> 8 | I31: =IFERROR(VLOOKUP(A31,Tabla4[#All],9,FALSE),"no encontrado") -> 5 | J31: =IFERROR(VLOOKUP(A31,Tabla4[#All],$J$7,FALSE),"no encontrado") -> $ - | K31: =IFERROR(VLOOKUP(A31,Tabla4[#All],$K$7,FALSE),"no encontrado") -> $ - | L31: =IFERROR(VLOOKUP(A31,Tabla4[#All],$L$7,FALSE),"no encontrado") -> 7121108 | M31: =IFERROR(VLOOKUP(A31,Tabla4[#All],$M$7,FALSE),"no encontrado") -> 6991703 | O31: DANIEL | T31: 8 | AA31: 8
A32: LORENZO | B32: LORENZO@gmail.com | C32: COLOMBIA | D32: Agroindustrial | E32: =IFERROR(VLOOKUP(A32,bdbuscarv!$A$1:$M$101,5,FALSE),"no encontrado") -> Inversión | F32: =IFERROR(VLOOKUP(A32,Tabla4[#All],6,FALSE),"no encontrado") -> Socio capitalista | G32: =IFERROR(VLOOKUP(A32,Tabla4[#All],7,FALSE),"no encontrado") -> NO | H32: =IFERROR(VLOOKUP(A32,Tabla4[#All],8,FALSE),"no encontrado") -> 7 | I32: =IFERROR(VLOOKUP(A32,Tabla4[#All],9,FALSE),"no encontrado") -> 10 | J32: =IFERROR(VLOOKUP(A32,Tabla4[#All],$J$7,FALSE),"no encontrado") -> 20000000 | K32: =IFERROR(VLOOKUP(A32,Tabla4[#All],$K$7,FALSE),"no encontrado") -> 93037614 | L32: =IFERROR(VLOOKUP(A32,Tabla4[#All],$L$7,FALSE),"no encontrado") -> 48185946 | M32: =IFERROR(VLOOKUP(A32,Tabla4[#All],$M$7,FALSE),"no encontrado") -> 75039300 | O32: DARIO | T32: 9 | AA32: 9
A33: ISAAC | B33: ISAAC@gmail.com | C33: COLOMBIA | D33: Tecnología | E33: =IFERROR(VLOOKUP(A33,bdbuscarv!$A$1:$M$101,5,FALSE),"no encontrado") -> Inversión | F33: =IFERROR(VLOOKUP(A33,Tabla4[#All],6,FALSE),"no encontrado") -> Socio capitalista | G33: =IFERROR(VLOOKUP(A33,Tabla4[#All],7,FALSE),"no encontrado") -> NO | H33: =IFERROR(VLOOKUP(A33,Tabla4[#All],8,FALSE),"no encontrado") -> 9 | I33: =IFERROR(VLOOKUP(A33,Tabla4[#All],9,FALSE),"no encontrado") -> 10 | J33: =IFERROR(VLOOKUP(A33,Tabla4[#All],$J$7,FALSE),"no encontrado") -> 90000000 | K33: =IFERROR(VLOOKUP(A33,Tabla4[#All],$K$7,FALSE),"no encontrado") -> 62088180 | L33: =IFERROR(VLOOKUP(A33,Tabla4[#All],$L$7,FALSE),"no encontrado") -> 18047519 | M33: =IFERROR(VLOOKUP(A33,Tabla4[#All],$M$7,FALSE),"no encontrado") -> 3738158 | O33: DAVID | T33: 9 | AA33: 9
A34: MARIA | B34: MARIA@gmail.com | C34: COLOMBIA | D34: Sector Real | E34: =IFERROR(VLOOKUP(A34,bdbuscarv!$A$1:$M$101,5,FALSE),"no encontrado") -> Inversión | F34: =IFERROR(VLOOKUP(A34,Tabla4[#All],6,FALSE),"no encontrado") -> Socio capitalista | G34: =IFERROR(VLOOKUP(A34,Tabla4[#All],7,FALSE),"no encontrado") -> NO | H34: =IFERROR(VLOOKUP(A34,Tabla4[#All],8,FALSE),"no encontrado") -> 3 | I34: =IFERROR(VLOOKUP(A34,Tabla4[#All],9,FALSE),"no encontrado") -> 9 | J34: =IFERROR(VLOOKUP(A34,Tabla4[#All],$J$7,FALSE),"no encontrado") -> 1000000 | K34: =IFERROR(VLOOKUP(A34,Tabla4[#All],$K$7,FALSE),"no encontrado") -> 1160848 | L34: =IFERROR(VLOOKUP(A34,Tabla4[#All],$L$7,FALSE),"no encontrado") -> 32268145 | M34: =IFERROR(VLOOKUP(A34,Tabla4[#All],$M$7,FALSE),"no encontrado") -> 13339687 | O34: DIEGO | T34: 10 | AA34: 10
A35: ANGEL | B35: ANGEL@gmail.com | C35: COLOMBIA | D35: Tecnología | E35: =IFERROR(VLOOKUP(A35,bdbuscarv!$A$1:$M$101,5,FALSE),"no encontrado") -> Trabajo | F35: =IFERROR(VLOOKUP(A35,Tabla4[#All],6,FALSE),"no encontrado") -> Ofreciendo trabajo | G35: =IFERROR(VLOOKUP(A35,Tabla4[#All],7,FALSE),"no encontrado") -> NO | H35: =IFERROR(VLOOKUP(A35,Tabla4[#All],8,FALSE),"no encontrado") -> 6 | I35: =IFERROR(VLOOKUP(A35,Tabla4[#All],9,FALSE),"no encontrado") -> 2 | J35: =IFERROR(VLOOKUP(A35,Tabla4[#All],$J$7,FALSE),"no encontrado") -> $ - | K35: =IFERROR(VLOOKUP(A35,Tabla4[#All],$K$7,FALSE),"no encontrado") -> $ - | L35: =IFERROR(VLOOKUP(A35,Tabla4[#All],$L$7,FALSE),"no encontrado") -> 21224611 | M35: =IFERROR(VLOOKUP(A35,Tabla4[#All],$M$7,FALSE),"no encontrado") -> 62562457 | O35: EDUARDO | T35: 8 | AA35: 8
A36: ADOLFO | B36: ADOLFO@gmail.com | C36: COLOMBIA | D36: Sector Real | E36: =IFERROR(VLOOKUP(A36,bdbuscarv!$A$1:$M$101,5,FALSE),"no encontrado") -> Trabajo | F36: =IFERROR(VLOOKUP(A36,Tabla4[#All],6,FALSE),"no encontrado") -> Ofreciendo trabajo | G36: =IFERROR(VLOOKUP(A36,Tabla4[#All],7,FALSE),"no encontrado") -> NO | H36: =IFERROR(VLOOKUP(A36,Tabla4[#All],8,FALSE),"no encontrado") -> 9 | I36: =IFERROR(VLOOKUP(A36,Tabla4[#All],9,FALSE),"no encontrado") -> 9 | J36: =IFERROR(VLOOKUP(A36,Tabla4[#All],$J$7,FALSE),"no encontrado") -> $ - | K36: =IFERROR(VLOOKUP(A36,Tabla4[#All],$K$7,FALSE),"no encontrado") -> $ - | L36: =IFERROR(VLOOKUP(A36,Tabla4[#All],$L$7,FALSE),"no encontrado") -> 85434615 | M36: =IFERROR(VLOOKUP(A36,Tabla4[#All],$M$7,FALSE),"no encontrado") -> 79508333 | O36: EMILIO | T36: 9 | AA36: 9
A37: ERNESTO | B37: ERNESTO@gmail.com | C37: COLOMBIA | D37: Tecnología | E37: =IFERROR(VLOOKUP(A37,bdbuscarv!$A$1:$M$101,5,FALSE),"no encontrado") -> Inversión | F37: =IFERROR(VLOOKUP(A37,Tabla4[#All],6,FALSE),"no encontrado") -> Socio de proyecto | G37: =IFERROR(VLOOKUP(A37,Tabla4[#All],7,FALSE),"no encontrado") -> NO | H37: =IFERROR(VLOOKUP(A37,Tabla4[#All],8,FALSE),"no encontrado") -> 8 | I37: =IFERROR(VLOOKUP(A37,Tabla4[#All],9,FALSE),"no encontrado") -> 7 | J37: =IFERROR(VLOOKUP(A37,Tabla4[#All],$J$7,FALSE),"no encontrado") -> 90000000 | K37: =IFERROR(VLOOKUP(A37,Tabla4[#All],$K$7,FALSE),"no encontrado") -> 23888885 | L37: =IFERROR(VLOOKUP(A37,Tabla4[#All],$L$7,FALSE),"no encontrado") -> 68725539 | M37: =IFERROR(VLOOKUP(A37,Tabla4[#All],$M$7,FALSE),"no encontrado") -> 78613526 | O37: ENRIQUE | T37: 7 | AA37: 7
... A40: MARCOS | B40: MARCOS@gmail.com | C40: BRASIL | D40: Sector Real | E40: =IFERROR(VLOOKUP(A40,bdbuscarv!$A$1:$M$101,5,FALSE),"no encontrado") -> Trabajo | F40: =IFERROR(VLOOKUP(A40,Tabla4[#All],6,FALSE),"no encontrado") -> Buscando trabajo | G40: =IFERROR(VLOOKUP(A40,Tabla4[#All],7,FALSE),"no encontrado") -> SI | H40: =IFERROR(VLOOKUP(A40,Tabla4[#All],8,FALSE),"no encontrado") -> 3 | I40: =IFERROR(VLOOKUP(A40,Tabla4[#All],9,FALSE),"no encontrado") -> 5 | J40: =IFERROR(VLOOKUP(A40,Tabla4[#All],$J$7,FALSE),"no encontrado") -> $ - | K40: =IFERROR(VLOOKUP(A40,Tabla4[#All],$K$7,FALSE),"no encontrado") -> $ - | L40: =IFERROR(VLOOKUP(A40,Tabla4[#All],$L$7,FALSE),"no encontrado") -> 30987169 | M40: =IFERROR(VLOOKUP(A40,Tabla4[#All],$M$7,FALSE),"no encontrado") -> 7339680 | O40: EUGENIO | T40: 5 | AA40: 5
A41: MARIO | B41: MARIO@gmail.com | C41: COLOMBIA | D41: Tecnología | E41: =IFERROR(VLOOKUP(A41,bdbuscarv!$A$1:$M$101,5,FALSE),"no encontrado") -> Inversión | F41: =IFERROR(VLOOKUP(A41,Tabla4[#All],6,FALSE),"no encontrado") -> Socio capitalista | G41: =IFERROR(VLOOKUP(A41,Tabla4[#All],7,FALSE),"no encontrado") -> NO | H41: =IFERROR(VLOOKUP(A41,Tabla4[#All],8,FALSE),"no encontrado") -> 6 | I41: =IFERROR(VLOOKUP(A41,Tabla4[#All],9,FALSE),"no encontrado") -> 7 | J41: =IFERROR(VLOOKUP(A41,Tabla4[#All],$J$7,FALSE),"no encontrado") -> 10000000 | K41: =IFERROR(VLOOKUP(A41,Tabla4[#All],$K$7,FALSE),"no encontrado") -> 22390348 | L41: =IFERROR(VLOOKUP(A41,Tabla4[#All],$L$7,FALSE),"no encontrado") -> 24476166 | M41: =IFERROR(VLOOKUP(A41,Tabla4[#All],$M$7,FALSE),"no encontrado") -> $ - | O41: FELIPE | R41: 8 | AA41: 8
A42: ARTURO | B42: ARTURO@gmail.com | C42: COLOMBIA | D42: Sector Real | E42: =IFERROR(VLOOKUP(A42,bdbuscarv!$A$1:$M$101,5,FALSE),"no encontrado") -> Inversión | F42: =IFERROR(VLOOKUP(A42,Tabla4[#All],6,FALSE),"no encontrado") -> Socio de proyecto | G42: =IFERROR(VLOOKUP(A42,Tabla4[#All],7,FALSE),"no encontrado") -> NO | H42: =IFERROR(VLOOKUP(A42,Tabla4[#All],8,FALSE),"no encontrado") -> 6 | I42: =IFERROR(VLOOKUP(A42,Tabla4[#All],9,FALSE),"no encontrado") -> 10 | J42: =IFERROR(VLOOKUP(A42,Tabla4[#All],$J$7,FALSE),"no encontrado") -> 20000000 | K42: =IFERROR(VLOOKUP(A42,Tabla4[#All],$K$7,FALSE),"no encontrado") -> 31670482 | L42: =IFERROR(VLOOKUP(A42,Tabla4[#All],$L$7,FALSE),"no encontrado") -> 15619630 | M42: =IFERROR(VLOOKUP(A42,Tabla4[#All],$M$7,FALSE),"no encontrado") -> 59838390 | O42: FELIX | T42: 7 | AA42: 7
A43: EUGENIO | B43: EUGENIO@gmail.com | C43: COLOMBIA | D43: Construcción | E43: =IFERROR(VLOOKUP(A43,bdbuscarv!$A$1:$M$101,5,FALSE),"no encontrado") -> Inversión | F43: =IFERROR(VLOOKUP(A43,Tabla4[#All],6,FALSE),"no encontrado") -> Socio de proyecto | G43: =IFERROR(VLOOKUP(A43,Tabla4[#All],7,FALSE),"no encontrado") -> NO | H43: =IFERROR(VLOOKUP(A43,Tabla4[#All],8,FALSE),"no encontrado") -> 8 | I43: =IFERROR(VLOOKUP(A43,Tabla4[#All],9,FALSE),"no encontrado") -> 5 | J43: =IFERROR(VLOOKUP(A43,Tabla4[#All],$J$7,FALSE),"no encontrado") -> 20000000 | K43: =IFERROR(VLOOKUP(A43,Tabla4[#All],$K$7,FALSE),"no encontrado") -> 81056910 | L43: =IFERROR(VLOOKUP(A43,Tabla4[#All],$L$7,FALSE),"no encontrado") -> 96438403 | M43: =IFERROR(VLOOKUP(A43,Tabla4[#All],$M$7,FALSE),"no encontrado") -> 90723423 | O43: FERNANDO | T43: 6 | AA43: 6
A44: JUAN | B44: JUAN@gmail.com | C44: COLOMBIA | D44: Tecnología | E44: =IFERROR(VLOOKUP(A44,bdbuscarv!$A$1:$M$101,5,FALSE),"no encontrado") -> Conocimiento | F44: =IFERROR(VLOOKUP(A44,Tabla4[#All],6,FALSE),"no encontrado") -> Otro tipo | G44: =IFERROR(VLOOKUP(A44,Tabla4[#All],7,FALSE),"no encontrado") -> NO | H44: =IFERROR(VLOOKUP(A44,Tabla4[#All],8,FALSE),"no encontrado") -> 5 | I44: =IFERROR(VLOOKUP(A44,Tabla4[#All],9,FALSE),"no encontrado") -> 7 | J44: =IFERROR(VLOOKUP(A44,Tabla4[#All],$J$7,FALSE),"no encontrado") -> $ - | K44: =IFERROR(VLOOKUP(A44,Tabla4[#All],$K$7,FALSE),"no encontrado") -> $ - | L44: =IFERROR(VLOOKUP(A44,Tabla4[#All],$L$7,FALSE),"no encontrado") -> $ - | M44: =IFERROR(VLOOKUP(A44,Tabla4[#All],$M$7,FALSE),"no encontrado") -> 52936315 | O44: FRANCISCO | T44: 8 | AA44: 8
A45: GONZALO | B45: GONZALO@gmail.com | C45: COLOMBIA | D45: Tecnología | E45: =IFERROR(VLOOKUP(A45,bdbuscarv!$A$1:$M$101,5,FALSE),"no encontrado") -> Inversión | F45: =IFERROR(VLOOKUP(A45,Tabla4[#All],6,FALSE),"no encontrado") -> Socio capitalista | G45: =IFERROR(VLOOKUP(A45,Tabla4[#All],7,FALSE),"no encontrado") -> NO | H45: =IFERROR(VLOOKUP(A45,Tabla4[#All],8,FALSE),"no encontrado") -> 9 | I45: =IFERROR(VLOOKUP(A45,Tabla4[#All],9,FALSE),"no encontrado") -> 7 | J45: =IFERROR(VLOOKUP(A45,Tabla4[#All],$J$7,FALSE),"no encontrado") -> 30000000 | K45: =IFERROR(VLOOKUP(A45,Tabla4[#All],$K$7,FALSE),"no encontrado") -> 91413171 | L45: =IFERROR(VLOOKUP(A45,Tabla4[#All],$L$7,FALSE),"no encontrado") -> 13211402 | M45: =IFERROR(VLOOKUP(A45,Tabla4[#All],$M$7,FALSE),"no encontrado") -> $ - | O45: GABRIEL | T45: 4 | AA45: 4
A46: ANTONIO | B46: ANTONIO@gmail.com | C46: COLOMBIA | D46: Construcción | E46: =IFERROR(VLOOKUP(A46,bdbuscarv!$A$1:$M$101,5,FALSE),"no encontrado") -> Inversión | F46: =IFERROR(VLOOKUP(A46,Tabla4[#All],6,FALSE),"no encontrado") -> Socio de proyecto | G46: =IFERROR(VLOOKUP(A46,Tabla4[#All],7,FALSE),"no encontrado") -> NO | H46: =IFERROR(VLOOKUP(A46,Tabla4[#All],8,FALSE),"no encontrado") -> 4 | I46: =IFERROR(VLOOKUP(A46,Tabla4[#All],9,FALSE),"no encontrado") -> 7 | J46: =IFERROR(VLOOKUP(A46,Tabla4[#All],$J$7,FALSE),"no encontrado") -> 1000000 | K46: =IFERROR(VLOOKUP(A46,Tabla4[#All],$K$7,FALSE),"no encontrado") -> 87347043 | L46: =IFERROR(VLOOKUP(A46,Tabla4[#All],$L$7,FALSE),"no encontrado") -> 50796112 | M46: =IFERROR(VLOOKUP(A46,Tabla4[#All],$M$7,FALSE),"no encontrado") -> 72757830 | O46: GERMAN | T46: 7 | AA46: 7
A47: EMILIO | B47: EMILIO@gmail.com | C47: COLOMBIA | D47: Sector Real | E47: =IFERROR(VLOOKUP(A47,bdbuscarv!$A$1:$M$101,5,FALSE),"no encontrado") -> Trabajo | F47: =IFERROR(VLOOKUP(A47,Tabla4[#All],6,FALSE),"no encontrado") -> Buscando trabajo | G47: =IFERROR(VLOOKUP(A47,Tabla4[#All],7,FALSE),"no encontrado") -> NO | H47: =IFERROR(VLOOKUP(A47,Tabla4[#All],8,FALSE),"no encontrado") -> 4 | I47: =IFERROR(VLOOKUP(A47,Tabla4[#All],9,FALSE),"no encontrado") -> 9 | J47: =IFERROR(VLOOKUP(A47,Tabla4[#All],$J$7,FALSE),"no encontrado") -> $ - | K47: =IFERROR(VLOOKUP(A47,Tabla4[#All],$K$7,FALSE),"no encontrado") -> $ - | L47: =IFERROR(VLOOKUP(A47,Tabla4[#All],$L$7,FALSE),"no encontrado") -> 38721754 | M47: =IFERROR(VLOOKUP(A47,Tabla4[#All],$M$7,FALSE),"no encontrado") -> 77230635 | O47: GONZALO | T47: 7 | AA47: 7
A48: AGUSTIN | B48: AGUSTIN@gmail.com | C48: COLOMBIA | D48: Tecnología | E48: =IFERROR(VLOOKUP(A48,bdbuscarv!$A$1:$M$101,5,FALSE),"no encontrado") -> Inversión | F48: =IFERROR(VLOOKUP(A48,Tabla4[#All],6,FALSE),"no encontrado") -> Socio de proyecto | G48: =IFERROR(VLOOKUP(A48,Tabla4[#All],7,FALSE),"no encontrado") -> NO | H48: =IFERROR(VLOOKUP(A48,Tabla4[#All],8,FALSE),"no encontrado") -> 9 | I48: =IFERROR(VLOOKUP(A48,Tabla4[#All],9,FALSE),"no encontrado") -> 5 | J48: =IFERROR(VLOOKUP(A48,Tabla4[#All],$J$7,FALSE),"no encontrado") -> 10000000 | K48: =IFERROR(VLOOKUP(A48,Tabla4[#All],$K$7,FALSE),"no encontrado") -> 43538967 | L48: =IFERROR(VLOOKUP(A48,Tabla4[#All],$L$7,FALSE),"no encontrado") -> 5161300 | M48: =IFERROR(VLOOKUP(A48,Tabla4[#All],$M$7,FALSE),"no encontrado") -> 85417673 | O48: GREGORIO | T48: 10 | AA48: 10
A49: JUAN PABLO | B49: JUAN PABLO@gmail.com | C49: COLOMBIA | D49: Tecnología | E49: =IFERROR(VLOOKUP(A49,bdbuscarv!$A$1:$M$101,5,FALSE),"no encontrado") -> Inversión | F49: =IFERROR(VLOOKUP(A49,Tabla4[#All],6,FALSE),"no encontrado") -> Socio de proyecto | G49: =IFERROR(VLOOKUP(A49,Tabla4[#All],7,FALSE),"no encontrado") -> SI | H49: =IFERROR(VLOOKUP(A49,Tabla4[#All],8,FALSE),"no encontrado") -> 6 | I49: =IFERROR(VLOOKUP(A49,Tabla4[#All],9,FALSE),"no encontrado") -> 10 | J49: =IFERROR(VLOOKUP(A49,Tabla4[#All],$J$7,FALSE),"no encontrado") -> 1000000 | K49: =IFERROR(VLOOKUP(A49,Tabla4[#All],$K$7,FALSE),"no encontrado") -> 95899452 | L49: =IFERROR(VLOOKUP(A49,Tabla4[#All],$L$7,FALSE),"no encontrado") -> 2565664 | M49: =IFERROR(VLOOKUP(A49,Tabla4[#All],$M$7,FALSE),"no encontrado") -> 39602953 | O49: GUILLERMO | T49: 6 | AA49: 6
A50: FRANCISCO | B50: FRANCISCO@gmail.com | C50: COLOMBIA | D50: Tecnología | E50: =IFERROR(VLOOKUP(A50,bdbuscarv!$A$1:$M$101,5,FALSE),"no encontrado") -> Inversión | F50: =IFERROR(VLOOKUP(A50,Tabla4[#All],6,FALSE),"no encontrado") -> Socio de proyecto | G50: =IFERROR(VLOOKUP(A50,Tabla4[#All],7,FALSE),"no encontrado") -> SI | H50: =IFERROR(VLOOKUP(A50,Tabla4[#All],8,FALSE),"no encontrado") -> 8 | I50: =IFERROR(VLOOKUP(A50,Tabla4[#All],9,FALSE),"no encontrado") -> 8 | J50: =IFERROR(VLOOKUP(A50,Tabla4[#All],$J$7,FALSE),"no encontrado") -> 1000000 | K50: =IFERROR(VLOOKUP(A50,Tabla4[#All],$K$7,FALSE),"no encontrado") -> 81347428 | L50: =IFERROR(VLOOKUP(A50,Tabla4[#All],$L$7,FALSE),"no encontrado") -> 10860215 | M50: =IFERROR(VLOOKUP(A50,Tabla4[#All],$M$7,FALSE),"no encontrado") -> 28637290 | O50: HECTOR | T50: 10 | AA50: 10
A51: MARC | B51: MARC@gmail.com | C51: COLOMBIA | D51: Sector Real | E51: =IFERROR(VLOOKUP(A51,bdbuscarv!$A$1:$M$101,5,FALSE),"no encontrado") -> Inversión | F51: =IFERROR(VLOOKUP(A51,Tabla4[#All],6,FALSE),"no encontrado") -> Socio de proyecto | G51: =IFERROR(VLOOKUP(A51,Tabla4[#All],7,FALSE),"no encontrado") -> SI | H51: =IFERROR(VLOOKUP(A51,Tabla4[#All],8,FALSE),"no encontrado") -> 6 | I51: =IFERROR(VLOOKUP(A51,Tabla4[#All],9,FALSE),"no encontrado") -> 10 | J51: =IFERROR(VLOOKUP(A51,Tabla4[#All],$J$7,FALSE),"no encontrado") -> 30000000 | K51: =IFERROR(VLOOKUP(A51,Tabla4[#All],$K$7,FALSE),"no encontrado") -> 52442860 | L51: =IFERROR(VLOOKUP(A51,Tabla4[#All],$L$7,FALSE),"no encontrado") -> 2659881 | M51: =IFERROR(VLOOKUP(A51,Tabla4[#All],$M$7,FALSE),"no encontrado") -> 80287314 | O51: HUGO | T51: 8 | AA51: 8
A52: ROBERTO | B52: ROBERTO@gmail.com | C52: COLOMBIA | D52: Tecnología | E52: =IFERROR(VLOOKUP(A52,bdbuscarv!$A$1:$M$101,5,FALSE),"no encontrado") -> Inversión | F52: =IFERROR(VLOOKUP(A52,Tabla4[#All],6,FALSE),"no encontrado") -> Socio de proyecto | G52: =IFERROR(VLOOKUP(A52,Tabla4[#All],7,FALSE),"no encontrado") -> SI | H52: =IFERROR(VLOOKUP(A52,Tabla4[#All],8,FALSE),"no encontrado") -> 7 | I52: =IFERROR(VLOOKUP(A52,Tabla4[#All],9,FALSE),"no encontrado") -> 5 | J52: =IFERROR(VLOOKUP(A52,Tabla4[#All],$J$7,FALSE),"no encontrado") -> 10000000 | K52: =IFERROR(VLOOKUP(A52,Tabla4[#All],$K$7,FALSE),"no encontrado") -> 96199053 | L52: =IFERROR(VLOOKUP(A52,Tabla4[#All],$L$7,FALSE),"no encontrado") -> 31746355 | M52: =IFERROR(VLOOKUP(A52,Tabla4[#All],$M$7,FALSE),"no encontrado") -> 80063468 | O52: IGNACIO | T52: 7 | AA52: 7
A53: CARLOS | B53: CARLOS@gmail.com | C53: COLOMBIA | D53: Tecnología | E53: =IFERROR(VLOOKUP(A53,bdbuscarv!$A$1:$M$101,5,FALSE),"no encontrado") -> Inversión | F53: =IFERROR(VLOOKUP(A53,Tabla4[#All],6,FALSE),"no encontrado") -> Socio de proyecto | G53: =IFERROR(VLOOKUP(A53,Tabla4[#All],7,FALSE),"no encontrado") -> NO | H53: =IFERROR(VLOOKUP(A53,Tabla4[#All],8,FALSE),"no encontrado") -> 5 | I53: =IFERROR(VLOOKUP(A53,Tabla4[#All],9,FALSE),"no encontrado") -> 7 | J53: =IFERROR(VLOOKUP(A53,Tabla4[#All],$J$7,FALSE),"no encontrado") -> 1000000 | K53: =IFERROR(VLOOKUP(A53,Tabla4[#All],$K$7,FALSE),"no encontrado") -> 71783742 | L53: =IFERROR(VLOOKUP(A53,Tabla4[#All],$L$7,FALSE),"no encontrado") -> 64667814 | M53: =IFERROR(VLOOKUP(A53,Tabla4[#All],$M$7,FALSE),"no encontrado") -> 70653180 | O53: ISAAC | T53: 10 | AA53: 10
A54: JOEL | B54: JOEL@gmail.com | C54: COLOMBIA | D54: Sector Real | E54: =IFERROR(VLOOKUP(A54,bdbuscarv!$A$1:$M$101,5,FALSE),"no encontrado") -> Inversión | F54: =IFERROR(VLOOKUP(A54,Tabla4[#All],6,FALSE),"no encontrado") -> Socio de proyecto | G54: =IFERROR(VLOOKUP(A54,Tabla4[#All],7,FALSE),"no encontrado") -> NO | H54: =IFERROR(VLOOKUP(A54,Tabla4[#All],8,FALSE),"no encontrado") -> 3 | I54: =IFERROR(VLOOKUP(A54,Tabla4[#All],9,FALSE),"no encontrado") -> 8 | J54: =IFERROR(VLOOKUP(A54,Tabla4[#All],$J$7,FALSE),"no encontrado") -> 90000000 | K54: =IFERROR(VLOOKUP(A54,Tabla4[#All],$K$7,FALSE),"no encontrado") -> 94913746 | L54: =IFERROR(VLOOKUP(A54,Tabla4[#All],$L$7,FALSE),"no encontrado") -> 74083223 | M54: =IFERROR(VLOOKUP(A54,Tabla4[#All],$M$7,FALSE),"no encontrado") -> 31617670 | O54: ISMAEL | R54: 9 | AA54: 9
A55: MARIANO | B55: MARIANO@gmail.com | C55: COLOMBIA | D55: Sector Real | E55: =IFERROR(VLOOKUP(A55,bdbuscarv!$A$1:$M$101,5,FALSE),"no encontrado") -> Trabajo | F55: =IFERROR(VLOOKUP(A55,Tabla4[#All],6,FALSE),"no encontrado") -> Ofreciendo trabajo | G55: =IFERROR(VLOOKUP(A55,Tabla4[#All],7,FALSE),"no encontrado") -> NO | H55: =IFERROR(VLOOKUP(A55,Tabla4[#All],8,FALSE),"no encontrado") -> 7 | I55: =IFERROR(VLOOKUP(A55,Tabla4[#All],9,FALSE),"no encontrado") -> 9 | J55: =IFERROR(VLOOKUP(A55,Tabla4[#All],$J$7,FALSE),"no encontrado") -> $ - | K55: =IFERROR(VLOOKUP(A55,Tabla4[#All],$K$7,FALSE),"no encontrado") -> $ - | L55: =IFERROR(VLOOKUP(A55,Tabla4[#All],$L$7,FALSE),"no encontrado") -> 67753952 | M55: =IFERROR(VLOOKUP(A55,Tabla4[#All],$M$7,FALSE),"no encontrado") -> 77205812 | O55: IVAN | T55: 6 | AA55: 6
A56: OSCAR | B56: OSCAR@gmail.com | C56: BRASIL | D56: Tecnología | E56: =IFERROR(VLOOKUP(A56,bdbuscarv!$A$1:$M$101,5,FALSE),"no encontrado") -> Inversión | F56: =IFERROR(VLOOKUP(A56,Tabla4[#All],6,FALSE),"no encontrado") -> Socio de proyecto | G56: =IFERROR(VLOOKUP(A56,Tabla4[#All],7,FALSE),"no encontrado") -> SI | H56: =IFERROR(VLOOKUP(A56,Tabla4[#All],8,FALSE),"no encontrado") -> 5 | I56: =IFERROR(VLOOKUP(A56,Tabla4[#All],9,FALSE),"no encontrado") -> 6 | J56: =IFERROR(VLOOKUP(A56,Tabla4[#All],$J$7,FALSE),"no encontrado") -> 30000000 | K56: =IFERROR(VLOOKUP(A56,Tabla4[#All],$K$7,FALSE),"no encontrado") -> 33477783 | L56: =IFERROR(VLOOKUP(A56,Tabla4[#All],$L$7,FALSE),"no encontrado") -> $ - | M56: =IFERROR(VLOOKUP(A56,Tabla4[#All],$M$7,FALSE),"no encontrado") -> 27651635 | O56: JAIME | T56: 10 | AA56: 10
A57: ALEXANDER | B57: ALEXANDER@gmail.com | C57: COLOMBIA | D57: Construcción | E57: =IFERROR(VLOOKUP(A57,bdbuscarv!$A$1:$M$101,5,FALSE),"no encontrado") -> Inversión | F57: =IFERROR(VLOOKUP(A57,Tabla4[#All],6,FALSE),"no encontrado") -> Socio capitalista | G57: =IFERROR(VLOOKUP(A57,Tabla4[#All],7,FALSE),"no encontrado") -> SI | H57: =IFERROR(VLOOKUP(A57,Tabla4[#All],8,FALSE),"no encontrado") -> 9 | I57: =IFERROR(VLOOKUP(A57,Tabla4[#All],9,FALSE),"no encontrado") -> 9 | J57: =IFERROR(VLOOKUP(A57,Tabla4[#All],$J$7,FALSE),"no encontrado") -> 50000000 | K57: =IFERROR(VLOOKUP(A57,Tabla4[#All],$K$7,FALSE),"no encontrado") -> 2702447 | L57: =IFERROR(VLOOKUP(A57,Tabla4[#All],$L$7,FALSE),"no encontrado") -> $ - | M57: =IFERROR(VLOOKUP(A57,Tabla4[#All],$M$7,FALSE),"no encontrado") -> 44671760 | O57: JAVIER | Q57: 5 | AA57: 5
A58: BORJA | B58: BORJA@gmail.com | C58: ECUADOR | D58: Tecnología | E58: =IFERROR(VLOOKUP(A58,bdbuscarv!$A$1:$M$101,5,FALSE),"no encontrado") -> Inversión | F58: =IFERROR(VLOOKUP(A58,Tabla4[#All],6,FALSE),"no encontrado") -> Socio capitalista | G58: =IFERROR(VLOOKUP(A58,Tabla4[#All],7,FALSE),"no encontrado") -> NO | H58: =IFERROR(VLOOKUP(A58,Tabla4[#All],8,FALSE),"no encontrado") -> 6 | I58: =IFERROR(VLOOKUP(A58,Tabla4[#All],9,FALSE),"no encontrado") -> 8 | J58: =IFERROR(VLOOKUP(A58,Tabla4[#All],$J$7,FALSE),"no encontrado") -> 50000000 | K58: =IFERROR(VLOOKUP(A58,Tabla4[#All],$K$7,FALSE),"no encontrado") -> 70787848 | L58: =IFERROR(VLOOKUP(A58,Tabla4[#All],$L$7,FALSE),"no encontrado") -> 33368202 | M58: =IFERROR(VLOOKUP(A58,Tabla4[#All],$M$7,FALSE),"no encontrado") -> 43277527 | O58: JESUS | V58: 10 | AA58: 10
A59: RAUL | B59: RAUL@gmail.com | C59: BRASIL | D59: Tecnología | E59: =IFERROR(VLOOKUP(A59,bdbuscarv!$A$1:$M$101,5,FALSE),"no encontrado") -> Trabajo | F59: =IFERROR(VLOOKUP(A59,Tabla4[#All],6,FALSE),"no encontrado") -> Ofreciendo trabajo | G59: =IFERROR(VLOOKUP(A59,Tabla4[#All],7,FALSE),"no encontrado") -> SI | H59: =IFERROR(VLOOKUP(A59,Tabla4[#All],8,FALSE),"no encontrado") -> 7 | I59: =IFERROR(VLOOKUP(A59,Tabla4[#All],9,FALSE),"no encontrado") -> 5 | J59: =IFERROR(VLOOKUP(A59,Tabla4[#All],$J$7,FALSE),"no encontrado") -> $ - | K59: =IFERROR(VLOOKUP(A59,Tabla4[#All],$K$7,FALSE),"no encontrado") -> $ - | L59: =IFERROR(VLOOKUP(A59,Tabla4[#All],$L$7,FALSE),"no encontrado") -> 46563396 | M59: =IFERROR(VLOOKUP(A59,Tabla4[#All],$M$7,FALSE),"no encontrado") -> 63313535 | O59: JOAN | T59: 7 | AA59: 7
A60: ALEX | B60: ALEX@gmail.com | C60: URUGUAY | D60: Tecnología | E60: =IFERROR(VLOOKUP(A60,bdbuscarv!$A$1:$M$101,5,FALSE),"no encontrado") -> Inversión | F60: =IFERROR(VLOOKUP(A60,Tabla4[#All],6,FALSE),"no encontrado") -> Socio capitalista | G60: =IFERROR(VLOOKUP(A60,Tabla4[#All],7,FALSE),"no encontrado") -> NO | H60: =IFERROR(VLOOKUP(A60,Tabla4[#All],8,FALSE),"no encontrado") -> 5 | I60: =IFERROR(VLOOKUP(A60,Tabla4[#All],9,FALSE),"no encontrado") -> 6 | J60: =IFERROR(VLOOKUP(A60,Tabla4[#All],$J$7,FALSE),"no encontrado") -> 20000000 | K60: =IFERROR(VLOOKUP(A60,Tabla4[#All],$K$7,FALSE),"no encontrado") -> 40064620 | L60: =IFERROR(VLOOKUP(A60,Tabla4[#All],$L$7,FALSE),"no encontrado") -> 98137438 | M60: =IFERROR(VLOOKUP(A60,Tabla4[#All],$M$7,FALSE),"no encontrado") -> $ - | O60: JOAQUIN | T60: 7 | AA60: 7
A61: IVAN | B61: IVAN@gmail.com | C61: COLOMBIA | D61: Tecnología | E61: =IFERROR(VLOOKUP(A61,bdbuscarv!$A$1:$M$101,5,FALSE),"no encontrado") -> Inversión | F61: =IFERROR(VLOOKUP(A61,Tabla4[#All],6,FALSE),"no encontrado") -> Socio de proyecto | G61: =IFERROR(VLOOKUP(A61,Tabla4[#All],7,FALSE),"no encontrado") -> NO | H61: =IFERROR(VLOOKUP(A61,Tabla4[#All],8,FALSE),"no encontrado") -> 4 | I61: =IFERROR(VLOOKUP(A61,Tabla4[#All],9,FALSE),"no encontrado") -> 6 | J61: =IFERROR(VLOOKUP(A61,Tabla4[#All],$J$7,FALSE),"no encontrado") -> 30000000 | K61: =IFERROR(VLOOKUP(A61,Tabla4[#All],$K$7,FALSE),"no encontrado") -> 45289360 | L61: =IFERROR(VLOOKUP(A61,Tabla4[#All],$L$7,FALSE),"no encontrado") -> $ - | M61: =IFERROR(VLOOKUP(A61,Tabla4[#All],$M$7,FALSE),"no encontrado") -> 46980526 | O61: JOEL | T61: 8 | AA61: 8
A62: SAMUEL | B62: SAMUEL@gmail.com | C62: COLOMBIA | D62: Sector Real | E62: =IFERROR(VLOOKUP(A62,bdbuscarv!$A$1:$M$101,5,FALSE),"no encontrado") -> Inversión | F62: =IFERROR(VLOOKUP(A62,Tabla4[#All],6,FALSE),"no encontrado") -> Socio de proyecto | G62: =IFERROR(VLOOKUP(A62,Tabla4[#All],7,FALSE),"no encontrado") -> NO | H62: =IFERROR(VLOOKUP(A62,Tabla4[#All],8,FALSE),"no encontrado") -> 7 | I62: =IFERROR(VLOOKUP(A62,Tabla4[#All],9,FALSE),"no encontrado") -> 5 | J62: =IFERROR(VLOOKUP(A62,Tabla4[#All],$J$7,FALSE),"no encontrado") -> 30000000 | K62: =IFERROR(VLOOKUP(A62,Tabla4[#All],$K$7,FALSE),"no encontrado") -> 34397393 | L62: =IFERROR(VLOOKUP(A62,Tabla4[#All],$L$7,FALSE),"no encontrado") -> 72192037 | M62: =IFERROR(VLOOKUP(A62,Tabla4[#All],$M$7,FALSE),"no encontrado") -> 21247716 | O62: JONATHAN | T62: 7 | AA62: 7
A63: ANDRES | B63: ANDRES@gmail.com | C63: COLOMBIA | D63: Tecnología | E63: =IFERROR(VLOOKUP(A63,bdbuscarv!$A$1:$M$101,5,FALSE),"no encontrado") -> Trabajo | F63: =IFERROR(VLOOKUP(A63,Tabla4[#All],6,FALSE),"no encontrado") -> Buscando trabajo | G63: =IFERROR(VLOOKUP(A63,Tabla4[#All],7,FALSE),"no encontrado") -> SI | H63: =IFERROR(VLOOKUP(A63,Tabla4[#All],8,FALSE),"no encontrado") -> 3 | I63: =IFERROR(VLOOKUP(A63,Tabla4[#All],9,FALSE),"no encontrado") -> 9 | J63: =IFERROR(VLOOKUP(A63,Tabla4[#All],$J$7,FALSE),"no encontrado") -> $ - | K63: =IFERROR(VLOOKUP(A63,Tabla4[#All],$K$7,FALSE),"no encontrado") -> $ - | L63: =IFERROR(VLOOKUP(A63,Tabla4[#All],$L$7,FALSE),"no encontrado") -> 69870077 | M63: =IFERROR(VLOOKUP(A63,Tabla4[#All],$M$7,FALSE),"no encontrado") -> 98441580 | O63: JORDI | T63: 6 | AA63: 6
A64: NORA | B64: NORA@gmail.com | C64: CHILE | D64: Sector Real | E64: =IFERROR(VLOOKUP(A64,bdbuscarv!$A$1:$M$101,5,FALSE),"no encontrado") -> Inversión | F64: =IFERROR(VLOOKUP(A64,Tabla4[#All],6,FALSE),"no encontrado") -> Socio de proyecto | G64: =IFERROR(VLOOKUP(A64,Tabla4[#All],7,FALSE),"no encontrado") -> NO | H64: =IFERROR(VLOOKUP(A64,Tabla4[#All],8,FALSE),"no encontrado") -> 3 | I64: =IFERROR(VLOOKUP(A64,Tabla4[#All],9,FALSE),"no encontrado") -> 6 | J64: =IFERROR(VLOOKUP(A64,Tabla4[#All],$J$7,FALSE),"no encontrado") -> 1000000 | K64: =IFERROR(VLOOKUP(A64,Tabla4[#All],$K$7,FALSE),"no encontrado") -> 34126405 | L64: =IFERROR(VLOOKUP(A64,Tabla4[#All],$L$7,FALSE),"no encontrado") -> 88265167 | M64: =IFERROR(VLOOKUP(A64,Tabla4[#All],$M$7,FALSE),"no encontrado") -> 56002928 | O64: JORGE | S64: 9 | AA64: 9
A65: ANDRÉS | B65: ANDRÉS@gmail.com | C65: COLOMBIA | D65: Tecnología | E65: =IFERROR(VLOOKUP(A65,bdbuscarv!$A$1:$M$101,5,FALSE),"no encontrado") -> Inversión | F65: =IFERROR(VLOOKUP(A65,Tabla4[#All],6,FALSE),"no encontrado") -> Socio capitalista | G65: =IFERROR(VLOOKUP(A65,Tabla4[#All],7,FALSE),"no encontrado") -> NO | H65: =IFERROR(VLOOKUP(A65,Tabla4[#All],8,FALSE),"no encontrado") -> 7 | I65: =IFERROR(VLOOKUP(A65,Tabla4[#All],9,FALSE),"no encontrado") -> 10 | J65: =IFERROR(VLOOKUP(A65,Tabla4[#All],$J$7,FALSE),"no encontrado") -> 1000000 | K65: =IFERROR(VLOOKUP(A65,Tabla4[#All],$K$7,FALSE),"no encontrado") -> 53008255 | L65: =IFERROR(VLOOKUP(A65,Tabla4[#All],$L$7,FALSE),"no encontrado") -> 46917910 | M65: =IFERROR(VLOOKUP(A65,Tabla4[#All],$M$7,FALSE),"no encontrado") -> 47557281 | O65: JOSE | T65: 6 | AA65: 6
A66: CRISTIAN | B66: CRISTIAN@gmail.com | C66: COLOMBIA | D66: Tecnología | E66: =IFERROR(VLOOKUP(A66,bdbuscarv!$A$1:$M$101,5,FALSE),"no encontrado") -> Trabajo | F66: =IFERROR(VLOOKUP(A66,Tabla4[#All],6,FALSE),"no encontrado") -> Buscando trabajo | G66: =IFERROR(VLOOKUP(A66,Tabla4[#All],7,FALSE),"no encontrado") -> NO | H66: =IFERROR(VLOOKUP(A66,Tabla4[#All],8,FALSE),"no encontrado") -> 5 | I66: =IFERROR(VLOOKUP(A66,Tabla4[#All],9,FALSE),"no encontrado") -> 9 | J66: =IFERROR(VLOOKUP(A66,Tabla4[#All],$J$7,FALSE),"no encontrado") -> $ - | K66: =IFERROR(VLOOKUP(A66,Tabla4[#All],$K$7,FALSE),"no encontrado") -> $ - | L66: =IFERROR(VLOOKUP(A66,Tabla4[#All],$L$7,FALSE),"no encontrado") -> $ - | M66: =IFERROR(VLOOKUP(A66,Tabla4[#All],$M$7,FALSE),"no encontrado") -> 22675260 | O66: JOSEP | T66: 9 | AA66: 9
A67: JAVIER | B67: JAVIER@gmail.com | C67: BOLIVIA | D67: Tecnología | E67: =IFERROR(VLOOKUP(A67,bdbuscarv!$A$1:$M$101,5,FALSE),"no encontrado") -> Inversión | F67: =IFERROR(VLOOKUP(A67,Tabla4[#All],6,FALSE),"no encontrado") -> Socio capitalista | G67: =IFERROR(VLOOKUP(A67,Tabla4[#All],7,FALSE),"no encontrado") -> NO | H67: =IFERROR(VLOOKUP(A67,Tabla4[#All],8,FALSE),"no encontrado") -> 9 | I67: =IFERROR(VLOOKUP(A67,Tabla4[#All],9,FALSE),"no encontrado") -> 5 | J67: =IFERROR(VLOOKUP(A67,Tabla4[#All],$J$7,FALSE),"no encontrado") -> 100000000 | K67: =IFERROR(VLOOKUP(A67,Tabla4[#All],$K$7,FALSE),"no encontrado") -> 94688720 | L67: =IFERROR(VLOOKUP(A67,Tabla4[#All],$L$7,FALSE),"no encontrado") -> 86323763 | M67: =IFERROR(VLOOKUP(A67,Tabla4[#All],$M$7,FALSE),"no encontrado") -> 20929788 | O67: JUAN | T67: 7 | AA67: 7
A68: DOMINGO | B68: DOMINGO@gmail.com | C68: COLOMBIA | D68: Educación | E68: =IFERROR(VLOOKUP(A68,bdbuscarv!$A$1:$M$101,5,FALSE),"no encontrado") -> Conocimiento | F68: =IFERROR(VLOOKUP(A68,Tabla4[#All],6,FALSE),"no encontrado") -> Académico | G68: =IFERROR(VLOOKUP(A68,Tabla4[#All],7,FALSE),"no encontrado") -> NO | H68: =IFERROR(VLOOKUP(A68,Tabla4[#All],8,FALSE),"no encontrado") -> 4 | I68: =IFERROR(VLOOKUP(A68,Tabla4[#All],9,FALSE),"no encontrado") -> 8 | J68: =IFERROR(VLOOKUP(A68,Tabla4[#All],$J$7,FALSE),"no encontrado") -> $ - | K68: =IFERROR(VLOOKUP(A68,Tabla4[#All],$K$7,FALSE),"no encontrado") -> $ - | L68: =IFERROR(VLOOKUP(A68,Tabla4[#All],$L$7,FALSE),"no encontrado") -> 96750826 | M68: =IFERROR(VLOOKUP(A68,Tabla4[#All],$M$7,FALSE),"no encontrado") -> 31435769 | O68: JUAN PABLO | T68: 10 | AA68: 10
A69: NICOLAS | B69: NICOLAS@gmail.com | C69: COLOMBIA | D69: Sector Real | E69: =IFERROR(VLOOKUP(A69,bdbuscarv!$A$1:$M$101,5,FALSE),"no encontrado") -> Inversión | F69: =IFERROR(VLOOKUP(A69,Tabla4[#All],6,FALSE),"no encontrado") -> Socio capitalista | G69: =IFERROR(VLOOKUP(A69,Tabla4[#All],7,FALSE),"no encontrado") -> NO | H69: =IFERROR(VLOOKUP(A69,Tabla4[#All],8,FALSE),"no encontrado") -> 5 | I69: =IFERROR(VLOOKUP(A69,Tabla4[#All],9,FALSE),"no encontrado") -> 10 | J69: =IFERROR(VLOOKUP(A69,Tabla4[#All],$J$7,FALSE),"no encontrado") -> 10000000 | K69: =IFERROR(VLOOKUP(A69,Tabla4[#All],$K$7,FALSE),"no encontrado") -> 89686683 | L69: =IFERROR(VLOOKUP(A69,Tabla4[#All],$L$7,FALSE),"no encontrado") -> 62448793 | M69: =IFERROR(VLOOKUP(A69,Tabla4[#All],$M$7,FALSE),"no encontrado") -> 26812600 | O69: JULIAN | T69: 9 | AA69: 9
A70: HECTOR | B70: HECTOR@gmail.com | C70: COLOMBIA | D70: Tecnología | E70: =IFERROR(VLOOKUP(A70,bdbuscarv!$A$1:$M$101,5,FALSE),"no encontrado") -> Inversión | F70: =IFERROR(VLOOKUP(A70,Tabla4[#All],6,FALSE),"no encontrado") -> Socio de proyecto | G70: =IFERROR(VLOOKUP(A70,Tabla4[#All],7,FALSE),"no encontrado") -> NO | H70: =IFERROR(VLOOKUP(A70,Tabla4[#All],8,FALSE),"no encontrado") -> 3 | I70: =IFERROR(VLOOKUP(A70,Tabla4[#All],9,FALSE),"no encontrado") -> 10 | J70: =IFERROR(VLOOKUP(A70,Tabla4[#All],$J$7,FALSE),"no encontrado") -> 30000000 | K70: =IFERROR(VLOOKUP(A70,Tabla4[#All],$K$7,FALSE),"no encontrado") -> 32890743 | L70: =IFERROR(VLOOKUP(A70,Tabla4[#All],$L$7,FALSE),"no encontrado") -> $ - | M70: =IFERROR(VLOOKUP(A70,Tabla4[#All],$M$7,FALSE),"no encontrado") -> 39864620 | O70: LEONEL | T70: 10 | AA70: 10
A71: RICARDO | B71: RICARDO@gmail.com | C71: COLOMBIA | D71: Sector Real | E71: =IFERROR(VLOOKUP(A71,bdbuscarv!$A$1:$M$101,5,FALSE),"no encontrado") -> Inversión | F71: =IFERROR(VLOOKUP(A71,Tabla4[#All],6,FALSE),"no encontrado") -> Socio capitalista | G71: =IFERROR(VLOOKUP(A71,Tabla4[#All],7,FALSE),"no encontrado") -> NO | H71: =IFERROR(VLOOKUP(A71,Tabla4[#All],8,FALSE),"no encontrado") -> 3 | I71: =IFERROR(VLOOKUP(A71,Tabla4[#All],9,FALSE),"no encontrado") -> 10 | J71: =IFERROR(VLOOKUP(A71,Tabla4[#All],$J$7,FALSE),"no encontrado") -> 10000000 | K71: =IFERROR(VLOOKUP(A71,Tabla4[#All],$K$7,FALSE),"no encontrado") -> 32370896 | L71: =IFERROR(VLOOKUP(A71,Tabla4[#All],$L$7,FALSE),"no encontrado") -> 96066942 | M71: =IFERROR(VLOOKUP(A71,Tabla4[#All],$M$7,FALSE),"no encontrado") -> 3767736 | O71: LORENZO | T71: 10 | AA71: 10
A72: ALBERTO | B72: ALBERTO@gmail.com | C72: COLOMBIA | D72: Sector Real | E72: =IFERROR(VLOOKUP(A72,bdbuscarv!$A$1:$M$101,5,FALSE),"no encontrado") -> Trabajo | F72: =IFERROR(VLOOKUP(A72,Tabla4[#All],6,FALSE),"no encontrado") -> Ofreciendo trabajo | G72: =IFERROR(VLOOKUP(A72,Tabla4[#All],7,FALSE),"no encontrado") -> NO | H72: =IFERROR(VLOOKUP(A72,Tabla4[#All],8,FALSE),"no encontrado") -> 5 | I72: =IFERROR(VLOOKUP(A72,Tabla4[#All],9,FALSE),"no encontrado") -> 5 | J72: =IFERROR(VLOOKUP(A72,Tabla4[#All],$J$7,FALSE),"no encontrado") -> $ - | K72: =IFERROR(VLOOKUP(A72,Tabla4[#All],$K$7,FALSE),"no encontrado") -> $ - | L72: =IFERROR(VLOOKUP(A72,Tabla4[#All],$L$7,FALSE),"no encontrado") -> 24514428 | M72: =IFERROR(VLOOKUP(A72,Tabla4[#All],$M$7,FALSE),"no encontrado") -> 27890231 | O72: LUCAS | T72: 9 | AA72: 9
A73: RUBEN | B73: RUBEN@gmail.com | C73: COLOMBIA | D73: Tecnología | E73: =IFERROR(VLOOKUP(A73,bdbuscarv!$A$1:$M$101,5,FALSE),"no encontrado") -> Inversión | F73: =IFERROR(VLOOKUP(A73,Tabla4[#All],6,FALSE),"no encontrado") -> Socio capitalista | G73: =IFERROR(VLOOKUP(A73,Tabla4[#All],7,FALSE),"no encontrado") -> SI | H73: =IFERROR(VLOOKUP(A73,Tabla4[#All],8,FALSE),"no encontrado") -> 7 | I73: =IFERROR(VLOOKUP(A73,Tabla4[#All],9,FALSE),"no encontrado") -> 7 | J73: =IFERROR(VLOOKUP(A73,Tabla4[#All],$J$7,FALSE),"no encontrado") -> 10000000 | K73: =IFERROR(VLOOKUP(A73,Tabla4[#All],$K$7,FALSE),"no encontrado") -> 31953589 | L73: =IFERROR(VLOOKUP(A73,Tabla4[#All],$L$7,FALSE),"no encontrado") -> 40068224 | M73: =IFERROR(VLOOKUP(A73,Tabla4[#All],$M$7,FALSE),"no encontrado") -> 80951038 | O73: LUIS | Z73: 5 | AA73: 5
A74: SEBASTIAN | B74: SEBASTIAN@gmail.com | C74: COLOMBIA | D74: Tecnología | E74: =IFERROR(VLOOKUP(A74,bdbuscarv!$A$1:$M$101,5,FALSE),"no encontrado") -> Inversión | F74: =IFERROR(VLOOKUP(A74,Tabla4[#All],6,FALSE),"no encontrado") -> Socio capitalista | G74: =IFERROR(VLOOKUP(A74,Tabla4[#All],7,FALSE),"no encontrado") -> NO | H74: =IFERROR(VLOOKUP(A74,Tabla4[#All],8,FALSE),"no encontrado") -> 7 | I74: =IFERROR(VLOOKUP(A74,Tabla4[#All],9,FALSE),"no encontrado") -> 5 | J74: =IFERROR(VLOOKUP(A74,Tabla4[#All],$J$7,FALSE),"no encontrado") -> 50000000 | K74: =IFERROR(VLOOKUP(A74,Tabla4[#All],$K$7,FALSE),"no encontrado") -> 78205651 | L74: =IFERROR(VLOOKUP(A74,Tabla4[#All],$L$7,FALSE),"no encontrado") -> 62381180 | M74: =IFERROR(VLOOKUP(A74,Tabla4[#All],$M$7,FALSE),"no encontrado") -> 6508585 | O74: MANUEL | P74: 5 | AA74: 5
A75: MOHAMED | B75: MOHAMED@gmail.com | C75: COLOMBIA | D75: Agroindustrial | E75: =IFERROR(VLOOKUP(A75,bdbuscarv!$A$1:$M$101,5,FALSE),"no encontrado") -> Trabajo | F75: =IFERROR(VLOOKUP(A75,Tabla4[#All],6,FALSE),"no encontrado") -> Buscando trabajo | G75: =IFERROR(VLOOKUP(A75,Tabla4[#All],7,FALSE),"no encontrado") -> NO | H75: =IFERROR(VLOOKUP(A75,Tabla4[#All],8,FALSE),"no encontrado") -> 5 | I75: =IFERROR(VLOOKUP(A75,Tabla4[#All],9,FALSE),"no encontrado") -> 4 | J75: =IFERROR(VLOOKUP(A75,Tabla4[#All],$J$7,FALSE),"no encontrado") -> $ - | K75: =IFERROR(VLOOKUP(A75,Tabla4[#All],$K$7,FALSE),"no encontrado") -> $ - | L75: =IFERROR(VLOOKUP(A75,Tabla4[#All],$L$7,FALSE),"no encontrado") -> 34584522 | M75: =IFERROR(VLOOKUP(A75,Tabla4[#All],$M$7,FALSE),"no encontrado") -> $ - | O75: MARC | T75: 10 | AA75: 10
A76: MARCO | B76: MARCO@gmail.com | C76: PERU | D76: Tecnología | E76: =IFERROR(VLOOKUP(A76,bdbuscarv!$A$1:$M$101,5,FALSE),"no encontrado") -> Conocimiento | F76: =IFERROR(VLOOKUP(A76,Tabla4[#All],6,FALSE),"no encontrado") -> Otro tipo | G76: =IFERROR(VLOOKUP(A76,Tabla4[#All],7,FALSE),"no encontrado") -> NO | H76: =IFERROR(VLOOKUP(A76,Tabla4[#All],8,FALSE),"no encontrado") -> 7 | I76: =IFERROR(VLOOKUP(A76,Tabla4[#All],9,FALSE),"no encontrado") -> 7 | J76: =IFERROR(VLOOKUP(A76,Tabla4[#All],$J$7,FALSE),"no encontrado") -> $ - | K76: =IFERROR(VLOOKUP(A76,Tabla4[#All],$K$7,FALSE),"no encontrado") -> $ - | L76: =IFERROR(VLOOKUP(A76,Tabla4[#All],$L$7,FALSE),"no encontrado") -> 76942676 | M76: =IFERROR(VLOOKUP(A76,Tabla4[#All],$M$7,FALSE),"no encontrado") -> 74216691 | O76: MARCO | X76: 7 | AA76: 7
A77: SERGIO | B77: SERGIO@gmail.com | C77: BRASIL | D77: Sector Real | E77: =IFERROR(VLOOKUP(A77,bdbuscarv!$A$1:$M$101,5,FALSE),"no encontrado") -> Inversión | F77: =IFERROR(VLOOKUP(A77,Tabla4[#All],6,FALSE),"no encontrado") -> Socio de proyecto | G77: =IFERROR(VLOOKUP(A77,Tabla4[#All],7,FALSE),"no encontrado") -> SI | H77: =IFERROR(VLOOKUP(A77,Tabla4[#All],8,FALSE),"no encontrado") -> 8 | I77: =IFERROR(VLOOKUP(A77,Tabla4[#All],9,FALSE),"no encontrado") -> 9 | J77: =IFERROR(VLOOKUP(A77,Tabla4[#All],$J$7,FALSE),"no encontrado") -> 5000000 | K77: =IFERROR(VLOOKUP(A77,Tabla4[#All],$K$7,FALSE),"no encontrado") -> 70270294 | L77: =IFERROR(VLOOKUP(A77,Tabla4[#All],$L$7,FALSE),"no encontrado") -> 19588762 | M77: =IFERROR(VLOOKUP(A77,Tabla4[#All],$M$7,FALSE),"no encontrado") -> 78634577 | O77: MARCOS | R77: 5 | AA77: 5
A78: RAMON | B78: RAMON@gmail.com | C78: COLOMBIA | D78: Agroindustrial | E78: =IFERROR(VLOOKUP(A78,bdbuscarv!$A$1:$M$101,5,FALSE),"no encontrado") -> Trabajo | F78: =IFERROR(VLOOKUP(A78,Tabla4[#All],6,FALSE),"no encontrado") -> Buscando trabajo | G78: =IFERROR(VLOOKUP(A78,Tabla4[#All],7,FALSE),"no encontrado") -> NO | H78: =IFERROR(VLOOKUP(A78,Tabla4[#All],8,FALSE),"no encontrado") -> 3 | I78: =IFERROR(VLOOKUP(A78,Tabla4[#All],9,FALSE),"no encontrado") -> 5 | J78: =IFERROR(VLOOKUP(A78,Tabla4[#All],$J$7,FALSE),"no encontrado") -> $ - | K78: =IFERROR(VLOOKUP(A78,Tabla4[#All],$K$7,FALSE),"no encontrado") -> $ - | L78: =IFERROR(VLOOKUP(A78,Tabla4[#All],$L$7,FALSE),"no encontrado") -> 85955846 | M78: =IFERROR(VLOOKUP(A78,Tabla4[#All],$M$7,FALSE),"no encontrado") -> 25891596 | O78: MARIA | T78: 9 | AA78: 9
A79: GREGORIO | B79: GREGORIO@gmail.com | C79: COLOMBIA | D79: Agroindustrial | E79: =IFERROR(VLOOKUP(A79,bdbuscarv!$A$1:$M$101,5,FALSE),"no encontrado") -> Inversión | F79: =IFERROR(VLOOKUP(A79,Tabla4[#All],6,FALSE),"no encontrado") -> Socio de proyecto | G79: =IFERROR(VLOOKUP(A79,Tabla4[#All],7,FALSE),"no encontrado") -> SI | H79: =IFERROR(VLOOKUP(A79,Tabla4[#All],8,FALSE),"no encontrado") -> 8 | I79: =IFERROR(VLOOKUP(A79,Tabla4[#All],9,FALSE),"no encontrado") -> 10 | J79: =IFERROR(VLOOKUP(A79,Tabla4[#All],$J$7,FALSE),"no encontrado") -> 20000000 | K79: =IFERROR(VLOOKUP(A79,Tabla4[#All],$K$7,FALSE),"no encontrado") -> 62745331 | L79: =IFERROR(VLOOKUP(A79,Tabla4[#All],$L$7,FALSE),"no encontrado") -> 39843357 | M79: =IFERROR(VLOOKUP(A79,Tabla4[#All],$M$7,FALSE),"no encontrado") -> 64840967 | O79: MARIA MÓNICA | T79: 10 | AA79: 10
A80: JOAN | B80: JOAN@gmail.com | C80: COLOMBIA | D80: Tecnología | E80: =IFERROR(VLOOKUP(A80,bdbuscarv!$A$1:$M$101,5,FALSE),"no encontrado") -> Trabajo | F80: =IFERROR(VLOOKUP(A80,Tabla4[#All],6,FALSE),"no encontrado") -> Ofreciendo trabajo | G80: =IFERROR(VLOOKUP(A80,Tabla4[#All],7,FALSE),"no encontrado") -> NO | H80: =IFERROR(VLOOKUP(A80,Tabla4[#All],8,FALSE),"no encontrado") -> 5 | I80: =IFERROR(VLOOKUP(A80,Tabla4[#All],9,FALSE),"no encontrado") -> 7 | J80: =IFERROR(VLOOKUP(A80,Tabla4[#All],$J$7,FALSE),"no encontrado") -> $ - | K80: =IFERROR(VLOOKUP(A80,Tabla4[#All],$K$7,FALSE),"no encontrado") -> $ - | L80: =IFERROR(VLOOKUP(A80,Tabla4[#All],$L$7,FALSE),"no encontrado") -> 82583322 | M80: =IFERROR(VLOOKUP(A80,Tabla4[#All],$M$7,FALSE),"no encontrado") -> 809058 | O80: MARIANO | T80: 9 | AA80: 9
A81: ALFONSO | B81: ALFONSO@gmail.com | C81: COLOMBIA | D81: Tecnología | E81: =IFERROR(VLOOKUP(A81,bdbuscarv!$A$1:$M$101,5,FALSE),"no encontrado") -> Inversión | F81: =IFERROR(VLOOKUP(A81,Tabla4[#All],6,FALSE),"no encontrado") -> Socio de proyecto | G81: =IFERROR(VLOOKUP(A81,Tabla4[#All],7,FALSE),"no encontrado") -> SI | H81: =IFERROR(VLOOKUP(A81,Tabla4[#All],8,FALSE),"no encontrado") -> 6 | I81: =IFERROR(VLOOKUP(A81,Tabla4[#All],9,FALSE),"no encontrado") -> 6 | J81: =IFERROR(VLOOKUP(A81,Tabla4[#All],$J$7,FALSE),"no encontrado") -> 10000000 | K81: =IFERROR(VLOOKUP(A81,Tabla4[#All],$K$7,FALSE),"no encontrado") -> 59890317 | L81: =IFERROR(VLOOKUP(A81,Tabla4[#All],$L$7,FALSE),"no encontrado") -> 42451842 | M81: =IFERROR(VLOOKUP(A81,Tabla4[#All],$M$7,FALSE),"no encontrado") -> $ - | O81: MARIO | T81: 7 | AA81: 7
A82: GUILLERMO | B82: GUILLERMO@gmail.com | C82: COLOMBIA | D82: Agroindustrial | E82: =IFERROR(VLOOKUP(A82,bdbuscarv!$A$1:$M$101,5,FALSE),"no encontrado") -> Inversión | F82: =IFERROR(VLOOKUP(A82,Tabla4[#All],6,FALSE),"no encontrado") -> Socio capitalista | G82: =IFERROR(VLOOKUP(A82,Tabla4[#All],7,FALSE),"no encontrado") -> NO | H82: =IFERROR(VLOOKUP(A82,Tabla4[#All],8,FALSE),"no encontrado") -> 3 | I82: =IFERROR(VLOOKUP(A82,Tabla4[#All],9,FALSE),"no encontrado") -> 6 | J82: =IFERROR(VLOOKUP(A82,Tabla4[#All],$J$7,FALSE),"no encontrado") -> 10000000 | K82: =IFERROR(VLOOKUP(A82,Tabla4[#All],$K$7,FALSE),"no encontrado") -> 97449662 | L82: =IFERROR(VLOOKUP(A82,Tabla4[#All],$L$7,FALSE),"no encontrado") -> 49624160 | M82: =IFERROR(VLOOKUP(A82,Tabla4[#All],$M$7,FALSE),"no encontrado") -> 17854677 | O82: MARTIN | T82: 5 | AA82: 5
A83: CHRISTIAN | B83: CHRISTIAN@gmail.com | C83: COLOMBIA | D83: Construcción | E83: =IFERROR(VLOOKUP(A83,bdbuscarv!$A$1:$M$101,5,FALSE),"no encontrado") -> Trabajo | F83: =IFERROR(VLOOKUP(A83,Tabla4[#All],6,FALSE),"no encontrado") -> Ofreciendo trabajo | G83: =IFERROR(VLOOKUP(A83,Tabla4[#All],7,FALSE),"no encontrado") -> NO | H83: =IFERROR(VLOOKUP(A83,Tabla4[#All],8,FALSE),"no encontrado") -> 8 | I83: =IFERROR(VLOOKUP(A83,Tabla4[#All],9,FALSE),"no encontrado") -> 10 | J83: =IFERROR(VLOOKUP(A83,Tabla4[#All],$J$7,FALSE),"no encontrado") -> $ - | K83: =IFERROR(VLOOKUP(A83,Tabla4[#All],$K$7,FALSE),"no encontrado") -> $ - | L83: =IFERROR(VLOOKUP(A83,Tabla4[#All],$L$7,FALSE),"no encontrado") -> 44422091 | M83: =IFERROR(VLOOKUP(A83,Tabla4[#All],$M$7,FALSE),"no encontrado") -> 8898260 | O83: MATEO | Y83: 7 | AA83: 7
A84: MATEO | B84: MATEO@gmail.com | C84: URUGUAY | D84: Tecnología | E84: =IFERROR(VLOOKUP(A84,bdbuscarv!$A$1:$M$101,5,FALSE),"no encontrado") -> Trabajo | F84: =IFERROR(VLOOKUP(A84,Tabla4[#All],6,FALSE),"no encontrado") -> Buscando trabajo | G84: =IFERROR(VLOOKUP(A84,Tabla4[#All],7,FALSE),"no encontrado") -> NO | H84: =IFERROR(VLOOKUP(A84,Tabla4[#All],8,FALSE),"no encontrado") -> 5 | I84: =IFERROR(VLOOKUP(A84,Tabla4[#All],9,FALSE),"no encontrado") -> 7 | J84: =IFERROR(VLOOKUP(A84,Tabla4[#All],$J$7,FALSE),"no encontrado") -> $ - | K84: =IFERROR(VLOOKUP(A84,Tabla4[#All],$K$7,FALSE),"no encontrado") -> $ - | L84: =IFERROR(VLOOKUP(A84,Tabla4[#All],$L$7,FALSE),"no encontrado") -> $ - | M84: =IFERROR(VLOOKUP(A84,Tabla4[#All],$M$7,FALSE),"no encontrado") -> 63436099 | O84: MIGUEL | T84: 10 | AA84: 10
A85: JULIAN | B85: JULIAN@gmail.com | C85: COLOMBIA | D85: Tecnología | E85: =IFERROR(VLOOKUP(A85,bdbuscarv!$A$1:$M$101,5,FALSE),"no encontrado") -> Inversión | F85: =IFERROR(VLOOKUP(A85,Tabla4[#All],6,FALSE),"no encontrado") -> Socio capitalista | G85: =IFERROR(VLOOKUP(A85,Tabla4[#All],7,FALSE),"no encontrado") -> SI | H85: =IFERROR(VLOOKUP(A85,Tabla4[#All],8,FALSE),"no encontrado") -> 8 | I85: =IFERROR(VLOOKUP(A85,Tabla4[#All],9,FALSE),"no encontrado") -> 9 | J85: =IFERROR(VLOOKUP(A85,Tabla4[#All],$J$7,FALSE),"no encontrado") -> 10000000 | K85: =IFERROR(VLOOKUP(A85,Tabla4[#All],$K$7,FALSE),"no encontrado") -> 99989764 | L85: =IFERROR(VLOOKUP(A85,Tabla4[#All],$L$7,FALSE),"no encontrado") -> 8030175 | M85: =IFERROR(VLOOKUP(A85,Tabla4[#All],$M$7,FALSE),"no encontrado") -> 37676206 | O85: MOHAMED | T85: 4 | AA85: 4
A86: CRISTOBAL | B86: CRISTOBAL@gmail.com | C86: COLOMBIA | D86: Tecnología | E86: =IFERROR(VLOOKUP(A86,bdbuscarv!$A$1:$M$101,5,FALSE),"no encontrado") -> Trabajo | F86: =IFERROR(VLOOKUP(A86,Tabla4[#All],6,FALSE),"no encontrado") -> Buscando trabajo | G86: =IFERROR(VLOOKUP(A86,Tabla4[#All],7,FALSE),"no encontrado") -> SI | H86: =IFERROR(VLOOKUP(A86,Tabla4[#All],8,FALSE),"no encontrado") -> 4 | I86: =IFERROR(VLOOKUP(A86,Tabla4[#All],9,FALSE),"no encontrado") -> 5 | J86: =IFERROR(VLOOKUP(A86,Tabla4[#All],$J$7,FALSE),"no encontrado") -> $ - | K86: =IFERROR(VLOOKUP(A86,Tabla4[#All],$K$7,FALSE),"no encontrado") -> $ - | L86: =IFERROR(VLOOKUP(A86,Tabla4[#All],$L$7,FALSE),"no encontrado") -> 12862402 | M86: =IFERROR(VLOOKUP(A86,Tabla4[#All],$M$7,FALSE),"no encontrado") -> 68922404 | O86: NICOLAS | T86: 10 | AA86: 10
A87: RODRIGO | B87: RODRIGO@gmail.com | C87: COLOMBIA | D87: Sector Real | E87: =IFERROR(VLOOKUP(A87,bdbuscarv!$A$1:$M$101,5,FALSE),"no encontrado") -> Trabajo | F87: =IFERROR(VLOOKUP(A87,Tabla4[#All],6,FALSE),"no encontrado") -> Buscando trabajo | G87: =IFERROR(VLOOKUP(A87,Tabla4[#All],7,FALSE),"no encontrado") -> SI | H87: =IFERROR(VLOOKUP(A87,Tabla4[#All],8,FALSE),"no encontrado") -> 9 | I87: =IFERROR(VLOOKUP(A87,Tabla4[#All],9,FALSE),"no encontrado") -> 9 | J87: =IFERROR(VLOOKUP(A87,Tabla4[#All],$J$7,FALSE),"no encontrado") -> $ - | K87: =IFERROR(VLOOKUP(A87,Tabla4[#All],$K$7,FALSE),"no encontrado") -> $ - | L87: =IFERROR(VLOOKUP(A87,Tabla4[#All],$L$7,FALSE),"no encontrado") -> 46914257 | M87: =IFERROR(VLOOKUP(A87,Tabla4[#All],$M$7,FALSE),"no encontrado") -> 43734508 | O87: NORA | S87: 6 | AA87: 6
A88: JESUS | B88: JESUS@gmail.com | C88: OTRO PAÍS DEL MUNDO | D88: Educación | E88: =IFERROR(VLOOKUP(A88,bdbuscarv!$A$1:$M$101,5,FALSE),"no encontrado") -> Conocimiento | F88: =IFERROR(VLOOKUP(A88,Tabla4[#All],6,FALSE),"no encontrado") -> Académico | G88: =IFERROR(VLOOKUP(A88,Tabla4[#All],7,FALSE),"no encontrado") -> NO | H88: =IFERROR(VLOOKUP(A88,Tabla4[#All],8,FALSE),"no encontrado") -> 6 | I88: =IFERROR(VLOOKUP(A88,Tabla4[#All],9,FALSE),"no encontrado") -> 10 | J88: =IFERROR(VLOOKUP(A88,Tabla4[#All],$J$7,FALSE),"no encontrado") -> $ - | K88: =IFERROR(VLOOKUP(A88,Tabla4[#All],$K$7,FALSE),"no encontrado") -> $ - | L88: =IFERROR(VLOOKUP(A88,Tabla4[#All],$L$7,FALSE),"no encontrado") -> 95212463 | M88: =IFERROR(VLOOKUP(A88,Tabla4[#All],$M$7,FALSE),"no encontrado") -> $ - | O88: OSCAR | R88: 6 | AA88: 6
A89: JORGE | B89: JORGE@gmail.com | C89: CHILE | D89: Tecnología | E89: =IFERROR(VLOOKUP(A89,bdbuscarv!$A$1:$M$101,5,FALSE),"no encontrado") -> Inversión | F89: =IFERROR(VLOOKUP(A89,Tabla4[#All],6,FALSE),"no encontrado") -> Socio capitalista | G89: =IFERROR(VLOOKUP(A89,Tabla4[#All],7,FALSE),"no encontrado") -> NO | H89: =IFERROR(VLOOKUP(A89,Tabla4[#All],8,FALSE),"no encontrado") -> 3 | I89: =IFERROR(VLOOKUP(A89,Tabla4[#All],9,FALSE),"no encontrado") -> 9 | J89: =IFERROR(VLOOKUP(A89,Tabla4[#All],$J$7,FALSE),"no encontrado") -> 5000000 | K89: =IFERROR(VLOOKUP(A89,Tabla4[#All],$K$7,FALSE),"no encontrado") -> 32915397 | L89: =IFERROR(VLOOKUP(A89,Tabla4[#All],$L$7,FALSE),"no encontrado") -> 74493461 | M89: =IFERROR(VLOOKUP(A89,Tabla4[#All],$M$7,FALSE),"no encontrado") -> 151779 | O89: PABLO | T89: 10 | AA89: 10
A90: JULIO | B90: JULIO@gmail.com | C90: COLOMBIA | D90: Sector Real | E90: =IFERROR(VLOOKUP(A90,bdbuscarv!$A$1:$M$101,5,FALSE),"no encontrado") -> Trabajo | F90: =IFERROR(VLOOKUP(A90,Tabla4[#All],6,FALSE),"no encontrado") -> Buscando trabajo | G90: =IFERROR(VLOOKUP(A90,Tabla4[#All],7,FALSE),"no encontrado") -> NO | H90: =IFERROR(VLOOKUP(A90,Tabla4[#All],8,FALSE),"no encontrado") -> 3 | I90: =IFERROR(VLOOKUP(A90,Tabla4[#All],9,FALSE),"no encontrado") -> 7 | J90: =IFERROR(VLOOKUP(A90,Tabla4[#All],$J$7,FALSE),"no encontrado") -> $ - | K90: =IFERROR(VLOOKUP(A90,Tabla4[#All],$K$7,FALSE),"no encontrado") -> $ - | L90: =IFERROR(VLOOKUP(A90,Tabla4[#All],$L$7,FALSE),"no encontrado") -> 43223505 | M90: =IFERROR(VLOOKUP(A90,Tabla4[#All],$M$7,FALSE),"no encontrado") -> $ - | O90: PEDRO | S90: 5 | AA90: 5
A91: MARIA MÓNICA | B91: MARIA MÓNICA@gmail.com | C91: COLOMBIA | D91: Tecnología | E91: =IFERROR(VLOOKUP(A91,bdbuscarv!$A$1:$M$101,5,FALSE),"no encontrado") -> Trabajo | F91: =IFERROR(VLOOKUP(A91,Tabla4[#All],6,FALSE),"no encontrado") -> Buscando trabajo | G91: =IFERROR(VLOOKUP(A91,Tabla4[#All],7,FALSE),"no encontrado") -> NO | H91: =IFERROR(VLOOKUP(A91,Tabla4[#All],8,FALSE),"no encontrado") -> 7 | I91: =IFERROR(VLOOKUP(A91,Tabla4[#All],9,FALSE),"no encontrado") -> 10 | J91: =IFERROR(VLOOKUP(A91,Tabla4[#All],$J$7,FALSE),"no encontrado") -> $ - | K91: =IFERROR(VLOOKUP(A91,Tabla4[#All],$K$7,FALSE),"no encontrado") -> $ - | L91: =IFERROR(VLOOKUP(A91,Tabla4[#All],$L$7,FALSE),"no encontrado") -> 14141858 | M91: =IFERROR(VLOOKUP(A91,Tabla4[#All],$M$7,FALSE),"no encontrado") -> 87162317 | O91: RAFAEL | T91: 8 | AA91: 8
A92: IGNACIO | B92: IGNACIO@gmail.com | C92: COLOMBIA | D92: Tecnología | E92: =IFERROR(VLOOKUP(A92,bdbuscarv!$A$1:$M$101,5,FALSE),"no encontrado") -> Trabajo | F92: =IFERROR(VLOOKUP(A92,Tabla4[#All],6,FALSE),"no encontrado") -> Buscando trabajo | G92: =IFERROR(VLOOKUP(A92,Tabla4[#All],7,FALSE),"no encontrado") -> NO | H92: =IFERROR(VLOOKUP(A92,Tabla4[#All],8,FALSE),"no encontrado") -> 3 | I92: =IFERROR(VLOOKUP(A92,Tabla4[#All],9,FALSE),"no encontrado") -> 7 | J92: =IFERROR(VLOOKUP(A92,Tabla4[#All],$J$7,FALSE),"no encontrado") -> $ - | K92: =IFERROR(VLOOKUP(A92,Tabla4[#All],$K$7,FALSE),"no encontrado") -> $ - | L92: =IFERROR(VLOOKUP(A92,Tabla4[#All],$L$7,FALSE),"no encontrado") -> 29525162 | M92: =IFERROR(VLOOKUP(A92,Tabla4[#All],$M$7,FALSE),"no encontrado") -> $ - | O92: RAMON | T92: 5 | AA92: 5
A93: GABRIEL | B93: GABRIEL@gmail.com | C93: COLOMBIA | D93: Tecnología | E93: =IFERROR(VLOOKUP(A93,bdbuscarv!$A$1:$M$101,5,FALSE),"no encontrado") -> Trabajo | F93: =IFERROR(VLOOKUP(A93,Tabla4[#All],6,FALSE),"no encontrado") -> Ofreciendo trabajo | G93: =IFERROR(VLOOKUP(A93,Tabla4[#All],7,FALSE),"no encontrado") -> SI | H93: =IFERROR(VLOOKUP(A93,Tabla4[#All],8,FALSE),"no encontrado") -> 7 | I93: =IFERROR(VLOOKUP(A93,Tabla4[#All],9,FALSE),"no encontrado") -> 4 | J93: =IFERROR(VLOOKUP(A93,Tabla4[#All],$J$7,FALSE),"no encontrado") -> $ - | K93: =IFERROR(VLOOKUP(A93,Tabla4[#All],$K$7,FALSE),"no encontrado") -> $ - | L93: =IFERROR(VLOOKUP(A93,Tabla4[#All],$L$7,FALSE),"no encontrado") -> 29366791 | M93: =IFERROR(VLOOKUP(A93,Tabla4[#All],$M$7,FALSE),"no encontrado") -> 89805774 | O93: RAUL | R93: 5 | AA93: 5
A94: MARTIN | B94: MARTIN@gmail.com | C94: COLOMBIA | D94: Tecnología | E94: =IFERROR(VLOOKUP(A94,bdbuscarv!$A$1:$M$101,5,FALSE),"no encontrado") -> Trabajo | F94: =IFERROR(VLOOKUP(A94,Tabla4[#All],6,FALSE),"no encontrado") -> Buscando trabajo | G94: =IFERROR(VLOOKUP(A94,Tabla4[#All],7,FALSE),"no encontrado") -> SI | H94: =IFERROR(VLOOKUP(A94,Tabla4[#All],8,FALSE),"no encontrado") -> 9 | I94: =IFERROR(VLOOKUP(A94,Tabla4[#All],9,FALSE),"no encontrado") -> 5 | J94: =IFERROR(VLOOKUP(A94,Tabla4[#All],$J$7,FALSE),"no encontrado") -> $ - | K94: =IFERROR(VLOOKUP(A94,Tabla4[#All],$K$7,FALSE),"no encontrado") -> $ - | L94: =IFERROR(VLOOKUP(A94,Tabla4[#All],$L$7,FALSE),"no encontrado") -> 73195518 | M94: =IFERROR(VLOOKUP(A94,Tabla4[#All],$M$7,FALSE),"no encontrado") -> 10695678 | O94: RICARDO | T94: 10 | AA94: 10
